Workbook

Sheet META
A1: META | E1: PRODUÇÃO NO PERÍODO | L1: VENDA ESTIMADA PARA OUTUBRO
A2: Amanda | B2: 4500
A3: Bruna | B3: 18000
A4: Camila | B4: 15000 | E4: Corretores | F4: Valor | G4: Meta | H4: Valor que falta | I4: % Atual | J4: % Que falta | L4: Corretores | M4: Valor | N4: Meta | O4: Valor que falta | P4: % Atual | Q4: % Que falta
A5: Darlin | B5: 3000 | E5: Amanda Facundo | F5: =IFERROR( SUMIFS('Amanda Facundo'!$H:$H, 'Amanda Facundo'!$G:$G, "Plano Fechado", 'Amanda Facundo'!$I:$I, ">=01/10/2025", 'Amanda Facundo'!$I:$I, "<01/11/2025") + SUMIFS('Amanda Facundo'!$H:$H, 'Amanda Facundo'!$G:$G, "Aguardando Pagamento", 'Amanda Facundo'!$I:$I, ">=01/10/2025", 'Amanda Facundo'!$I:$I, "<01/11/2025") + SUMIFS('Amanda Facundo'!$H:$H, 'Amanda Facundo'!$G:$G, "Em Análise", 'Amanda Facundo'!$I:$I, ">=01/10/2025", 'Amanda Facundo'!$I:$I, "<01/11/2025"), "") -> 686.05 | G5: 4500 | H5: =G5-F5 -> 3813.95 | I5: =F5/G5 -> 0.15245556 | J5: =H5/G5 -> 0.84754444 | L5: Amanda Facundo | M5: =IFERROR( SUMIFS('Amanda Facundo'!$H:$H, 'Amanda Facundo'!$G:$G, "Plano Fechado", 'Amanda Facundo'!$L:$L, "=10") + SUMIFS('Amanda Facundo'!$H:$H, 'Amanda Facundo'!$G:$G, "Aguardando Pagamento", 'Amanda Facundo'!$L:$L, "=10") + SUMIFS('Amanda Facundo'!$H:$H, 'Amanda Facundo'!$G:$G, "Em Análise", 'Amanda Facundo'!$L:$L, "=10"), "") -> 686.05 | N5: 4500 | O5: =N5-M5 -> 3813.95 | P5: =M5/N5 -> 0.15245556 | Q5: =O5/N5 -> 0.84754444
A6: Diogo | B6: 15000 | E6: Bruna Mamedes | F6: =IFERROR( SUMIFS('Bruna Mamedes'!$H:$H, 'Bruna Mamedes'!$G:$G, "Plano Fechado", 'Bruna Mamedes'!$I:$I, ">=01/10/2025", 'Bruna Mamedes'!$I:$I, "<01/11/2025") + SUMIFS('Bruna Mamedes'!$H:$H, 'Bruna Mamedes'!$G:$G, "Aguardando Pagamento", 'Bruna Mamedes'!$I:$I, ">=01/10/2025", 'Bruna Mamedes'!$I:$I, "<01/11/2025") + SUMIFS('Bruna Mamedes'!$H:$H, 'Bruna Mamedes'!$G:$G, "Em Análise", 'Bruna Mamedes'!$I:$I, ">=01/10/2025", 'Bruna Mamedes'!$I:$I, "<01/11/2025"), "") -> 18083.72 | G6: 18000 | H6: =G6-F6 -> -83.72 | I6: =F6/G6 -> 1.0046511 | J6: =H6/G6 -> -0.0046511111 | L6: Bruna Mamedes | M6: =IFERROR( SUMIFS('Bruna Mamedes'!$H:$H, 'Bruna Mamedes'!$G:$G, "Plano Fechado", 'Bruna Mamedes'!$L:$L, "=10") + SUMIFS('Bruna Mamedes'!$H:$H, 'Bruna Mamedes'!$G:$G, "Aguardando Pagamento", 'Bruna Mamedes'!$L:$L, "=10") + SUMIFS('Bruna Mamedes'!$H:$H, 'Bruna Mamedes'!$G:$G, "Em Análise", 'Bruna Mamedes'!$L:$L, "=10"), "") -> 17622.55 | N6: 18000 | O6: =N6-M6 -> 377.45 | P6: =M6/N6 -> 0.97903056 | Q6: =O6/N6 -> 0.020969444
A7: Externo | B7: 18000 | E7: Camila Adão | F7: =IFERROR( SUMIFS('Camila Adão'!$H:$H, 'Camila Adão'!$G:$G, "Plano Fechado", 'Camila Adão'!$I:$I, ">=01/10/2025", 'Camila Adão'!$I:$I, "<01/11/2025") + SUMIFS('Camila Adão'!$H:$H, 'Camila Adão'!$G:$G, "Aguardando Pagamento", 'Camila Adão'!$I:$I, ">=01/10/2025", 'Camila Adão'!$I:$I, "<01/11/2025") + SUMIFS('Camila Adão'!$H:$H, 'Camila Adão'!$G:$G, "Em Análise", 'Camila Adão'!$I:$I, ">=01/10/2025", 'Camila Adão'!$I:$I, "<01/11/2025"), "") -> 18337.98 | G7: 15000 | H7: =G7-F7 -> -3337.98 | I7: =F7/G7 -> 1.222532 | J7: =H7/G7 -> -0.222532 | L7: Camila Adão | M7: =IFERROR( SUMIFS('Camila Adão'!$H:$H, 'Camila Adão'!$G:$G, "Plano Fechado", 'Camila Adão'!$L:$L, "=10") + SUMIFS('Camila Adão'!$H:$H, 'Camila Adão'!$G:$G, "Aguardando Pagamento", 'Camila Adão'!$L:$L, "=10") + SUMIFS('Camila Adão'!$H:$H, 'Camila Adão'!$G:$G, "Em Análise", 'Camila Adão'!$L:$L, "=10"), "") -> 17293.72 | N7: 15000 | O7: =N7-M7 -> -2293.72 | P7: =M7/N7 -> 1.1529147 | Q7: =O7/N7 -> -0.15291467
A8: Maiara | B8: 18000 | E8: Darlin Amorim | F8: =IFERROR( SUMIFS('Darlin Amorim'!$H:$H, 'Darlin Amorim'!$G:$G, "Plano Fechado", 'Darlin Amorim'!$I:$I, ">=01/10/2025", 'Darlin Amorim'!$I:$I, "<01/11/2025") + SUMIFS('Darlin Amorim'!$H:$H, 'Darlin Amorim'!$G:$G, "Aguardando Pagamento", 'Darlin Amorim'!$I:$I, ">=01/10/2025", 'Darlin Amorim'!$I:$I, "<01/11/2025") + SUMIFS('Darlin Amorim'!$H:$H, 'Darlin Amorim'!$G:$G, "Em Análise", 'Darlin Amorim'!$I:$I, ">=01/10/2025", 'Darlin Amorim'!$I:$I, "<01/11/2025"), "") -> 586 | G8: 3000 | H8: =G8-F8 -> 2414 | I8: =F8/G8 -> 0.19533333 | J8: =H8/G8 -> 0.80466667 | L8: Darlin Amorim | M8: =IFERROR( SUMIFS('Darlin Amorim'!$H:$H, 'Darlin Amorim'!$G:$G, "Plano Fechado", 'Darlin Amorim'!$L:$L, "=10") + SUMIFS('Darlin Amorim'!$H:$H, 'Darlin Amorim'!$G:$G, "Aguardando Pagamento", 'Darlin Amorim'!$L:$L, "=10") + SUMIFS('Darlin Amorim'!$H:$H, 'Darlin Amorim'!$G:$G, "Em Análise", 'Darlin Amorim'!$L:$L, "=10"), "") -> 0 | N8: 3000 | O8: =N8-M8 -> 3000 | P8: =M8/N8 -> 0 | Q8: =O8/N8 -> 1
A9: Marcio | B9: 12000 | E9: Diogo Lima | F9: =IFERROR( SUMIFS('Diogo Lima'!$H:$H, 'Diogo Lima'!$G:$G, "Plano Fechado", 'Diogo Lima'!$I:$I, ">=01/10/2025", 'Diogo Lima'!$I:$I, "<01/11/2025") + SUMIFS('Diogo Lima'!$H:$H, 'Diogo Lima'!$G:$G, "Aguardando Pagamento", 'Diogo Lima'!$I:$I, ">=01/10/2025", 'Diogo Lima'!$I:$I, "<01/11/2025") + SUMIFS('Diogo Lima'!$H:$H, 'Diogo Lima'!$G:$G, "Em Análise", 'Diogo Lima'!$I:$I, ">=01/10/2025", 'Diogo Lima'!$I:$I, "<01/11/2025"), "") -> 9964.09 | G9: 15000 | H9: =G9-F9 -> 5035.91 | I9: =F9/G9 -> 0.66427267 | J9: =H9/G9 -> 0.33572733 | L9: Diogo Lima | M9: =IFERROR( SUMIFS('Diogo Lima'!$H:$H, 'Diogo Lima'!$G:$G, "Plano Fechado", 'Diogo Lima'!$L:$L, "=10") + SUMIFS('Diogo Lima'!$H:$H, 'Diogo Lima'!$G:$G, "Aguardando Pagamento", 'Diogo Lima'!$L:$L, "=10") + SUMIFS('Diogo Lima'!$H:$H, 'Diogo Lima'!$G:$G, "Em Análise", 'Diogo Lima'!$L:$L, "=10"), "") -> 10430.14 | N9: 15000 | O9: =N9-M9 -> 4569.86 | P9: =M9/N9 -> 0.69534267 | Q9: =O9/N9 -> 0.30465733
A10: Roberto | B10: 14000 | E10: Externos | F10: =IFERROR( SUMIFS('Fernando Diamantino'!$H:$H, 'Fernando Diamantino'!$G:$G, "Plano Fechado", 'Fernando Diamantino'!$I:$I, ">=01/10/2025", 'Fernando Diamantino'!$I:$I, "<01/11/2025") + SUMIFS('Fernando Diamantino'!$H:$H, 'Fernando Diamantino'!$G:$G, "Aguardando Pagamento", 'Fernando Diamantino'!$I:$I, ">=01/10/2025", 'Fernando Diamantino'!$I:$I, "<01/11/2025") + SUMIFS('Fernando Diamantino'!$H:$H, 'Fernando Diamantino'!$G:$G, "Em Análise", 'Fernando Diamantino'!$I:$I, ">=01/10/2025", 'Fernando Diamantino'!$I:$I, "<01/11/2025"), "") -> 4445.86 | G10: 18000 | H10: =G10-F10 -> 13554.14 | I10: =F10/G10 -> 0.24699222 | J10: =H10/G10 -> 0.75300778 | L10: Externos | M10: =IFERROR( SUMIFS('Fernando Diamantino'!$H:$H, 'Fernando Diamantino'!$G:$G, "Plano Fechado", 'Fernando Diamantino'!$L:$L, "=10") + SUMIFS('Fernando Diamantino'!$H:$H, 'Fernando Diamantino'!$G:$G, "Aguardando Pagamento", 'Fernando Diamantino'!$L:$L, "=10") + SUMIFS('Fernando Diamantino'!$H:$H, 'Fernando Diamantino'!$G:$G, "Em Análise", 'Fernando Diamantino'!$L:$L, "=10"), "") -> 15547.74 | N10: 18000 | O10: =N10-M10 -> 2452.26 | P10: =M10/N10 -> 0.86376333 | Q10: =O10/N10 -> 0.13623667
A11: Rodrigo | B11: 4000 | E11: Maiara Andrade | F11: =IFERROR( SUMIFS('Maiara Andrade'!$H:$H, 'Maiara Andrade'!$G:$G, "Plano Fechado", 'Maiara Andrade'!$I:$I, ">=01/10/2025", 'Maiara Andrade'!$I:$I, "<01/11/2025") + SUMIFS('Maiara Andrade'!$H:$H, 'Maiara Andrade'!$G:$G, "Aguardando Pagamento", 'Maiara Andrade'!$I:$I, ">=01/10/2025", 'Maiara Andrade'!$I:$I, "<01/11/2025") + SUMIFS('Maiara Andrade'!$H:$H, 'Maiara Andrade'!$G:$G, "Em Análise", 'Maiara Andrade'!$I:$I, ">=01/10/2025", 'Maiara Andrade'!$I:$I, "<01/11/2025"), "") -> 8595.5 | G11: 18000 | H11: =G11-F11 -> 9404.5 | I11: =F11/G11 -> 0.47752778 | J11: =H11/G11 -> 0.52247222 | L11: Maiara Andrade | M11: =IFERROR( SUMIFS('Maiara Andrade'!$H:$H, 'Maiara Andrade'!$G:$G, "Plano Fechado", 'Maiara Andrade'!$L:$L, "=10") + SUMIFS('Maiara Andrade'!$H:$H, 'Maiara Andrade'!$G:$G, "Aguardando Pagamento", 'Maiara Andrade'!$L:$L, "=10") + SUMIFS('Maiara Andrade'!$H:$H, 'Maiara Andrade'!$G:$G, "Em Análise", 'Maiara Andrade'!$L:$L, "=10"), "") -> 18640.44 | N11: 18000 | O11: =N11-M11 -> -640.44 | P11: =M11/N11 -> 1.03558 | Q11: =O11/N11 -> -0.03558
A12: Leandro Nascimento | B12: 2800 | E12: Marcio Jorge | F12: =IFERROR( SUMIFS('Marcio Jorge'!$H:$H, 'Marcio Jorge'!$G:$G, "Plano Fechado", 'Marcio Jorge'!$I:$I, ">=01/10/2025", 'Marcio Jorge'!$I:$I, "<01/11/2025") + SUMIFS('Marcio Jorge'!$H:$H, 'Marcio Jorge'!$G:$G, "Aguardando Pagamento", 'Marcio Jorge'!$I:$I, ">=01/10/2025", 'Marcio Jorge'!$I:$I, "<01/11/2025") + SUMIFS('Marcio Jorge'!$H:$H, 'Marcio Jorge'!$G:$G, "Em Análise", 'Marcio Jorge'!$I:$I, ">=01/10/2025", 'Marcio Jorge'!$I:$I, "<01/11/2025"), "") -> 5283.78 | G12: 12000 | H12: =G12-F12 -> 6716.22 | I12: =F12/G12 -> 0.440315 | J12: =H12/G12 -> 0.559685 | L12: Marcio Jorge | M12: =IFERROR( SUMIFS('Marcio Jorge'!$H:$H, 'Marcio Jorge'!$G:$G, "Plano Fechado", 'Marcio Jorge'!$L:$L, "=10") + SUMIFS('Marcio Jorge'!$H:$H, 'Marcio Jorge'!$G:$G, "Aguardando Pagamento", 'Marcio Jorge'!$L:$L, "=10") + SUMIFS('Marcio Jorge'!$H:$H, 'Marcio Jorge'!$G:$G, "Em Análise", 'Marcio Jorge'!$L:$L, "=10"), "") -> 10794.91 | N12: 12000 | O12: =N12-M12 -> 1205.09 | P12: =M12/N12 -> 0.89957583 | Q12: =O12/N12 -> 0.10042417
A13: Leandro Drumond | B13: 4500 | E13: Lucas Almeida | F13: =IFERROR( SUMIFS('Lucas Almeida'!$H:$H, 'Lucas Almeida'!$G:$G, "Plano Fechado", 'Lucas Almeida'!$I:$I, ">=01/10/2025", 'Lucas Almeida'!$I:$I, "<01/11/2025") + SUMIFS('Lucas Almeida'!$H:$H, 'Lucas Almeida'!$G:$G, "Aguardando Pagamento", 'Lucas Almeida'!$I:$I, ">=01/10/2025", 'Lucas Almeida'!$I:$I, "<01/11/2025") + SUMIFS('Lucas Almeida'!$H:$H, 'Lucas Almeida'!$G:$G, "Em Análise", 'Lucas Almeida'!$I:$I, ">=01/10/2025", 'Lucas Almeida'!$I:$I, "<01/11/2025"), "") -> 0 | G13: 4500 | H13: =G13-F13 -> 4500 | I13: =F13/G13 -> 0 | J13: =H13/G13 -> 1 | L13: Lucas Almeida | M13: =IFERROR( SUMIFS('Lucas Almeida'!$H:$H, 'Lucas Almeida'!$G:$G, "Plano Fechado", 'Lucas Almeida'!$L:$L, "=10") + SUMIFS('Lucas Almeida'!$H:$H, 'Lucas Almeida'!$G:$G, "Aguardando Pagamento", 'Lucas Almeida'!$L:$L, "=10") + SUMIFS('Lucas Almeida'!$H:$H, 'Lucas Almeida'!$G:$G, "Em Análise", 'Lucas Almeida'!$L:$L, "=10"), "") -> 1963.8 | N13: 4500 | O13: =N13-M13 -> 2536.2 | P13: =M13/N13 -> 0.4364 | Q13: =O13/N13 -> 0.5636
A14: Mauro | B14: 2800 | E14: Roberto Ramos | F14: =IFERROR( SUMIFS('Roberto Ramos'!$H:$H, 'Roberto Ramos'!$G:$G, "Plano Fechado", 'Roberto Ramos'!$I:$I, ">=01/10/2025", 'Roberto Ramos'!$I:$I, "<01/11/2025") + SUMIFS('Roberto Ramos'!$H:$H, 'Roberto Ramos'!$G:$G, "Aguardando Pagamento", 'Roberto Ramos'!$I:$I, ">=01/10/2025", 'Roberto Ramos'!$I:$I, "<01/11/2025") + SUMIFS('Roberto Ramos'!$H:$H, 'Roberto Ramos'!$G:$G, "Em Análise", 'Roberto Ramos'!$I:$I, ">=01/10/2025", 'Roberto Ramos'!$I:$I, "<01/11/2025"), "") -> 7459.98 | G14: 14000 | H14: =G14-F14 -> 6540.02 | I14: =F14/G14 -> 0.53285571 | J14: =H14/G14 -> 0.46714429 | L14: Roberto Ramos | M14: =IFERROR( SUMIFS('Roberto Ramos'!$H:$H, 'Roberto Ramos'!$G:$G, "Plano Fechado", 'Roberto Ramos'!$L:$L, "=10") + SUMIFS('Roberto Ramos'!$H:$H, 'Roberto Ramos'!$G:$G, "Aguardando Pagamento", 'Roberto Ramos'!$L:$L, "=10") + SUMIFS('Roberto Ramos'!$H:$H, 'Roberto Ramos'!$G:$G, "Em Análise", 'Roberto Ramos'!$L:$L, "=10"), "") -> 8641.16 | N14: 14000 | O14: =N14-M14 -> 5358.84 | P14: =M14/N14 -> 0.61722571 | Q14: =O14/N14 -> 0.38277429
A15: Lucas | B15: 4500 | E15: Rodrigo Oliviera | F15: =IFERROR( SUMIFS('Rodrigo Oliveira'!$H:$H, 'Rodrigo Oliveira'!$G:$G, "Plano Fechado", 'Rodrigo Oliveira'!$I:$I, ">=01/10/2025", 'Rodrigo Oliveira'!$I:$I, "<01/11/2025") + SUMIFS('Rodrigo Oliveira'!$H:$H, 'Rodrigo Oliveira'!$G:$G, "Aguardando Pagamento", 'Rodrigo Oliveira'!$I:$I, ">=01/10/2025", 'Rodrigo Oliveira'!$I:$I, "<01/11/2025") + SUMIFS('Rodrigo Oliveira'!$H:$H, 'Rodrigo Oliveira'!$G:$G, "Em Análise", 'Rodrigo Oliveira'!$I:$I, ">=01/10/2025", 'Rodrigo Oliveira'!$I:$I, "<01/11/2025"), "") -> 3284.71 | G15: 4000 | H15: =G15-F15 -> 715.29 | I15: =F15/G15 -> 0.8211775 | J15: =H15/G15 -> 0.1788225 | L15: Rodrigo Oliviera | M15: =IFERROR( SUMIFS('Rodrigo Oliveira'!$H:$H, 'Rodrigo Oliveira'!$G:$G, "Plano Fechado", 'Rodrigo Oliveira'!$L:$L, "=10") + SUMIFS('Rodrigo Oliveira'!$H:$H, 'Rodrigo Oliveira'!$G:$G, "Aguardando Pagamento", 'Rodrigo Oliveira'!$L:$L, "=10") + SUMIFS('Rodrigo Oliveira'!$H:$H, 'Rodrigo Oliveira'!$G:$G, "Em Análise", 'Rodrigo Oliveira'!$L:$L, "=10"), "") -> 0 | N15: 4000 | O15: =N15-M15 -> 4000 | P15: =M15/N15 -> 0 | Q15: =O15/N15 -> 1
E16: Leandro Nascimento | F16: =IFERROR( SUMIFS('Leandro Nascimento'!$H:$H, 'Leandro Nascimento'!$G:$G, "Plano Fechado", 'Leandro Nascimento'!$I:$I, ">=01/10/2025", 'Leandro Nascimento'!$I:$I, "<01/11/2025") + SUMIFS('Leandro Nascimento'!$H:$H, 'Leandro Nascimento'!$G:$G, "Aguardando Pagamento", 'Leandro Nascimento'!$I:$I, ">=01/10/2025", 'Leandro Nascimento'!$I:$I, "<01/11/2025") + SUMIFS('Leandro Nascimento'!$H:$H, 'Leandro Nascimento'!$G:$G, "Em Análise", 'Leandro Nascimento'!$I:$I, ">=01/10/2025", 'Leandro Nascimento'!$I:$I, "<01/11/2025"), "") -> 0 | G16: 2800 | H16: =G16-F16 -> 2800 | I16: =F16/G16 -> 0 | J16: =H16/G16 -> 1 | L16: Leandro Nascimento | M16: =IFERROR( SUMIFS('Leandro Nascimento'!$H:$H, 'Leandro Nascimento'!$G:$G, "Plano Fechado", 'Leandro Nascimento'!$L:$L, "=10") + SUMIFS('Leandro Nascimento'!$H:$H, 'Leandro Nascimento'!$G:$G, "Aguardando Pagamento", 'Leandro Nascimento'!$L:$L, "=10") + SUMIFS('Leandro Nascimento'!$H:$H, 'Leandro Nascimento'!$G:$G, "Em Análise", 'Leandro Nascimento'!$L:$L, "=10"), "") -> 1578.6 | N16: 2800 | O16: =N16-M16 -> 1221.4 | P16: =M16/N16 -> 0.56378571 | Q16: =O16/N16 -> 0.43621429
E17: Leandro Drumond | F17: =IFERROR( SUMIFS('Leandro Drumond'!$H:$H, 'Leandro Drumond'!$G:$G, "Plano Fechado", 'Leandro Drumond'!$I:$I, ">=01/10/2025", 'Leandro Drumond'!$I:$I, "<01/11/2025") + SUMIFS('Leandro Drumond'!$H:$H, 'Leandro Drumond'!$G:$G, "Aguardando Pagamento", 'Leandro Drumond'!$I:$I, ">=01/10/2025", 'Leandro Drumond'!$I:$I, "<01/11/2025") + SUMIFS('Leandro Drumond'!$H:$H, 'Leandro Drumond'!$G:$G, "Em Análise", 'Leandro Drumond'!$I:$I, ">=01/10/2025", 'Leandro Drumond'!$I:$I, "<01/11/2025"), "") -> 0 | G17: 4500 | H17: =G17-F17 -> 4500 | I17: =F17/G17 -> 0 | J17: =H17/G17 -> 1 | L17: Leandro Drumond | M17: =IFERROR( SUMIFS('Leandro Drumond'!$H:$H, 'Leandro Drumond'!$G:$G, "Plano Fechado", 'Leandro Drumond'!$L:$L, "=10") + SUMIFS('Leandro Drumond'!$H:$H, 'Leandro Drumond'!$G:$G, "Aguardando Pagamento", 'Leandro Drumond'!$L:$L, "=10") + SUMIFS('Leandro Drumond'!$H:$H, 'Leandro Drumond'!$G:$G, "Em Análise", 'Leandro Drumond'!$L:$L, "=10"), "") -> 0 | N17: 4500 | O17: =N17-M17 -> 4500 | P17: =M17/N17 -> 0 | Q17: =O17/N17 -> 1
E18: Marcelle Marcela | F18: =IFERROR( SUMIFS('Marcelle Marcela'!$H:$H, 'Marcelle Marcela'!$G:$G, "Plano Fechado", 'Marcelle Marcela'!$I:$I, ">=01/10/2025", 'Marcelle Marcela'!$I:$I, "<01/11/2025") + SUMIFS('Marcelle Marcela'!$H:$H, 'Marcelle Marcela'!$G:$G, "Aguardando Pagamento", 'Marcelle Marcela'!$I:$I, ">=01/10/2025", 'Marcelle Marcela'!$I:$I, "<01/11/2025") + SUMIFS('Marcelle Marcela'!$H:$H, 'Marcelle Marcela'!$G:$G, "Em Análise", 'Marcelle Marcela'!$I:$I, ">=01/10/2025", 'Marcelle Marcela'!$I:$I, "<01/11/2025"), "") -> 0 | G18: 2800 | H18: =G18-F18 -> 2800 | I18: =F18/G18 -> 0 | J18: =H18/G18 -> 1 | L18: Marcelle Marcela | M18: =IFERROR( SUMIFS('Marcelle Marcela'!$H:$H, 'Marcelle Marcela'!$G:$G, "Plano Fechado", 'Marcelle Marcela'!$L:$L, "=10") + SUMIFS('Marcelle Marcela'!$H:$H, 'Marcelle Marcela'!$G:$G, "Aguardando Pagamento", 'Marcelle Marcela'!$L:$L, "=10") + SUMIFS('Marcelle Marcela'!$H:$H, 'Marcelle Marcela'!$G:$G, "Em Análise", 'Marcelle Marcela'!$L:$L, "=10"), "") -> 0 | N18: 2800 | O18: =N18-M18 -> 2800 | P18: =M18/N18 -> 0 | Q18: =O18/N18 -> 1
E21: TOTAL | F21: =SUM(F5:F18) -> 76727.67 | G21: =SUM(G5:G18) -> 136100 | H21: =SUM(H5:H18) -> 59372.33 | I21: =AVERAGE(I5:I18) -> 0.41129378 | J21: =AVERAGE(J5:J18) -> 0.58870622 | L21: TOTAL | M21: =SUM(M5:M18) -> 103199.11 | N21: =SUM(N5:N18) -> 136100 | O21: =SUM(O5:O18) -> 32900.89 | P21: =AVERAGE(P5:P18) -> 0.528291 | Q21: =AVERAGE(Q5:Q18) -> 0.471709
A26: VENDA FECHADA PARA OUTUBRO | H26: VENDA EM ANÁLISE PARA OUTUBRO | O26: VENDA À QUITAÇÃO PARA OUTUBRO
A29: Corretores | B29: Valor | C29: Meta | D29: Valor que falta | E29: % Atual | F29: % Que falta | H29: Corretores | I29: Valor | J29: Meta | K29: Valor que falta | L29: % Atual | M29: % Que falta | O29: Corretores | P29: Valor | Q29: Meta | R29: Valor que falta | S29: % Atual | T29: % Que falta
A30: Amanda Facundo | B30: =IFERROR( SUMIFS('Amanda Facundo'!$H:$H, 'Amanda Facundo'!$G:$G, "Plano Fechado", 'Amanda Facundo'!$L:$L, "=10"), "") -> 686.05 | C30: 4500 | D30: =C30-B30 -> 3813.95 | E30: =B30/C30 -> 0.15245556 | F30: =D30/C30 -> 0.84754444 | H30: Amanda Facundo | I30: =IFERROR( SUMIFS('Amanda Facundo'!$H:$H, 'Amanda Facundo'!$G:$G, "Em Análise", 'Amanda Facundo'!$L:$L, "=10"), "") -> 0 | J30: 4500 | K30: =J30-I30 -> 4500 | L30: =I30/J30 -> 0 | M30: =K30/J30 -> 1 | O30: Amanda Facundo | P30: =IFERROR( SUMIFS('Amanda Facundo'!$H:$H, 'Amanda Facundo'!$G:$G, "Aguardando Pagamento", 'Amanda Facundo'!$L:$L, "=10"), "") -> 0 | Q30: 4500 | R30: =Q30-P30 -> 4500 | S30: =P30/Q30 -> 0 | T30: =R30/Q30 -> 1
A31: Bruna Mamedes | B31: =IFERROR( SUMIFS('Bruna Mamedes'!$H:$H, 'Bruna Mamedes'!$G:$G, "Plano Fechado", 'Bruna Mamedes'!$L:$L, "=10"), "") -> 12816.45 | C31: 18000 | D31: =C31-B31 -> 5183.55 | E31: =B31/C31 -> 0.712025 | F31: =D31/C31 -> 0.287975 | H31: Bruna Mamedes | I31: =IFERROR( SUMIFS('Bruna Mamedes'!$H:$H, 'Bruna Mamedes'!$G:$G, "Em Análise", 'Bruna Mamedes'!$L:$L, "=10"), "") -> 4806.1 | J31: 18000 | K31: =J31-I31 -> 13193.9 | L31: =I31/J31 -> 0.26700556 | M31: =K31/J31 -> 0.73299444 | O31: Bruna Mamedes | P31: =IFERROR( SUMIFS('Bruna Mamedes'!$H:$H, 'Bruna Mamedes'!$G:$G, "Aguardando Pagamento", 'Bruna Mamedes'!$L:$L, "=10"), "") -> 0 | Q31: 18000 | R31: =Q31-P31 -> 18000 | S31: =P31/Q31 -> 0 | T31: =R31/Q31 -> 1
A32: Camila Adão | B32: =IFERROR( SUMIFS('Camila Adão'!$H:$H, 'Camila Adão'!$G:$G, "Plano Fechado", 'Camila Adão'!$L:$L, "=10"), "") -> 17293.72 | C32: 15000 | D32: =C32-B32 -> -2293.72 | E32: =B32/C32 -> 1.1529147 | F32: =D32/C32 -> -0.15291467 | H32: Camila Adão | I32: =IFERROR( SUMIFS('Camila Adão'!$H:$H, 'Camila Adão'!$G:$G, "Em Análise", 'Camila Adão'!$L:$L, "=10"), "") -> 0 | J32: 15000 | K32: =J32-I32 -> 15000 | L32: =I32/J32 -> 0 | M32: =K32/J32 -> 1 | O32: Camila Adão | P32: =IFERROR( SUMIFS('Camila Adão'!$H:$H, 'Camila Adão'!$G:$G, "Aguardando Pagamento", 'Camila Adão'!$L:$L, "=10"), "") -> 0 | Q32: 15000 | R32: =Q32-P32 -> 15000 | S32: =P32/Q32 -> 0 | T32: =R32/Q32 -> 1
A33: Darlin Amorim | B33: =IFERROR( SUMIFS('Darlin Amorim'!$H:$H, 'Darlin Amorim'!$G:$G, "Plano Fechado", 'Darlin Amorim'!$L:$L, "=10"), "") -> 0 | C33: 3000 | D33: =C33-B33 -> 3000 | E33: =B33/C33 -> 0 | F33: =D33/C33 -> 1 | H33: Darlin Amorim | I33: =IFERROR( SUMIFS('Darlin Amorim'!$H:$H, 'Darlin Amorim'!$G:$G, "Em Análise", 'Darlin Amorim'!$L:$L, "=10"), "") -> 0 | J33: 3000 | K33: =J33-I33 -> 3000 | L33: =I33/J33 -> 0 | M33: =K33/J33 -> 1 | O33: Darlin Amorim | P33: =IFERROR( SUMIFS('Darlin Amorim'!$H:$H, 'Darlin Amorim'!$G:$G, "Aguardando Pagamento", 'Darlin Amorim'!$L:$L, "=10"), "") -> 0 | Q33: 3000 | R33: =Q33-P33 -> 3000 | S33: =P33/Q33 -> 0 | T33: =R33/Q33 -> 1
A34: Diogo Lima | B34: =IFERROR( SUMIFS('Diogo Lima'!$H:$H, 'Diogo Lima'!$G:$G, "Plano Fechado", 'Diogo Lima'!$L:$L, "=10"), "") -> 10430.14 | C34: 15000 | D34: =C34-B34 -> 4569.86 | E34: =B34/C34 -> 0.69534267 | F34: =D34/C34 -> 0.30465733 | H34: Diogo Lima | I34: =IFERROR( SUMIFS('Diogo Lima'!$H:$H, 'Diogo Lima'!$G:$G, "Em Análise", 'Diogo Lima'!$L:$L, "=10"), "") -> 0 | J34: 15000 | K34: =J34-I34 -> 15000 | L34: =I34/J34 -> 0 | M34: =K34/J34 -> 1 | O34: Diogo Lima | P34: =IFERROR( SUMIFS('Diogo Lima'!$H:$H, 'Diogo Lima'!$G:$G, "Aguardando Pagamento", 'Diogo Lima'!$L:$L, "=10"), "") -> 0 | Q34: 15000 | R34: =Q34-P34 -> 15000 | S34: =P34/Q34 -> 0 | T34: =R34/Q34 -> 1
A35: Externos | B35: =IFERROR( SUMIFS('Fernando Diamantino'!$H:$H, 'Fernando Diamantino'!$G:$G, "Plano Fechado", 'Fernando Diamantino'!$L:$L, "=10"), "") -> 15547.74 | C35: 18000 | D35: =C35-B35 -> 2452.26 | E35: =B35/C35 -> 0.86376333 | F35: =D35/C35 -> 0.13623667 | H35: Externos | I35: =IFERROR( SUMIFS('Fernando Diamantino'!$H:$H, 'Fernando Diamantino'!$G:$G, "Em Análise", 'Fernando Diamantino'!$L:$L, "=10"), "") -> 0 | J35: 18000 | K35: =J35-I35 -> 18000 | L35: =I35/J35 -> 0 | M35: =K35/J35 -> 1 | O35: Externos | P35: =IFERROR( SUMIFS('Fernando Diamantino'!$H:$H, 'Fernando Diamantino'!$G:$G, "Aguardando Pagamento", 'Fernando Diamantino'!$L:$L, "=10"), "") -> 0 | Q35: 18000 | R35: =Q35-P35 -> 18000 | S35: =P35/Q35 -> 0 | T35: =R35/Q35 -> 1
A36: Maiara Andrade | B36: =IFERROR( SUMIFS('Maiara Andrade'!$H:$H, 'Maiara Andrade'!$G:$G, "Plano Fechado", 'Maiara Andrade'!$L:$L, "=10"), "") -> 12378.43 | C36: 18000 | D36: =C36-B36 -> 5621.57 | E36: =B36/C36 -> 0.68769056 | F36: =D36/C36 -> 0.31230944 | H36: Maiara Andrade | I36: =IFERROR( SUMIFS('Maiara Andrade'!$H:$H, 'Maiara Andrade'!$G:$G, "Em Análise", 'Maiara Andrade'!$L:$L, "=10"), "") -> 6262.01 | J36: 18000 | K36: =J36-I36 -> 11737.99 | L36: =I36/J36 -> 0.34788944 | M36: =K36/J36 -> 0.65211056 | O36: Maiara Andrade | P36: =IFERROR( SUMIFS('Maiara Andrade'!$H:$H, 'Maiara Andrade'!$G:$G, "Aguardando Pagamento", 'Maiara Andrade'!$L:$L, "=10"), "") -> 0 | Q36: 18000 | R36: =Q36-P36 -> 18000 | S36: =P36/Q36 -> 0 | T36: =R36/Q36 -> 1
A37: Marcio Jorge | B37: =IFERROR( SUMIFS('Marcio Jorge'!$H:$H, 'Marcio Jorge'!$G:$G, "Plano Fechado", 'Marcio Jorge'!$L:$L, "=10"), "") -> 10794.91 | C37: 12000 | D37: =C37-B37 -> 1205.09 | E37: =B37/C37 -> 0.89957583 | F37: =D37/C37 -> 0.10042417 | H37: Marcio Jorge | I37: =IFERROR( SUMIFS('Marcio Jorge'!$H:$H, 'Marcio Jorge'!$G:$G, "Em Análise", 'Marcio Jorge'!$L:$L, "=10"), "") -> 0 | J37: 12000 | K37: =J37-I37 -> 12000 | L37: =I37/J37 -> 0 | M37: =K37/J37 -> 1 | O37: Marcio Jorge | P37: =IFERROR( SUMIFS('Marcio Jorge'!$H:$H, 'Marcio Jorge'!$G:$G, "Aguardando Pagamento", 'Marcio Jorge'!$L:$L, "=10"), "") -> 0 | Q37: 12000 | R37: =Q37-P37 -> 12000 | S37: =P37/Q37 -> 0 | T37: =R37/Q37 -> 1
A38: Lucas Almeida | B38: =IFERROR( SUMIFS('Lucas Almeida'!$H:$H, 'Lucas Almeida'!$G:$G, "Plano Fechado", 'Lucas Almeida'!$L:$L, "=10"), "") -> 1963.8 | C38: 4500 | D38: =C38-B38 -> 2536.2 | E38: =B38/C38 -> 0.4364 | F38: =D38/C38 -> 0.5636 | H38: Lucas Almeida | I38: =IFERROR( SUMIFS('Lucas Almeida'!$H:$H, 'Lucas Almeida'!$G:$G, "Em Análise", 'Lucas Almeida'!$L:$L, "=10"), "") -> 0 | J38: 4500 | K38: =J38-I38 -> 4500 | L38: =I38/J38 -> 0 | M38: =K38/J38 -> 1 | O38: Lucas Almeida | P38: =IFERROR( SUMIFS('Lucas Almeida'!$H:$H, 'Lucas Almeida'!$G:$G, "Aguardando Pagamento", 'Lucas Almeida'!$L:$L, "=10"), "") -> 0 | Q38: 4500 | R38: =Q38-P38 -> 4500 | S38: =P38/Q38 -> 0 | T38: =R38/Q38 -> 1
A39: Roberto Ramos | B39: =IFERROR( SUMIFS('Roberto Ramos'!$H:$H, 'Roberto Ramos'!$G:$G, "Plano Fechado", 'Roberto Ramos'!$L:$L, "=10"), "") -> 2273.53 | C39: 14000 | D39: =C39-B39 -> 11726.47 | E39: =B39/C39 -> 0.162395 | F39: =D39/C39 -> 0.837605 | H39: Roberto Ramos | I39: =IFERROR( SUMIFS('Roberto Ramos'!$H:$H, 'Roberto Ramos'!$G:$G, "Em Análise", 'Roberto Ramos'!$L:$L, "=10"), "") -> 2420.14 | J39: 14000 | K39: =J39-I39 -> 11579.86 | L39: =I39/J39 -> 0.17286714 | M39: =K39/J39 -> 0.82713286 | O39: Roberto Ramos | P39: =IFERROR( SUMIFS('Roberto Ramos'!$H:$H, 'Roberto Ramos'!$G:$G, "Aguardando Pagamento", 'Roberto Ramos'!$L:$L, "=10"), "") -> 3947.49 | Q39: 14000 | R39: =Q39-P39 -> 10052.51 | S39: =P39/Q39 -> 0.28196357 | T39: =R39/Q39 -> 0.71803643
A40: Rodrigo Oliviera | B40: =IFERROR( SUMIFS('Rodrigo Oliveira'!$H:$H, 'Rodrigo Oliveira'!$G:$G, "Plano Fechado", 'Rodrigo Oliveira'!$L:$L, "=10"), "") -> 0 | C40: 4000 | D40: =C40-B40 -> 4000 | E40: =B40/C40 -> 0 | F40: =D40/C40 -> 1 | H40: Rodrigo Oliviera | I40: =IFERROR( SUMIFS('Rodrigo Oliveira'!$H:$H, 'Rodrigo Oliveira'!$G:$G, "Em Análise", 'Rodrigo Oliveira'!$L:$L, "=10"), "") -> 0 | J40: 4000 | K40: =J40-I40 -> 4000 | L40: =I40/J40 -> 0 | M40: =K40/J40 -> 1 | O40: Rodrigo Oliviera | P40: =IFERROR( SUMIFS('Rodrigo Oliveira'!$H:$H, 'Rodrigo Oliveira'!$G:$G, "Aguardando Pagamento", 'Rodrigo Oliveira'!$L:$L, "=10"), "") -> 0 | Q40: 4000 | R40: =Q40-P40 -> 4000 | S40: =P40/Q40 -> 0 | T40: =R40/Q40 -> 1
A41: Leandro Nascimento | B41: =IFERROR( SUMIFS('Leandro Nascimento'!$H:$H, 'Leandro Nascimento'!$G:$G, "Plano Fechado", 'Leandro Nascimento'!$L:$L, "=10"), "") -> 0 | C41: 2800 | D41: =C41-B41 -> 2800 | E41: =B41/C41 -> 0 | F41: =D41/C41 -> 1 | H41: Leandro Nascimento | I41: =IFERROR( SUMIFS('Leandro Nascimento'!$H:$H, 'Leandro Nascimento'!$G:$G, "Em Análise", 'Leandro Nascimento'!$L:$L, "=10"), "") -> 1578.6 | J41: 2800 | K41: =J41-I41 -> 1221.4 | L41: =I41/J41 -> 0.56378571 | M41: =K41/J41 -> 0.43621429 | O41: Leandro Nascimento | P41: =IFERROR( SUMIFS('Leandro Nascimento'!$H:$H, 'Leandro Nascimento'!$G:$G, "Aguardando Pagamento", 'Leandro Nascimento'!$L:$L, "=10"), "") -> 0 | Q41: 2800 | R41: =Q41-P41 -> 2800 | S41: =P41/Q41 -> 0 | T41: =R41/Q41 -> 1
A42: Leandro Drumond | B42: =IFERROR( SUMIFS('Leandro Drumond'!$H:$H, 'Leandro Drumond'!$G:$G, "Plano Fechado", 'Leandro Drumond'!$L:$L, "=10"), "") -> 0 | C42: 4500 | D42: =C42-B42 -> 4500 | E42: =B42/C42 -> 0 | F42: =D42/C42 -> 1 | H42: Leandro Drumond | I42: =IFERROR( SUMIFS('Leandro Drumond'!$H:$H, 'Leandro Drumond'!$G:$G, "Em Análise", 'Leandro Drumond'!$L:$L, "=10"), "") -> 0 | J42: 4500 | K42: =J42-I42 -> 4500 | L42: =I42/J42 -> 0 | M42: =K42/J42 -> 1 | O42: Leandro Drumond | P42: =IFERROR( SUMIFS('Leandro Drumond'!$H:$H, 'Leandro Drumond'!$G:$G, "Aguardando Pagamento", 'Leandro Drumond'!$L:$L, "=10"), "") -> 0 | Q42: 4500 | R42: =Q42-P42 -> 4500 | S42: =P42/Q42 -> 0 | T42: =R42/Q42 -> 1
A43: Marcelle Marcela | B43: =IFERROR( SUMIFS('Marcelle Marcela'!$H:$H, 'Marcelle Marcela'!$G:$G, "Plano Fechado", 'Marcelle Marcela'!$L:$L, "=10"), "") -> 0 | C43: 2800 | D43: =C43-B43 -> 2800 | E43: =B43/C43 -> 0 | F43: =D43/C43 -> 1 | H43: Marcelle Marcela | I43: =IFERROR( SUMIFS('Marcelle Marcela'!$H:$H, 'Marcelle Marcela'!$G:$G, "Em Análise", 'Marcelle Marcela'!$L:$L, "=10"), "") -> 0 | J43: 2800 | K43: =J43-I43 -> 2800 | L43: =I43/J43 -> 0 | M43: =K43/J43 -> 1 | O43: Marcelle Marcela | P43: =IFERROR( SUMIFS('Marcelle Marcela'!$H:$H, 'Marcelle Marcela'!$G:$G, "Aguardando Pagamento", 'Marcelle Marcela'!$L:$L, "=10"), "") -> 0 | Q43: 2800 | R43: =Q43-P43 -> 2800 | S43: =P43/Q43 -> 0 | T43: =R43/Q43 -> 1
A46: TOTAL | B46: =SUM(B30:B43) -> 84184.77 | C46: =SUM(C30:C43) -> 136100 | D46: =SUM(D30:D43) -> 51915.23 | E46: =AVERAGE(E30:E43) -> 0.41161162 | F46: =AVERAGE(F30:F43) -> 0.58838838 | H46: TOTAL | I46: =SUM(I30:I43) -> 15066.85 | J46: =SUM(J30:J43) -> 136100 | K46: =SUM(K30:K43) -> 121033.15 | L46: =AVERAGE(L30:L43) -> 0.096539133 | M46: =AVERAGE(M30:M43) -> 0.90346087 | O46: TOTAL | P46: =SUM(P30:P43) -> 3947.49 | Q46: =SUM(Q30:Q43) -> 136100 | R46: =SUM(R30:R43) -> 132152.51 | S46: =AVERAGE(S30:S43) -> 0.020140255 | T46: =AVERAGE(T30:T43) -> 0.97985974

Sheet MKT
B1: MAIO | J1: JUNHO | R1: JULHO | Z1: AGOSTO | AH1: SETEMBRO | AP1: OUTUBRO
B3: VISÃO MACRO PROSPECÇÃO LEADS | J3: VISÃO MACRO PROSPECÇÃO LEADS | R3: VISÃO MACRO PROSPECÇÃO LEADS | Z3: VISÃO MACRO PROSPECÇÃO LEADS | AH3: VISÃO MACRO PROSPECÇÃO LEADS | AP3: VISÃO MACRO PROSPECÇÃO LEADS
B4: QTD. Leads | C4: Vendas Fechadas | D4: Leads em Conversação | E4: Leads com Proposta Enviada | F4: Leads Desistentes | G4: Leads sem Resposta | H4: Faturamento | J4: QTD. Leads | K4: Vendas Fechadas | L4: Leads em Conversação | M4: Leads com Proposta Enviada | N4: Leads Desistentes | O4: Leads sem Resposta | P4: Faturamento | R4: QTD. Leads | S4: Vendas Fechadas | T4: Leads em Conversação | U4: Leads com Proposta Enviada | V4: Leads Desistentes | W4: Leads sem Resposta | X4: Faturamento | Z4: QTD. Leads | AA4: Vendas Fechadas | AB4: Leads em Conversação | AC4: Leads com Proposta Enviada | AD4: Leads Desistentes | AE4: Leads sem Resposta | AF4: Faturamento | AH4: QTD. Leads | AI4: Vendas Fechadas | AJ4: Leads em Conversação | AK4: Leads com Proposta Enviada | AL4: Leads Desistentes | AM4: Leads sem Resposta | AN4: Faturamento | AP4: QTD. Leads | AQ4: Plano Fechado | AR4: Em Análise | AS4: Aguardando Pagamento | AT4: Conversação | AU4: Proposta Enviada | AV4: Desistentes | AW4: Sem Resposta | AX4: Faturamento
B5: 401 | C5: 4 | D5: 39 | E5: 108 | F5: 18 | G5: 232 | H5: 3267.91 | J5: 1368 | K5: 61 | L5: 42 | M5: 355 | N5: 49 | O5: 670 | P5: 100469.35 | R5: 1485 | S5: 60 | T5: 52 | U5: 325 | V5: 39 | W5: 688 | X5: 90022.06 | Z5: 1241 | AA5: 63 | AB5: 80 | AC5: 253 | AD5: 46 | AE5: 511 | AF5: 64270.88 | AH5: 1447 | AI5: 62 | AJ5: 72 | AK5: 407 | AL5: 54 | AM5: 576 | AN5: 77071.27 | AP5: {=LET( abas, {"Amanda Facundo";"Bruna Mamedes";"Camila Adão";"Darlin Amorim";"Diogo Lima";"Externos";"Maiara Andrade";"Marcio Jorge";"Lucas Almeida";"Roberto Ramos";"Rodrigo Oliviera";"Leandro Nascimento";"Leandro Drumond";"Marcelle Marcela";"Anteriores";"Corretor 1";"Corretor 2";"Corretor 3";"Corretor 4";"Corretor 5"}, SUM(BYROW(abas, LAMBDA(a, COUNTIFS( INDIRECT("'"&a&"'!N:N"), ">="&DATE(2025,10,1), INDIRECT("'"&a&"'!N:N"), "<="&DATE(2025,10,31) )))) )} -> 1252 | AQ5: =SUM( COUNTIFS('Bruna Mamedes'!$A$2:$A$4000, "<>", 'Bruna Mamedes'!$N$2:$N$4000, ">01/10/2025", 'Bruna Mamedes'!$N$2:$N$4000, "<01/11/2025", 'Bruna Mamedes'!$G$2:$G$4000, "Plano Fechado"), COUNTIFS('Camila Adão'!$A$2:$A$4000, "<>", 'Camila Adão'!$N$2:$N$4000, ">01/10/2025", 'Camila Adão'!$N$2:$N$4000, "<01/11/2025", 'Camila Adão'!$G$2:$G$4000, "Plano Fechado"), COUNTIFS('Vendas Organicas'!$A$2:$A$4000, "<>", 'Vendas Organicas'!$N$2:$N$4000, ">01/10/2025", 'Vendas Organicas'!$N$2:$N$4000, "<01/11/2025", 'Vendas Organicas'!$G$2:$G$4000, "Plano Fechado"), COUNTIFS('Diogo Lima'!$A$2:$A$3999, "<>", 'Diogo Lima'!$N$2:$N$3999, ">01/10/2025", 'Diogo Lima'!$N$2:$N$3999, "<01/11/2025", 'Diogo Lima'!$G$2:$G$3999, "Plano Fechado"), COUNTIFS('Lucas Almeida'!$A$2:$A$4000, "<>", 'Lucas Almeida'!$N$2:$N$4000, ">01/10/2025", 'Lucas Almeida'!$N$2:$N$4000, "<01/11/2025", 'Lucas Almeida'!$G$2:$G$4000, "Plano Fechado"), COUNTIFS('Fernando Diamantino'!$A$2:$A$4000, "<>", 'Fernando Diamantino'!$N$2:$N$4000, ">01/10/2025", 'Fernando Diamantino'!$N$2:$N$4000, "<01/11/2025", 'Fernando Diamantino'!$G$2:$G$4000, "Plano Fechado"), COUNTIFS('Maiara Andrade'!$A$2:$A$4000, "<>", 'Maiara Andrade'!$N$2:$N$4000, ">01/10/2025", 'Maiara Andrade'!$N$2:$N$4000, "<01/11/2025", 'Maiara Andrade'!$G$2:$G$4000, "Plano Fechado"), COUNTIFS('Roberto Ramos'!$A$2:$A$4000, "<>", 'Roberto Ramos'!$N$2:$N$4000, ">01/10/2025", 'Roberto Ramos'!$N$2:$N$4000, "<01/11/2025", 'Roberto Ramos'!$G$2:$G$4000, "Plano Fechado"), COUNTIFS('Amanda Facundo'!$A$2:$A$4000, "<>", 'Amanda Facundo'!$N$2:$N$4000, ">01/10/2025", 'Amanda Facundo'!$N$2:$N$4000, "<01/11/2025", 'Amanda Facundo'!$G$2:$G$4000, "Plano Fechado"), COUNTIFS('Rodrigo Oliveira'!$A$2:$A$4000, "<>", 'Rodrigo Oliveira'!$N$2:$N$4000, ">01/10/2025", 'Rodrigo Oliveira'!$N$2:$N$4000, "<01/11/2025", 'Rodrigo Oliveira'!$G$2:$G$4000, "Plano Fechado"), COUNTIFS('Marcio Jorge'!$A$2:$A$4000, "<>", 'Marcio Jorge'!$N$2:$N$4000, ">01/10/2025", 'Marcio Jorge'!$N$2:$N$4000, "<01/11/2025", 'Marcio Jorge'!$G$2:$G$4000, "Plano Fechado"), COUNTIFS(Anteriores!$A$2:$A$3998, "<>", Anteriores!$N$2:$N$3998, ">01/10/2025", Anteriores!$N$2:$N$3998, "<01/11/2025", Anteriores!$G$2:$G$3998, "Plano Fechado"), COUNTIFS('Corretor 1'!$A$2:$A$4000, "<>", 'Corretor 1'!$N$2:$N$4000, ">01/10/2025", 'Corretor 1'!$N$2:$N$4000, "<01/11/2025", 'Corretor 1'!$G$2:$G$4000, "Plano Fechado"), COUNTIFS('Corretor 2'!$A$2:$A$4000, "<>", 'Corretor 2'!$N$2:$N$4000, ">01/10/2025", 'Corretor 2'!$N$2:$N$4000, "<01/11/2025", 'Corretor 2'!$G$2:$G$4000, "Plano Fechado"), COUNTIFS('Corretor 3'!$A$2:$A$4000, "<>", 'Corretor 3'!$N$2:$N$4000, ">01/10/2025", 'Corretor 3'!$N$2:$N$4000, "<01/11/2025", 'Corretor 3'!$G$2:$G$4000, "Plano Fechado"), COUNTIFS('Corretor 4'!$A$2:$A$4000, "<>", 'Corretor 4'!$N$2:$N$4000, ">01/10/2025", 'Corretor 4'!$N$2:$N$4000, "<01/11/2025", 'Corretor 4'!$G$2:$G$4000, "Plano Fechado"), COUNTIFS('Corretor 5'!$A$2:$A$4000, "<>", 'Corretor 5'!$N$2:$N$4000, ">01/10/2025", 'Corretor 5'!$N$2:$N$4000, "<01/11/2025", 'Corretor 5'!$G$2:$G$4000, "Plano Fechado") ) -> 46 | AR5: =SUM( COUNTIFS('Bruna Mamedes'!$A$2:$A$4000, "<>", 'Bruna Mamedes'!$N$2:$N$4000, ">01/10/2025", 'Bruna Mamedes'!$N$2:$N$4000, "<01/11/2025", 'Bruna Mamedes'!$G$2:$G$4000, "Em Análise"), COUNTIFS('Camila Adão'!$A$2:$A$4000, "<>", 'Camila Adão'!$N$2:$N$4000, ">01/10/2025", 'Camila Adão'!$N$2:$N$4000, "<01/11/2025", 'Camila Adão'!$G$2:$G$4000, "Em Análise"), COUNTIFS('Vendas Organicas'!$A$2:$A$4000, "<>", 'Vendas Organicas'!$N$2:$N$4000, ">01/10/2025", 'Vendas Organicas'!$N$2:$N$4000, "<01/11/2025", 'Vendas Organicas'!$G$2:$G$4000, "Em Análise"), COUNTIFS('Diogo Lima'!$A$2:$A$3999, "<>", 'Diogo Lima'!$N$2:$N$3999, ">01/10/2025", 'Diogo Lima'!$N$2:$N$3999, "<01/11/2025", 'Diogo Lima'!$G$2:$G$3999, "Em Análise"), COUNTIFS('Lucas Almeida'!$A$2:$A$4000, "<>", 'Lucas Almeida'!$N$2:$N$4000, ">01/10/2025", 'Lucas Almeida'!$N$2:$N$4000, "<01/11/2025", 'Lucas Almeida'!$G$2:$G$4000, "Em Análise"), COUNTIFS('Fernando Diamantino'!$A$2:$A$4000, "<>", 'Fernando Diamantino'!$N$2:$N$4000, ">01/10/2025", 'Fernando Diamantino'!$N$2:$N$4000, "<01/11/2025", 'Fernando Diamantino'!$G$2:$G$4000, "Em Análise"), COUNTIFS('Maiara Andrade'!$A$2:$A$4000, "<>", 'Maiara Andrade'!$N$2:$N$4000, ">01/10/2025", 'Maiara Andrade'!$N$2:$N$4000, "<01/11/2025", 'Maiara Andrade'!$G$2:$G$4000, "Em Análise"), COUNTIFS('Roberto Ramos'!$A$2:$A$4000, "<>", 'Roberto Ramos'!$N$2:$N$4000, ">01/10/2025", 'Roberto Ramos'!$N$2:$N$4000, "<01/11/2025", 'Roberto Ramos'!$G$2:$G$4000, "Em Análise"), COUNTIFS('Amanda Facundo'!$A$2:$A$4000, "<>", 'Amanda Facundo'!$N$2:$N$4000, ">01/10/2025", 'Amanda Facundo'!$N$2:$N$4000, "<01/11/2025", 'Amanda Facundo'!$G$2:$G$4000, "Em Análise"), COUNTIFS('Rodrigo Oliveira'!$A$2:$A$4000, "<>", 'Rodrigo Oliveira'!$N$2:$N$4000, ">01/10/2025", 'Rodrigo Oliveira'!$N$2:$N$4000, "<01/11/2025", 'Rodrigo Oliveira'!$G$2:$G$4000, "Em Análise"), COUNTIFS('Marcio Jorge'!$A$2:$A$4000, "<>", 'Marcio Jorge'!$N$2:$N$4000, ">01/10/2025", 'Marcio Jorge'!$N$2:$N$4000, "<01/11/2025", 'Marcio Jorge'!$G$2:$G$4000, "Em Análise"), COUNTIFS(Anteriores!$A$2:$A$3998, "<>", Anteriores!$N$2:$N$3998, ">01/10/2025", Anteriores!$N$2:$N$3998, "<01/11/2025", Anteriores!$G$2:$G$3998, "Em Análise"), COUNTIFS('Corretor 1'!$A$2:$A$4000, "<>", 'Corretor 1'!$N$2:$N$4000, ">01/10/2025", 'Corretor 1'!$N$2:$N$4000, "<01/11/2025", 'Corretor 1'!$G$2:$G$4000, "Em Análise"), COUNTIFS('Corretor 2'!$A$2:$A$4000, "<>", 'Corretor 2'!$N$2:$N$4000, ">01/10/2025", 'Corretor 2'!$N$2:$N$4000, "<01/11/2025", 'Corretor 2'!$G$2:$G$4000, "Em Análise"), COUNTIFS('Corretor 3'!$A$2:$A$4000, "<>", 'Corretor 3'!$N$2:$N$4000, ">01/10/2025", 'Corretor 3'!$N$2:$N$4000, "<01/11/2025", 'Corretor 3'!$G$2:$G$4000, "Em Análise"), COUNTIFS('Corretor 4'!$A$2:$A$4000, "<>", 'Corretor 4'!$N$2:$N$4000, ">01/10/2025", 'Corretor 4'!$N$2:$N$4000, "<01/11/2025", 'Corretor 4'!$G$2:$G$4000, "Em Análise"), COUNTIFS('Corretor 5'!$A$2:$A$4000, "<>", 'Corretor 5'!$N$2:$N$4000, ">01/10/2025", 'Corretor 5'!$N$2:$N$4000, "<01/11/2025", 'Corretor 5'!$G$2:$G$4000, "Em Análise") ) -> 18 | AS5: =SUM( COUNTIFS('Bruna Mamedes'!$A$2:$A$4000, "<>", 'Bruna Mamedes'!$N$2:$N$4000, ">01/10/2025", 'Bruna Mamedes'!$N$2:$N$4000, "<01/11/2025", 'Bruna Mamedes'!$G$2:$G$4000, "Aguardando Pagamento"), COUNTIFS('Camila Adão'!$A$2:$A$4000, "<>", 'Camila Adão'!$N$2:$N$4000, ">01/10/2025", 'Camila Adão'!$N$2:$N$4000, "<01/11/2025", 'Camila Adão'!$G$2:$G$4000, "Aguardando Pagamento"), COUNTIFS('Vendas Organicas'!$A$2:$A$4000, "<>", 'Vendas Organicas'!$N$2:$N$4000, ">01/10/2025", 'Vendas Organicas'!$N$2:$N$4000, "<01/11/2025", 'Vendas Organicas'!$G$2:$G$4000, "Aguardando Pagamento"), COUNTIFS('Diogo Lima'!$A$2:$A$3999, "<>", 'Diogo Lima'!$N$2:$N$3999, ">01/10/2025", 'Diogo Lima'!$N$2:$N$3999, "<01/11/2025", 'Diogo Lima'!$G$2:$G$3999, "Aguardando Pagamento"), COUNTIFS('Lucas Almeida'!$A$2:$A$4000, "<>", 'Lucas Almeida'!$N$2:$N$4000, ">01/10/2025", 'Lucas Almeida'!$N$2:$N$4000, "<01/11/2025", 'Lucas Almeida'!$G$2:$G$4000, "Aguardando Pagamento"), COUNTIFS('Fernando Diamantino'!$A$2:$A$4000, "<>", 'Fernando Diamantino'!$N$2:$N$4000, ">01/10/2025", 'Fernando Diamantino'!$N$2:$N$4000, "<01/11/2025", 'Fernando Diamantino'!$G$2:$G$4000, "Aguardando Pagamento"), COUNTIFS('Maiara Andrade'!$A$2:$A$4000, "<>", 'Maiara Andrade'!$N$2:$N$4000, ">01/10/2025", 'Maiara Andrade'!$N$2:$N$4000, "<01/11/2025", 'Maiara Andrade'!$G$2:$G$4000, "Aguardando Pagamento"), COUNTIFS('Roberto Ramos'!$A$2:$A$4000, "<>", 'Roberto Ramos'!$N$2:$N$4000, ">01/10/2025", 'Roberto Ramos'!$N$2:$N$4000, "<01/11/2025", 'Roberto Ramos'!$G$2:$G$4000, "Aguardando Pagamento"), COUNTIFS('Amanda Facundo'!$A$2:$A$4000, "<>", 'Amanda Facundo'!$N$2:$N$4000, ">01/10/2025", 'Amanda Facundo'!$N$2:$N$4000, "<01/11/2025", 'Amanda Facundo'!$G$2:$G$4000, "Aguardando Pagamento"), COUNTIFS('Rodrigo Oliveira'!$A$2:$A$4000, "<>", 'Rodrigo Oliveira'!$N$2:$N$4000, ">01/10/2025", 'Rodrigo Oliveira'!$N$2:$N$4000, "<01/11/2025", 'Rodrigo Oliveira'!$G$2:$G$4000, "Aguardando Pagamento"), COUNTIFS('Marcio Jorge'!$A$2:$A$4000, "<>", 'Marcio Jorge'!$N$2:$N$4000, ">01/10/2025", 'Marcio Jorge'!$N$2:$N$4000, "<01/11/2025", 'Marcio Jorge'!$G$2:$G$4000, "Aguardando Pagamento"), COUNTIFS(Anteriores!$A$2:$A$3998, "<>", Anteriores!$N$2:$N$3998, ">01/10/2025", Anteriores!$N$2:$N$3998, "<01/11/2025", Anteriores!$G$2:$G$3998, "Aguardando Pagamento"), COUNTIFS('Corretor 1'!$A$2:$A$4000, "<>", 'Corretor 1'!$N$2:$N$4000, ">01/10/2025", 'Corretor 1'!$N$2:$N$4000, "<01/11/2025", 'Corretor 1'!$G$2:$G$4000, "Aguardando Pagamento"), COUNTIFS('Corretor 2'!$A$2:$A$4000, "<>", 'Corretor 2'!$N$2:$N$4000, ">01/10/2025", 'Corretor 2'!$N$2:$N$4000, "<01/11/2025", 'Corretor 2'!$G$2:$G$4000, "Aguardando Pagamento"), COUNTIFS('Corretor 3'!$A$2:$A$4000, "<>", 'Corretor 3'!$N$2:$N$4000, ">01/10/2025", 'Corretor 3'!$N$2:$N$4000, "<01/11/2025", 'Corretor 3'!$G$2:$G$4000, "Aguardando Pagamento"), COUNTIFS('Corretor 4'!$A$2:$A$4000, "<>", 'Corretor 4'!$N$2:$N$4000, ">01/10/2025", 'Corretor 4'!$N$2:$N$4000, "<01/11/2025", 'Corretor 4'!$G$2:$G$4000, "Aguardando Pagamento"), COUNTIFS('Corretor 5'!$A$2:$A$4000, "<>", 'Corretor 5'!$N$2:$N$4000, ">01/10/2025", 'Corretor 5'!$N$2:$N$4000, "<01/11/2025", 'Corretor 5'!$G$2:$G$4000, "Aguardando Pagamento") ) -> 4 | AT5: =SUM( COUNTIFS('Bruna Mamedes'!$A$2:$A$4000, "<>", 'Bruna Mamedes'!$N$2:$N$4000, ">01/10/2025", 'Bruna Mamedes'!$N$2:$N$4000, "<01/11/2025", 'Bruna Mamedes'!$G$2:$G$4000, "Em conversação"), COUNTIFS('Camila Adão'!$A$2:$A$4000, "<>", 'Camila Adão'!$N$2:$N$4000, ">01/10/2025", 'Camila Adão'!$N$2:$N$4000, "<01/11/2025", 'Camila Adão'!$G$2:$G$4000, "Em conversação"), COUNTIFS('Vendas Organicas'!$A$2:$A$4000, "<>", 'Vendas Organicas'!$N$2:$N$4000, ">01/10/2025", 'Vendas Organicas'!$N$2:$N$4000, "<01/11/2025", 'Vendas Organicas'!$G$2:$G$4000, "Em conversação"), COUNTIFS('Diogo Lima'!$A$2:$A$3999, "<>", 'Diogo Lima'!$N$2:$N$3999, ">01/10/2025", 'Diogo Lima'!$N$2:$N$3999, "<01/11/2025", 'Diogo Lima'!$G$2:$G$3999, "Em conversação"), COUNTIFS('Lucas Almeida'!$A$2:$A$4000, "<>", 'Lucas Almeida'!$N$2:$N$4000, ">01/10/2025", 'Lucas Almeida'!$N$2:$N$4000, "<01/11/2025", 'Lucas Almeida'!$G$2:$G$4000, "Em conversação"), COUNTIFS('Fernando Diamantino'!$A$2:$A$4000, "<>", 'Fernando Diamantino'!$N$2:$N$4000, ">01/10/2025", 'Fernando Diamantino'!$N$2:$N$4000, "<01/11/2025", 'Fernando Diamantino'!$G$2:$G$4000, "Em conversação"), COUNTIFS('Maiara Andrade'!$A$2:$A$4000, "<>", 'Maiara Andrade'!$N$2:$N$4000, ">01/10/2025", 'Maiara Andrade'!$N$2:$N$4000, "<01/11/2025", 'Maiara Andrade'!$G$2:$G$4000, "Em conversação"), COUNTIFS('Roberto Ramos'!$A$2:$A$4000, "<>", 'Roberto Ramos'!$N$2:$N$4000, ">01/10/2025", 'Roberto Ramos'!$N$2:$N$4000, "<01/11/2025", 'Roberto Ramos'!$G$2:$G$4000, "Em conversação"), COUNTIFS('Amanda Facundo'!$A$2:$A$4000, "<>", 'Amanda Facundo'!$N$2:$N$4000, ">01/10/2025", 'Amanda Facundo'!$N$2:$N$4000, "<01/11/2025", 'Amanda Facundo'!$G$2:$G$4000, "Em conversação"), COUNTIFS('Rodrigo Oliveira'!$A$2:$A$4000, "<>", 'Rodrigo Oliveira'!$N$2:$N$4000, ">01/10/2025", 'Rodrigo Oliveira'!$N$2:$N$4000, "<01/11/2025", 'Rodrigo Oliveira'!$G$2:$G$4000, "Em conversação"), COUNTIFS('Marcio Jorge'!$A$2:$A$4000, "<>", 'Marcio Jorge'!$N$2:$N$4000, ">01/10/2025", 'Marcio Jorge'!$N$2:$N$4000, "<01/11/2025", 'Marcio Jorge'!$G$2:$G$4000, "Em conversação"), COUNTIFS(Anteriores!$A$2:$A$3998, "<>", Anteriores!$N$2:$N$3998, ">01/10/2025", Anteriores!$N$2:$N$3998, "<01/11/2025", Anteriores!$G$2:$G$3998, "Em conversação"), COUNTIFS('Corretor 1'!$A$2:$A$4000, "<>", 'Corretor 1'!$N$2:$N$4000, ">01/10/2025", 'Corretor 1'!$N$2:$N$4000, "<01/11/2025", 'Corretor 1'!$G$2:$G$4000, "Em conversação"), COUNTIFS('Corretor 2'!$A$2:$A$4000, "<>", 'Corretor 2'!$N$2:$N$4000, ">01/10/2025", 'Corretor 2'!$N$2:$N$4000, "<01/11/2025", 'Corretor 2'!$G$2:$G$4000, "Em conversação"), COUNTIFS('Corretor 3'!$A$2:$A$4000, "<>", 'Corretor 3'!$N$2:$N$4000, ">01/10/2025", 'Corretor 3'!$N$2:$N$4000, "<01/11/2025", 'Corretor 3'!$G$2:$G$4000, "Em conversação"), COUNTIFS('Corretor 4'!$A$2:$A$4000, "<>", 'Corretor 4'!$N$2:$N$4000, ">01/10/2025", 'Corretor 4'!$N$2:$N$4000, "<01/11/2025", 'Corretor 4'!$G$2:$G$4000, "Em conversação"), COUNTIFS('Corretor 5'!$A$2:$A$4000, "<>", 'Corretor 5'!$N$2:$N$4000, ">01/10/2025", 'Corretor 5'!$N$2:$N$4000, "<01/11/2025", 'Corretor 5'!$G$2:$G$4000, "Em conversação") ) -> 31 | AU5: =SUM( COUNTIFS('Bruna Mamedes'!$A$2:$A$4000, "<>", 'Bruna Mamedes'!$N$2:$N$4000, ">01/10/2025", 'Bruna Mamedes'!$N$2:$N$4000, "<01/11/2025", 'Bruna Mamedes'!$G$2:$G$4000, "Cotação Enviada"), COUNTIFS('Camila Adão'!$A$2:$A$4000, "<>", 'Camila Adão'!$N$2:$N$4000, ">01/10/2025", 'Camila Adão'!$N$2:$N$4000, "<01/11/2025", 'Camila Adão'!$G$2:$G$4000, "Cotação Enviada"), COUNTIFS('Vendas Organicas'!$A$2:$A$4000, "<>", 'Vendas Organicas'!$N$2:$N$4000, ">01/10/2025", 'Vendas Organicas'!$N$2:$N$4000, "<01/11/2025", 'Vendas Organicas'!$G$2:$G$4000, "Cotação Enviada"), COUNTIFS('Diogo Lima'!$A$2:$A$3999, "<>", 'Diogo Lima'!$N$2:$N$3999, ">01/10/2025", 'Diogo Lima'!$N$2:$N$3999, "<01/11/2025", 'Diogo Lima'!$G$2:$G$3999, "Cotação Enviada"), COUNTIFS('Lucas Almeida'!$A$2:$A$4000, "<>", 'Lucas Almeida'!$N$2:$N$4000, ">01/10/2025", 'Lucas Almeida'!$N$2:$N$4000, "<01/11/2025", 'Lucas Almeida'!$G$2:$G$4000, "Cotação Enviada"), COUNTIFS('Fernando Diamantino'!$A$2:$A$4000, "<>", 'Fernando Diamantino'!$N$2:$N$4000, ">01/10/2025", 'Fernando Diamantino'!$N$2:$N$4000, "<01/11/2025", 'Fernando Diamantino'!$G$2:$G$4000, "Cotação Enviada"), COUNTIFS('Maiara Andrade'!$A$2:$A$4000, "<>", 'Maiara Andrade'!$N$2:$N$4000, ">01/10/2025", 'Maiara Andrade'!$N$2:$N$4000, "<01/11/2025", 'Maiara Andrade'!$G$2:$G$4000, "Cotação Enviada"), COUNTIFS('Roberto Ramos'!$A$2:$A$4000, "<>", 'Roberto Ramos'!$N$2:$N$4000, ">01/10/2025", 'Roberto Ramos'!$N$2:$N$4000, "<01/11/2025", 'Roberto Ramos'!$G$2:$G$4000, "Cotação Enviada"), COUNTIFS('Amanda Facundo'!$A$2:$A$4000, "<>", 'Amanda Facundo'!$N$2:$N$4000, ">01/10/2025", 'Amanda Facundo'!$N$2:$N$4000, "<01/11/2025", 'Amanda Facundo'!$G$2:$G$4000, "Cotação Enviada"), COUNTIFS('Rodrigo Oliveira'!$A$2:$A$4000, "<>", 'Rodrigo Oliveira'!$N$2:$N$4000, ">01/10/2025", 'Rodrigo Oliveira'!$N$2:$N$4000, "<01/11/2025", 'Rodrigo Oliveira'!$G$2:$G$4000, "Cotação Enviada"), COUNTIFS('Marcio Jorge'!$A$2:$A$4000, "<>", 'Marcio Jorge'!$N$2:$N$4000, ">01/10/2025", 'Marcio Jorge'!$N$2:$N$4000, "<01/11/2025", 'Marcio Jorge'!$G$2:$G$4000, "Cotação Enviada"), COUNTIFS(Anteriores!$A$2:$A$3998, "<>", Anteriores!$N$2:$N$3998, ">01/10/2025", Anteriores!$N$2:$N$3998, "<01/11/2025", Anteriores!$G$2:$G$3998, "Cotação Enviada"), COUNTIFS('Corretor 1'!$A$2:$A$4000, "<>", 'Corretor 1'!$N$2:$N$4000, ">01/10/2025", 'Corretor 1'!$N$2:$N$4000, "<01/11/2025", 'Corretor 1'!$G$2:$G$4000, "Cotação Enviada"), COUNTIFS('Corretor 2'!$A$2:$A$4000, "<>", 'Corretor 2'!$N$2:$N$4000, ">01/10/2025", 'Corretor 2'!$N$2:$N$4000, "<01/11/2025", 'Corretor 2'!$G$2:$G$4000, "Cotação Enviada"), COUNTIFS('Corretor 3'!$A$2:$A$4000, "<>", 'Corretor 3'!$N$2:$N$4000, ">01/10/2025", 'Corretor 3'!$N$2:$N$4000, "<01/11/2025", 'Corretor 3'!$G$2:$G$4000, "Cotação Enviada"), COUNTIFS('Corretor 4'!$A$2:$A$4000, "<>", 'Corretor 4'!$N$2:$N$4000, ">01/10/2025", 'Corretor 4'!$N$2:$N$4000, "<01/11/2025", 'Corretor 4'!$G$2:$G$4000, "Cotação Enviada"), COUNTIFS('Corretor 5'!$A$2:$A$4000, "<>", 'Corretor 5'!$N$2:$N$4000, ">01/10/2025", 'Corretor 5'!$N$2:$N$4000, "<01/11/2025", 'Corretor 5'!$G$2:$G$4000, "Cotação Enviada") ) -> 267 | AV5: =SUM( COUNTIFS('Bruna Mamedes'!$A$2:$A$4000, "<>", 'Bruna Mamedes'!$N$2:$N$4000, ">01/10/2025", 'Bruna Mamedes'!$N$2:$N$4000, "<01/11/2025", 'Bruna Mamedes'!$G$2:$G$4000, "Desistência"), COUNTIFS('Camila Adão'!$A$2:$A$4000, "<>", 'Camila Adão'!$N$2:$N$4000, ">01/10/2025", 'Camila Adão'!$N$2:$N$4000, "<01/11/2025", 'Camila Adão'!$G$2:$G$4000, "Desistência"), COUNTIFS('Vendas Organicas'!$A$2:$A$4000, "<>", 'Vendas Organicas'!$N$2:$N$4000, ">01/10/2025", 'Vendas Organicas'!$N$2:$N$4000, "<01/11/2025", 'Vendas Organicas'!$G$2:$G$4000, "Desistência"), COUNTIFS('Diogo Lima'!$A$2:$A$3999, "<>", 'Diogo Lima'!$N$2:$N$3999, ">01/10/2025", 'Diogo Lima'!$N$2:$N$3999, "<01/11/2025", 'Diogo Lima'!$G$2:$G$3999, "Desistência"), COUNTIFS('Lucas Almeida'!$A$2:$A$4000, "<>", 'Lucas Almeida'!$N$2:$N$4000, ">01/10/2025", 'Lucas Almeida'!$N$2:$N$4000, "<01/11/2025", 'Lucas Almeida'!$G$2:$G$4000, "Desistência"), COUNTIFS('Fernando Diamantino'!$A$2:$A$4000, "<>", 'Fernando Diamantino'!$N$2:$N$4000, ">01/10/2025", 'Fernando Diamantino'!$N$2:$N$4000, "<01/11/2025", 'Fernando Diamantino'!$G$2:$G$4000, "Desistência"), COUNTIFS('Maiara Andrade'!$A$2:$A$4000, "<>", 'Maiara Andrade'!$N$2:$N$4000, ">01/10/2025", 'Maiara Andrade'!$N$2:$N$4000, "<01/11/2025", 'Maiara Andrade'!$G$2:$G$4000, "Desistência"), COUNTIFS('Roberto Ramos'!$A$2:$A$4000, "<>", 'Roberto Ramos'!$N$2:$N$4000, ">01/10/2025", 'Roberto Ramos'!$N$2:$N$4000, "<01/11/2025", 'Roberto Ramos'!$G$2:$G$4000, "Desistência"), COUNTIFS('Amanda Facundo'!$A$2:$A$4000, "<>", 'Amanda Facundo'!$N$2:$N$4000, ">01/10/2025", 'Amanda Facundo'!$N$2:$N$4000, "<01/11/2025", 'Amanda Facundo'!$G$2:$G$4000, "Desistência"), COUNTIFS('Rodrigo Oliveira'!$A$2:$A$4000, "<>", 'Rodrigo Oliveira'!$N$2:$N$4000, ">01/10/2025", 'Rodrigo Oliveira'!$N$2:$N$4000, "<01/11/2025", 'Rodrigo Oliveira'!$G$2:$G$4000, "Desistência"), COUNTIFS('Marcio Jorge'!$A$2:$A$4000, "<>", 'Marcio Jorge'!$N$2:$N$4000, ">01/10/2025", 'Marcio Jorge'!$N$2:$N$4000, "<01/11/2025", 'Marcio Jorge'!$G$2:$G$4000, "Desistência"), COUNTIFS(Anteriores!$A$2:$A$3998, "<>", Anteriores!$N$2:$N$3998, ">01/10/2025", Anteriores!$N$2:$N$3998, "<01/11/2025", Anteriores!$G$2:$G$3998, "Desistência"), COUNTIFS('Corretor 1'!$A$2:$A$4000, "<>", 'Corretor 1'!$N$2:$N$4000, ">01/10/2025", 'Corretor 1'!$N$2:$N$4000, "<01/11/2025", 'Corretor 1'!$G$2:$G$4000, "Desistência"), COUNTIFS('Corretor 2'!$A$2:$A$4000, "<>", 'Corretor 2'!$N$2:$N$4000, ">01/10/2025", 'Corretor 2'!$N$2:$N$4000, "<01/11/2025", 'Corretor 2'!$G$2:$G$4000, "Desistência"), COUNTIFS('Corretor 3'!$A$2:$A$4000, "<>", 'Corretor 3'!$N$2:$N$4000, ">01/10/2025", 'Corretor 3'!$N$2:$N$4000, "<01/11/2025", 'Corretor 3'!$G$2:$G$4000, "Desistência"), COUNTIFS('Corretor 4'!$A$2:$A$4000, "<>", 'Corretor 4'!$N$2:$N$4000, ">01/10/2025", 'Corretor 4'!$N$2:$N$4000, "<01/11/2025", 'Corretor 4'!$G$2:$G$4000, "Desistência"), COUNTIFS('Corretor 5'!$A$2:$A$4000, "<>", 'Corretor 5'!$N$2:$N$4000, ">01/10/2025", 'Corretor 5'!$N$2:$N$4000, "<01/11/2025", 'Corretor 5'!$G$2:$G$4000, "Desistência") ) -> 73 | AW5: =SUM( COUNTIFS('Bruna Mamedes'!$A$2:$A$4000, "<>", 'Bruna Mamedes'!$N$2:$N$4000, ">01/10/2025", 'Bruna Mamedes'!$N$2:$N$4000, "<01/11/2025", 'Bruna Mamedes'!$G$2:$G$4000, "Não Respondeu"), COUNTIFS('Camila Adão'!$A$2:$A$4000, "<>", 'Camila Adão'!$N$2:$N$4000, ">01/10/2025", 'Camila Adão'!$N$2:$N$4000, "<01/11/2025", 'Camila Adão'!$G$2:$G$4000, "Não Respondeu"), COUNTIFS('Vendas Organicas'!$A$2:$A$4000, "<>", 'Vendas Organicas'!$N$2:$N$4000, ">01/10/2025", 'Vendas Organicas'!$N$2:$N$4000, "<01/11/2025", 'Vendas Organicas'!$G$2:$G$4000, "Não Respondeu"), COUNTIFS('Diogo Lima'!$A$2:$A$3999, "<>", 'Diogo Lima'!$N$2:$N$3999, ">01/10/2025", 'Diogo Lima'!$N$2:$N$3999, "<01/11/2025", 'Diogo Lima'!$G$2:$G$3999, "Não Respondeu"), COUNTIFS('Lucas Almeida'!$A$2:$A$4000, "<>", 'Lucas Almeida'!$N$2:$N$4000, ">01/10/2025", 'Lucas Almeida'!$N$2:$N$4000, "<01/11/2025", 'Lucas Almeida'!$G$2:$G$4000, "Não Respondeu"), COUNTIFS('Fernando Diamantino'!$A$2:$A$4000, "<>", 'Fernando Diamantino'!$N$2:$N$4000, ">01/10/2025", 'Fernando Diamantino'!$N$2:$N$4000, "<01/11/2025", 'Fernando Diamantino'!$G$2:$G$4000, "Não Respondeu"), COUNTIFS('Maiara Andrade'!$A$2:$A$4000, "<>", 'Maiara Andrade'!$N$2:$N$4000, ">01/10/2025", 'Maiara Andrade'!$N$2:$N$4000, "<01/11/2025", 'Maiara Andrade'!$G$2:$G$4000, "Não Respondeu"), COUNTIFS('Roberto Ramos'!$A$2:$A$4000, "<>", 'Roberto Ramos'!$N$2:$N$4000, ">01/10/2025", 'Roberto Ramos'!$N$2:$N$4000, "<01/11/2025", 'Roberto Ramos'!$G$2:$G$4000, "Não Respondeu"), COUNTIFS('Amanda Facundo'!$A$2:$A$4000, "<>", 'Amanda Facundo'!$N$2:$N$4000, ">01/10/2025", 'Amanda Facundo'!$N$2:$N$4000, "<01/11/2025", 'Amanda Facundo'!$G$2:$G$4000, "Não Respondeu"), COUNTIFS('Rodrigo Oliveira'!$A$2:$A$4000, "<>", 'Rodrigo Oliveira'!$N$2:$N$4000, ">01/10/2025", 'Rodrigo Oliveira'!$N$2:$N$4000, "<01/11/2025", 'Rodrigo Oliveira'!$G$2:$G$4000, "Não Respondeu"), COUNTIFS('Marcio Jorge'!$A$2:$A$4000, "<>", 'Marcio Jorge'!$N$2:$N$4000, ">01/10/2025", 'Marcio Jorge'!$N$2:$N$4000, "<01/11/2025", 'Marcio Jorge'!$G$2:$G$4000, "Não Respondeu"), COUNTIFS(Anteriores!$A$2:$A$3998, "<>", Anteriores!$N$2:$N$3998, ">01/10/2025", Anteriores!$N$2:$N$3998, "<01/11/2025", Anteriores!$G$2:$G$3998, "Não Respondeu"), COUNTIFS('Corretor 1'!$A$2:$A$4000, "<>", 'Corretor 1'!$N$2:$N$4000, ">01/10/2025", 'Corretor 1'!$N$2:$N$4000, "<01/11/2025", 'Corretor 1'!$G$2:$G$4000, "Não Respondeu"), COUNTIFS('Corretor 2'!$A$2:$A$4000, "<>", 'Corretor 2'!$N$2:$N$4000, ">01/10/2025", 'Corretor 2'!$N$2:$N$4000, "<01/11/2025", 'Corretor 2'!$G$2:$G$4000, "Não Respondeu"), COUNTIFS('Corretor 3'!$A$2:$A$4000, "<>", 'Corretor 3'!$N$2:$N$4000, ">01/10/2025", 'Corretor 3'!$N$2:$N$4000, "<01/11/2025", 'Corretor 3'!$G$2:$G$4000, "Não Respondeu"), COUNTIFS('Corretor 4'!$A$2:$A$4000, "<>", 'Corretor 4'!$N$2:$N$4000, ">01/10/2025", 'Corretor 4'!$N$2:$N$4000, "<01/11/2025", 'Corretor 4'!$G$2:$G$4000, "Não Respondeu"), COUNTIFS('Corretor 5'!$A$2:$A$4000, "<>", 'Corretor 5'!$N$2:$N$4000, ">01/10/2025", 'Corretor 5'!$N$2:$N$4000, "<01/11/2025", 'Corretor 5'!$G$2:$G$4000, "Não Respondeu") ) -> 428 | AX5: =SUM( SUMIFS('Bruna Mamedes'!$H$2:$H$4000, 'Bruna Mamedes'!$G$2:$G$4000, "Plano Fechado", 'Bruna Mamedes'!$N$2:$N$4000, ">=01/10/2025", 'Bruna Mamedes'!$N$2:$N$4000, "<=31/10/2025"), SUMIFS('Camila Adão'!$H$2:$H$1997, 'Camila Adão'!$G$2:$G$1997, "Plano Fechado", 'Camila Adão'!$N$2:$N$1997, ">=01/10/2025", 'Camila Adão'!$N$2:$N$1997, "<=31/10/2025"), SUMIFS('Vendas Organicas'!$H$2:$H$3000, 'Vendas Organicas'!$G$2:$G$3000, "Plano Fechado", 'Vendas Organicas'!$N$2:$N$3000, ">=01/10/2025", 'Vendas Organicas'!$N$2:$N$3000, "<=31/10/2025"), SUMIFS('Diogo Lima'!$H$2:$H$1996, 'Diogo Lima'!$G$2:$G$1996, "Plano Fechado", 'Diogo Lima'!$N$2:$N$1996, ">=01/10/2025", 'Diogo Lima'!$N$2:$N$1996, "<=31/10/2025"), SUMIFS('Lucas Almeida'!$H$2:$H$4000, 'Lucas Almeida'!$G$2:$G$4000, "Plano Fechado", 'Lucas Almeida'!$N$2:$N$4000, ">=01/10/2025", 'Lucas Almeida'!$N$2:$N$4000, "<=31/10/2025"), SUMIFS('Fernando Diamantino'!$H$2:$H$1999, 'Fernando Diamantino'!$G$2:$G$1999, "Plano Fechado", 'Fernando Diamantino'!$N$2:$N$1999, ">=01/10/2025", 'Fernando Diamantino'!$N$2:$N$1999, "<=31/10/2025"), SUMIFS('Maiara Andrade'!$H$2:$H$4000, 'Maiara Andrade'!$G$2:$G$4000, "Plano Fechado", 'Maiara Andrade'!$N$2:$N$4000, ">=01/10/2025", 'Maiara Andrade'!$N$2:$N$4000, "<=31/10/2025"), SUMIFS('Roberto Ramos'!$H$2:$H$4000, 'Roberto Ramos'!$G$2:$G$4000, "Plano Fechado", 'Roberto Ramos'!$N$2:$N$4000, ">=01/10/2025", 'Roberto Ramos'!$N$2:$N$4000, "<=31/10/2025"), SUMIFS('Amanda Facundo'!$H$2:$H$1999, 'Amanda Facundo'!$G$2:$G$1999, "Plano Fechado", 'Amanda Facundo'!$N$2:$N$1999, ">=01/10/2025", 'Amanda Facundo'!$N$2:$N$1999, "<=31/10/2025"), SUMIFS('Rodrigo Oliveira'!$H$2:$H$4000, 'Rodrigo Oliveira'!$G$2:$G$4000, "Plano Fechado", 'Rodrigo Oliveira'!$N$2:$N$4000, ">=01/10/2025", 'Rodrigo Oliveira'!$N$2:$N$4000, "<=31/10/2025"), SUMIFS(Anteriores!$H$2:$H$3998, Anteriores!$G$2:$G$3998, "Plano Fechado", Anteriores!$N$2:$N$3998, ">=01/10/2025", Anteriores!$N$2:$N$3998, "<=31/10/2025"), SUMIFS('Corretor 1'!$H$2:$H$4000, 'Corretor 1'!$G$2:$G$4000, "Plano Fechado", 'Corretor 1'!$N$2:$N$4000, ">=01/10/2025", 'Corretor 1'!$N$2:$N$4000, "<=31/10/2025"), SUMIFS('Corretor 2'!$H$2:$H$4000, 'Corretor 2'!$G$2:$G$4000, "Plano Fechado", 'Corretor 2'!$N$2:$N$4000, ">=01/10/2025", 'Corretor 2'!$N$2:$N$4000, "<=31/10/2025"), SUMIFS('Corretor 3'!$H$2:$H$4000, 'Corretor 3'!$G$2:$G$4000, "Plano Fechado", 'Corretor 3'!$N$2:$N$4000, ">=01/10/2025", 'Corretor 3'!$N$2:$N$4000, "<=31/10/2025"), SUMIFS('Corretor 4'!$H$2:$H$4000, 'Corretor 4'!$G$2:$G$4000, "Plano Fechado", 'Corretor 4'!$N$2:$N$4000, ">=01/10/2025", 'Corretor 4'!$N$2:$N$4000, "<=31/10/2025"), SUMIFS('Corretor 5'!$H$2:$H$4000, 'Corretor 5'!$G$2:$G$4000, "Plano Fechado", 'Corretor 5'!$N$2:$N$4000, ">=01/10/2025", 'Corretor 5'!$N$2:$N$4000, "<=31/10/2025") ) -> 77911.36
C6: 0.01 | D6: 0.097 | E6: 0.269 | F6: 0.045 | G6: 0.579 | K6: 0.045 | L6: 0.031 | M6: 0.26 | N6: 0.036 | O6: 0.49 | S6: 0.04 | T6: 0.035 | U6: 0.219 | V6: 0.026 | W6: 0.463 | AA6: 0.051 | AB6: 0.064 | AC6: 0.204 | AD6: 0.037 | AE6: 0.412 | AI6: 0.043 | AJ6: 0.05 | AK6: 0.281 | AL6: 0.037 | AM6: 0.398 | AQ6: =(AQ5/AP5) -> 0.036741214 | AR6: =AR5/AP5 -> 0.014376997 | AS6: =AS5/AP5 -> 0.0031948882 | AT6: =(AT5/AP5) -> 0.024760383 | AU6: =AU5/AP5 -> 0.21325879 | AV6: =AV5/AP5 -> 0.058306709 | AW6: =AW5/AP5 -> 0.34185304
B8: LEADS INSTAGRAM | J8: LEADS INSTAGRAM | R8: LEADS INSTAGRAM | Z8: LEADS INSTAGRAM | AH8: LEADS INSTAGRAM | AP8: LEADS INSTAGRAM
B9: QTD. Leads | C9: Vendas Fechadas | D9: Leads em Conversação | E9: Leads com Proposta Enviada | F9: Leads Desistentes | G9: Leads sem Resposta | H9: Faturamento | J9: QTD. Leads | K9: Vendas Fechadas | L9: Leads em Conversação | M9: Leads com Proposta Enviada | N9: Leads Desistentes | O9: Leads sem Resposta | P9: Faturamento | R9: QTD. Leads | S9: Vendas Fechadas | T9: Leads em Conversação | U9: Leads com Proposta Enviada | V9: Leads Desistentes | W9: Leads sem Resposta | X9: Faturamento | Z9: QTD. Leads | AA9: Vendas Fechadas | AB9: Leads em Conversação | AC9: Leads com Proposta Enviada | AD9: Leads Desistentes | AE9: Leads sem Resposta | AF9: Faturamento | AH9: QTD. Leads | AI9: Vendas Fechadas | AJ9: Leads em Conversação | AK9: Leads com Proposta Enviada | AL9: Leads Desistentes | AM9: Leads sem Resposta | AN9: Faturamento | AP9: QTD. Leads | AQ9: Plano Fechado | AR9: Em Análise | AS9: Aguardando Pagamento | AT9: Conversação | AU9: Proposta Enviada | AV9: Desistentes | AW9: Sem Resposta | AX9: Faturamento
B10: 63 | C10: 0 | D10: 8 | E10: 9 | F10: 8 | G10: 38 | H10: 0 | J10: 127 | K10: 1 | L10: 1 | M10: 20 | N10: 3 | O10: 72 | P10: 3290.03 | R10: 110 | S10: 0 | T10: 4 | U10: 20 | V10: 3 | W10: 83 | X10: 0 | Z10: 121 | AA10: 3 | AB10: 13 | AC10: 17 | AD10: 6 | AE10: 87 | AF10: 2752.86 | AH10: 196 | AI10: 2 | AJ10: 1 | AK10: 35 | AL10: 5 | AM10: 141 | AN10: 2552.51 | AP10: {=LET( abas, {"Amanda Facundo";"Bruna Mamedes";"Camila Adão";"Darlin Amorim";"Diogo Lima";"Externos";"Maiara Andrade";"Marcio Jorge";"Lucas Almeida";"Roberto Ramos";"Rodrigo Oliviera";"Leandro Nascimento";"Leandro Drumond";"Marcelle Marcela";"Anteriores";"Corretor 1";"Corretor 2";"Corretor 3";"Corretor 4";"Corretor 5"}, SUM( BYROW( abas, LAMBDA(a, COUNTIFS( INDIRECT("'"&a&"'!E:E"), "Instagram", INDIRECT("'"&a&"'!N:N"), ">="&DATE(2025,10,1), INDIRECT("'"&a&"'!N:N"), "<="&DATE(2025,10,31) ) ) ) ) )} -> 51 | AQ10: =SUM( COUNTIFS('Bruna Mamedes'!$E$2:$E$4000, "Instagram", 'Bruna Mamedes'!$G$2:$G$4000, "Plano Fechado", 'Bruna Mamedes'!$N$2:$N$4000, ">=01/10/2025", 'Bruna Mamedes'!$N$2:$N$4000, "<=31/10/2025"), COUNTIFS('Camila Adão'!$E$2:$E$1997, "Instagram", 'Camila Adão'!$G$2:$G$1997, "Plano Fechado", 'Camila Adão'!$N$2:$N$1997, ">=01/10/2025", 'Camila Adão'!$N$2:$N$1997, "<=31/10/2025"), COUNTIFS('Vendas Organicas'!$E$2:$E$3000, "Instagram", 'Vendas Organicas'!$G$2:$G$3000, "Plano Fechado", 'Vendas Organicas'!$N$2:$N$3000, ">=01/10/2025", 'Vendas Organicas'!$N$2:$N$3000, "<=31/10/2025"), COUNTIFS('Diogo Lima'!$E$2:$E$1996, "Instagram", 'Diogo Lima'!$G$2:$G$1996, "Plano Fechado", 'Diogo Lima'!$N$2:$N$1996, ">=01/10/2025", 'Diogo Lima'!$N$2:$N$1996, "<=31/10/2025"), COUNTIFS('Lucas Almeida'!$E$2:$E$4000, "Instagram", 'Lucas Almeida'!$G$2:$G$4000, "Plano Fechado", 'Lucas Almeida'!$N$2:$N$4000, ">=01/10/2025", 'Lucas Almeida'!$N$2:$N$4000, "<=31/10/2025"), COUNTIFS('Fernando Diamantino'!$E$2:$E$1999, "Instagram", 'Fernando Diamantino'!$G$2:$G$1999, "Plano Fechado", 'Fernando Diamantino'!$N$2:$N$1999, ">=01/10/2025", 'Fernando Diamantino'!$N$2:$N$1999, "<=31/10/2025"), COUNTIFS('Maiara Andrade'!$E$2:$E$4000, "Instagram", 'Maiara Andrade'!$G$2:$G$4000, "Plano Fechado", 'Maiara Andrade'!$N$2:$N$4000, ">=01/10/2025", 'Maiara Andrade'!$N$2:$N$4000, "<=31/10/2025"), COUNTIFS('Roberto Ramos'!$E$2:$E$4000, "Instagram", 'Roberto Ramos'!$G$2:$G$4000, "Plano Fechado", 'Roberto Ramos'!$N$2:$N$4000, ">=01/10/2025", 'Roberto Ramos'!$N$2:$N$4000, "<=31/10/2025"), COUNTIFS('Amanda Facundo'!$E$2:$E$1999, "Instagram", 'Amanda Facundo'!$G$2:$G$1999, "Plano Fechado", 'Amanda Facundo'!$N$2:$N$1999, ">=01/10/2025", 'Amanda Facundo'!$N$2:$N$1999, "<=31/10/2025"), COUNTIFS('Rodrigo Oliveira'!$E$2:$E$4000, "Instagram", 'Rodrigo Oliveira'!$G$2:$G$4000, "Plano Fechado", 'Rodrigo Oliveira'!$N$2:$N$4000, ">=01/10/2025", 'Rodrigo Oliveira'!$N$2:$N$4000, "<=31/10/2025"), COUNTIFS('Marcio Jorge'!$E$2:$E$4000, "Instagram", 'Marcio Jorge'!$G$2:$G$4000, "Plano Fechado", 'Marcio Jorge'!$N$2:$N$4000, ">=01/10/2025", 'Marcio Jorge'!$N$2:$N$4000, "<=31/10/2025") ) -> 1 | AR10: =SUM( COUNTIFS('Bruna Mamedes'!$E$2:$E$4000, "Instagram", 'Bruna Mamedes'!$G$2:$G$4000, "Em Análise", 'Bruna Mamedes'!$N$2:$N$4000, ">=01/10/2025", 'Bruna Mamedes'!$N$2:$N$4000, "<=31/10/2025"), COUNTIFS('Camila Adão'!$E$2:$E$1997, "Instagram", 'Camila Adão'!$G$2:$G$1997, "Em Análise", 'Camila Adão'!$N$2:$N$1997, ">=01/10/2025", 'Camila Adão'!$N$2:$N$1997, "<=31/10/2025"), COUNTIFS('Vendas Organicas'!$E$2:$E$3000, "Instagram", 'Vendas Organicas'!$G$2:$G$3000, "Em Análise", 'Vendas Organicas'!$N$2:$N$3000, ">=01/10/2025", 'Vendas Organicas'!$N$2:$N$3000, "<=31/10/2025"), COUNTIFS('Diogo Lima'!$E$2:$E$1996, "Instagram", 'Diogo Lima'!$G$2:$G$1996, "Em Análise", 'Diogo Lima'!$N$2:$N$1996, ">=01/10/2025", 'Diogo Lima'!$N$2:$N$1996, "<=31/10/2025"), COUNTIFS('Lucas Almeida'!$E$2:$E$4000, "Instagram", 'Lucas Almeida'!$G$2:$G$4000, "Em Análise", 'Lucas Almeida'!$N$2:$N$4000, ">=01/10/2025", 'Lucas Almeida'!$N$2:$N$4000, "<=31/10/2025"), COUNTIFS('Fernando Diamantino'!$E$2:$E$1999, "Instagram", 'Fernando Diamantino'!$G$2:$G$1999, "Em Análise", 'Fernando Diamantino'!$N$2:$N$1999, ">=01/10/2025", 'Fernando Diamantino'!$N$2:$N$1999, "<=31/10/2025"), COUNTIFS('Maiara Andrade'!$E$2:$E$4000, "Instagram", 'Maiara Andrade'!$G$2:$G$4000, "Em Análise", 'Maiara Andrade'!$N$2:$N$4000, ">=01/10/2025", 'Maiara Andrade'!$N$2:$N$4000, "<=31/10/2025"), COUNTIFS('Roberto Ramos'!$E$2:$E$4000, "Instagram", 'Roberto Ramos'!$G$2:$G$4000, "Em Análise", 'Roberto Ramos'!$N$2:$N$4000, ">=01/10/2025", 'Roberto Ramos'!$N$2:$N$4000, "<=31/10/2025"), COUNTIFS('Amanda Facundo'!$E$2:$E$1999, "Instagram", 'Amanda Facundo'!$G$2:$G$1999, "Em Análise", 'Amanda Facundo'!$N$2:$N$1999, ">=01/10/2025", 'Amanda Facundo'!$N$2:$N$1999, "<=31/10/2025"), COUNTIFS('Rodrigo Oliveira'!$E$2:$E$4000, "Instagram", 'Rodrigo Oliveira'!$G$2:$G$4000, "Em Análise", 'Rodrigo Oliveira'!$N$2:$N$4000, ">=01/10/2025", 'Rodrigo Oliveira'!$N$2:$N$4000, "<=31/10/2025"), COUNTIFS('Marcio Jorge'!$E$2:$E$4000, "Instagram", 'Marcio Jorge'!$G$2:$G$4000, "Em Análise", 'Marcio Jorge'!$N$2:$N$4000, ">=01/10/2025", 'Marcio Jorge'!$N$2:$N$4000, "<=31/10/2025") ) -> 0 | AS10: =SUM( COUNTIFS('Bruna Mamedes'!$E$2:$E$4000, "Instagram", 'Bruna Mamedes'!$G$2:$G$4000, "Aguardando Pagamento", 'Bruna Mamedes'!$N$2:$N$4000, ">=01/10/2025", 'Bruna Mamedes'!$N$2:$N$4000, "<=31/10/2025"), COUNTIFS('Camila Adão'!$E$2:$E$1997, "Instagram", 'Camila Adão'!$G$2:$G$1997, "Aguardando Pagamento", 'Camila Adão'!$N$2:$N$1997, ">=01/10/2025", 'Camila Adão'!$N$2:$N$1997, "<=31/10/2025"), COUNTIFS('Vendas Organicas'!$E$2:$E$3000, "Instagram", 'Vendas Organicas'!$G$2:$G$3000, "Aguardando Pagamento", 'Vendas Organicas'!$N$2:$N$3000, ">=01/10/2025", 'Vendas Organicas'!$N$2:$N$3000, "<=31/10/2025"), COUNTIFS('Diogo Lima'!$E$2:$E$1996, "Instagram", 'Diogo Lima'!$G$2:$G$1996, "Aguardando Pagamento", 'Diogo Lima'!$N$2:$N$1996, ">=01/10/2025", 'Diogo Lima'!$N$2:$N$1996, "<=31/10/2025"), COUNTIFS('Lucas Almeida'!$E$2:$E$4000, "Instagram", 'Lucas Almeida'!$G$2:$G$4000, "Aguardando Pagamento", 'Lucas Almeida'!$N$2:$N$4000, ">=01/10/2025", 'Lucas Almeida'!$N$2:$N$4000, "<=31/10/2025"), COUNTIFS('Fernando Diamantino'!$E$2:$E$1999, "Instagram", 'Fernando Diamantino'!$G$2:$G$1999, "Aguardando Pagamento", 'Fernando Diamantino'!$N$2:$N$1999, ">=01/10/2025", 'Fernando Diamantino'!$N$2:$N$1999, "<=31/10/2025"), COUNTIFS('Maiara Andrade'!$E$2:$E$4000, "Instagram", 'Maiara Andrade'!$G$2:$G$4000, "Aguardando Pagamento", 'Maiara Andrade'!$N$2:$N$4000, ">=01/10/2025", 'Maiara Andrade'!$N$2:$N$4000, "<=31/10/2025"), COUNTIFS('Roberto Ramos'!$E$2:$E$4000, "Instagram", 'Roberto Ramos'!$G$2:$G$4000, "Aguardando Pagamento", 'Roberto Ramos'!$N$2:$N$4000, ">=01/10/2025", 'Roberto Ramos'!$N$2:$N$4000, "<=31/10/2025"), COUNTIFS('Amanda Facundo'!$E$2:$E$1999, "Instagram", 'Amanda Facundo'!$G$2:$G$1999, "Aguardando Pagamento", 'Amanda Facundo'!$N$2:$N$1999, ">=01/10/2025", 'Amanda Facundo'!$N$2:$N$1999, "<=31/10/2025"), COUNTIFS('Rodrigo Oliveira'!$E$2:$E$4000, "Instagram", 'Rodrigo Oliveira'!$G$2:$G$4000, "Aguardando Pagamento", 'Rodrigo Oliveira'!$N$2:$N$4000, ">=01/10/2025", 'Rodrigo Oliveira'!$N$2:$N$4000, "<=31/10/2025"), COUNTIFS('Marcio Jorge'!$E$2:$E$4000, "Instagram", 'Marcio Jorge'!$G$2:$G$4000, "Aguardando Pagamento", 'Marcio Jorge'!$N$2:$N$4000, ">=01/10/2025", 'Marcio Jorge'!$N$2:$N$4000, "<=31/10/2025") ) -> 0 | AT10: =SUM( COUNTIFS('Bruna Mamedes'!$E$2:$E$4000, "Instagram", 'Bruna Mamedes'!$G$2:$G$4000, "Em conversação", 'Bruna Mamedes'!$N$2:$N$4000, ">=01/10/2025", 'Bruna Mamedes'!$N$2:$N$4000, "<=31/10/2025"), COUNTIFS('Camila Adão'!$E$2:$E$1997, "Instagram", 'Camila Adão'!$G$2:$G$1997, "Em conversação", 'Camila Adão'!$N$2:$N$1997, ">=01/10/2025", 'Camila Adão'!$N$2:$N$1997, "<=31/10/2025"), COUNTIFS('Vendas Organicas'!$E$2:$E$3000, "Instagram", 'Vendas Organicas'!$G$2:$G$3000, "Em conversação", 'Vendas Organicas'!$N$2:$N$3000, ">=01/10/2025", 'Vendas Organicas'!$N$2:$N$3000, "<=31/10/2025"), COUNTIFS('Diogo Lima'!$E$2:$E$1996, "Instagram", 'Diogo Lima'!$G$2:$G$1996, "Em conversação", 'Diogo Lima'!$N$2:$N$1996, ">=01/10/2025", 'Diogo Lima'!$N$2:$N$1996, "<=31/10/2025"), COUNTIFS('Lucas Almeida'!$E$2:$E$4000, "Instagram", 'Lucas Almeida'!$G$2:$G$4000, "Em conversação", 'Lucas Almeida'!$N$2:$N$4000, ">=01/10/2025", 'Lucas Almeida'!$N$2:$N$4000, "<=31/10/2025"), COUNTIFS('Fernando Diamantino'!$E$2:$E$1999, "Instagram", 'Fernando Diamantino'!$G$2:$G$1999, "Em conversação", 'Fernando Diamantino'!$N$2:$N$1999, ">=01/10/2025", 'Fernando Diamantino'!$N$2:$N$1999, "<=31/10/2025"), COUNTIFS('Maiara Andrade'!$E$2:$E$4000, "Instagram", 'Maiara Andrade'!$G$2:$G$4000, "Em conversação", 'Maiara Andrade'!$N$2:$N$4000, ">=01/10/2025", 'Maiara Andrade'!$N$2:$N$4000, "<=31/10/2025"), COUNTIFS('Roberto Ramos'!$E$2:$E$4000, "Instagram", 'Roberto Ramos'!$G$2:$G$4000, "Em conversação", 'Roberto Ramos'!$N$2:$N$4000, ">=01/10/2025", 'Roberto Ramos'!$N$2:$N$4000, "<=31/10/2025"), COUNTIFS('Amanda Facundo'!$E$2:$E$1999, "Instagram", 'Amanda Facundo'!$G$2:$G$1999, "Em conversação", 'Amanda Facundo'!$N$2:$N$1999, ">=01/10/2025", 'Amanda Facundo'!$N$2:$N$1999, "<=31/10/2025"), COUNTIFS('Rodrigo Oliveira'!$E$2:$E$4000, "Instagram", 'Rodrigo Oliveira'!$G$2:$G$4000, "Em conversação", 'Rodrigo Oliveira'!$N$2:$N$4000, ">=01/10/2025", 'Rodrigo Oliveira'!$N$2:$N$4000, "<=31/10/2025"), COUNTIFS('Marcio Jorge'!$E$2:$E$4000, "Instagram", 'Marcio Jorge'!$G$2:$G$4000, "Em conversação", 'Marcio Jorge'!$N$2:$N$4000, ">=01/10/2025", 'Marcio Jorge'!$N$2:$N$4000, "<=31/10/2025") ) -> 0 | AU10: =SUM( COUNTIFS('Bruna Mamedes'!$E$2:$E$4000, "Instagram", 'Bruna Mamedes'!$G$2:$G$4000, "Cotação Enviada", 'Bruna Mamedes'!$N$2:$N$4000, ">=01/10/2025", 'Bruna Mamedes'!$N$2:$N$4000, "<=31/10/2025"), COUNTIFS('Camila Adão'!$E$2:$E$1997, "Instagram", 'Camila Adão'!$G$2:$G$1997, "Cotação Enviada", 'Camila Adão'!$N$2:$N$1997, ">=01/10/2025", 'Camila Adão'!$N$2:$N$1997, "<=31/10/2025"), COUNTIFS('Vendas Organicas'!$E$2:$E$3000, "Instagram", 'Vendas Organicas'!$G$2:$G$3000, "Cotação Enviada", 'Vendas Organicas'!$N$2:$N$3000, ">=01/10/2025", 'Vendas Organicas'!$N$2:$N$3000, "<=31/10/2025"), COUNTIFS('Diogo Lima'!$E$2:$E$1996, "Instagram", 'Diogo Lima'!$G$2:$G$1996, "Cotação Enviada", 'Diogo Lima'!$N$2:$N$1996, ">=01/10/2025", 'Diogo Lima'!$N$2:$N$1996, "<=31/10/2025"), COUNTIFS('Lucas Almeida'!$E$2:$E$4000, "Instagram", 'Lucas Almeida'!$G$2:$G$4000, "Cotação Enviada", 'Lucas Almeida'!$N$2:$N$4000, ">=01/10/2025", 'Lucas Almeida'!$N$2:$N$4000, "<=31/10/2025"), COUNTIFS('Fernando Diamantino'!$E$2:$E$1999, "Instagram", 'Fernando Diamantino'!$G$2:$G$1999, "Cotação Enviada", 'Fernando Diamantino'!$N$2:$N$1999, ">=01/10/2025", 'Fernando Diamantino'!$N$2:$N$1999, "<=31/10/2025"), COUNTIFS('Maiara Andrade'!$E$2:$E$4000, "Instagram", 'Maiara Andrade'!$G$2:$G$4000, "Cotação Enviada", 'Maiara Andrade'!$N$2:$N$4000, ">=01/10/2025", 'Maiara Andrade'!$N$2:$N$4000, "<=31/10/2025"), COUNTIFS('Roberto Ramos'!$E$2:$E$4000, "Instagram", 'Roberto Ramos'!$G$2:$G$4000, "Cotação Enviada", 'Roberto Ramos'!$N$2:$N$4000, ">=01/10/2025", 'Roberto Ramos'!$N$2:$N$4000, "<=31/10/2025"), COUNTIFS('Amanda Facundo'!$E$2:$E$1999, "Instagram", 'Amanda Facundo'!$G$2:$G$1999, "Cotação Enviada", 'Amanda Facundo'!$N$2:$N$1999, ">=01/10/2025", 'Amanda Facundo'!$N$2:$N$1999, "<=31/10/2025"), COUNTIFS('Rodrigo Oliveira'!$E$2:$E$4000, "Instagram", 'Rodrigo Oliveira'!$G$2:$G$4000, "Cotação Enviada", 'Rodrigo Oliveira'!$N$2:$N$4000, ">=01/10/2025", 'Rodrigo Oliveira'!$N$2:$N$4000, "<=31/10/2025"), COUNTIFS('Marcio Jorge'!$E$2:$E$4000, "Instagram", 'Marcio Jorge'!$G$2:$G$4000, "Cotação Enviada", 'Marcio Jorge'!$N$2:$N$4000, ">=01/10/2025", 'Marcio Jorge'!$N$2:$N$4000, "<=31/10/2025") ) -> 9 | AV10: =SUM( COUNTIFS('Bruna Mamedes'!$E$2:$E$4000, "Instagram", 'Bruna Mamedes'!$G$2:$G$4000, "Desistência", 'Bruna Mamedes'!$N$2:$N$4000, ">=01/10/2025", 'Bruna Mamedes'!$N$2:$N$4000, "<=31/10/2025"), COUNTIFS('Camila Adão'!$E$2:$E$1997, "Instagram", 'Camila Adão'!$G$2:$G$1997, "Desistência", 'Camila Adão'!$N$2:$N$1997, ">=01/10/2025", 'Camila Adão'!$N$2:$N$1997, "<=31/10/2025"), COUNTIFS('Vendas Organicas'!$E$2:$E$3000, "Instagram", 'Vendas Organicas'!$G$2:$G$3000, "Desistência", 'Vendas Organicas'!$N$2:$N$3000, ">=01/10/2025", 'Vendas Organicas'!$N$2:$N$3000, "<=31/10/2025"), COUNTIFS('Diogo Lima'!$E$2:$E$1996, "Instagram", 'Diogo Lima'!$G$2:$G$1996, "Desistência", 'Diogo Lima'!$N$2:$N$1996, ">=01/10/2025", 'Diogo Lima'!$N$2:$N$1996, "<=31/10/2025"), COUNTIFS('Lucas Almeida'!$E$2:$E$4000, "Instagram", 'Lucas Almeida'!$G$2:$G$4000, "Desistência", 'Lucas Almeida'!$N$2:$N$4000, ">=01/10/2025", 'Lucas Almeida'!$N$2:$N$4000, "<=31/10/2025"), COUNTIFS('Fernando Diamantino'!$E$2:$E$1999, "Instagram", 'Fernando Diamantino'!$G$2:$G$1999, "Desistência", 'Fernando Diamantino'!$N$2:$N$1999, ">=01/10/2025", 'Fernando Diamantino'!$N$2:$N$1999, "<=31/10/2025"), COUNTIFS('Maiara Andrade'!$E$2:$E$4000, "Instagram", 'Maiara Andrade'!$G$2:$G$4000, "Desistência", 'Maiara Andrade'!$N$2:$N$4000, ">=01/10/2025", 'Maiara Andrade'!$N$2:$N$4000, "<=31/10/2025"), COUNTIFS('Roberto Ramos'!$E$2:$E$4000, "Instagram", 'Roberto Ramos'!$G$2:$G$4000, "Desistência", 'Roberto Ramos'!$N$2:$N$4000, ">=01/10/2025", 'Roberto Ramos'!$N$2:$N$4000, "<=31/10/2025"), COUNTIFS('Amanda Facundo'!$E$2:$E$1999, "Instagram", 'Amanda Facundo'!$G$2:$G$1999, "Desistência", 'Amanda Facundo'!$N$2:$N$1999, ">=01/10/2025", 'Amanda Facundo'!$N$2:$N$1999, "<=31/10/2025"), COUNTIFS('Rodrigo Oliveira'!$E$2:$E$4000, "Instagram", 'Rodrigo Oliveira'!$G$2:$G$4000, "Desistência", 'Rodrigo Oliveira'!$N$2:$N$4000, ">=01/10/2025", 'Rodrigo Oliveira'!$N$2:$N$4000, "<=31/10/2025"), COUNTIFS('Marcio Jorge'!$E$2:$E$4000, "Instagram", 'Marcio Jorge'!$G$2:$G$4000, "Desistência", 'Marcio Jorge'!$N$2:$N$4000, ">=01/10/2025", 'Marcio Jorge'!$N$2:$N$4000, "<=31/10/2025") ) -> 2 | AW10: =SUM( COUNTIFS('Bruna Mamedes'!$E$2:$E$4000, "Instagram", 'Bruna Mamedes'!$G$2:$G$4000, "Não Respondeu", 'Bruna Mamedes'!$N$2:$N$4000, ">=01/10/2025", 'Bruna Mamedes'!$N$2:$N$4000, "<=31/10/2025"), COUNTIFS('Camila Adão'!$E$2:$E$1997, "Instagram", 'Camila Adão'!$G$2:$G$1997, "Não Respondeu", 'Camila Adão'!$N$2:$N$1997, ">=01/10/2025", 'Camila Adão'!$N$2:$N$1997, "<=31/10/2025"), COUNTIFS('Vendas Organicas'!$E$2:$E$3000, "Instagram", 'Vendas Organicas'!$G$2:$G$3000, "Não Respondeu", 'Vendas Organicas'!$N$2:$N$3000, ">=01/10/2025", 'Vendas Organicas'!$N$2:$N$3000, "<=31/10/2025"), COUNTIFS('Diogo Lima'!$E$2:$E$1996, "Instagram", 'Diogo Lima'!$G$2:$G$1996, "Não Respondeu", 'Diogo Lima'!$N$2:$N$1996, ">=01/10/2025", 'Diogo Lima'!$N$2:$N$1996, "<=31/10/2025"), COUNTIFS('Lucas Almeida'!$E$2:$E$4000, "Instagram", 'Lucas Almeida'!$G$2:$G$4000, "Não Respondeu", 'Lucas Almeida'!$N$2:$N$4000, ">=01/10/2025", 'Lucas Almeida'!$N$2:$N$4000, "<=31/10/2025"), COUNTIFS('Fernando Diamantino'!$E$2:$E$1999, "Instagram", 'Fernando Diamantino'!$G$2:$G$1999, "Não Respondeu", 'Fernando Diamantino'!$N$2:$N$1999, ">=01/10/2025", 'Fernando Diamantino'!$N$2:$N$1999, "<=31/10/2025"), COUNTIFS('Maiara Andrade'!$E$2:$E$4000, "Instagram", 'Maiara Andrade'!$G$2:$G$4000, "Não Respondeu", 'Maiara Andrade'!$N$2:$N$4000, ">=01/10/2025", 'Maiara Andrade'!$N$2:$N$4000, "<=31/10/2025"), COUNTIFS('Roberto Ramos'!$E$2:$E$4000, "Instagram", 'Roberto Ramos'!$G$2:$G$4000, "Não Respondeu", 'Roberto Ramos'!$N$2:$N$4000, ">=01/10/2025", 'Roberto Ramos'!$N$2:$N$4000, "<=31/10/2025"), COUNTIFS('Amanda Facundo'!$E$2:$E$1999, "Instagram", 'Amanda Facundo'!$G$2:$G$1999, "Não Respondeu", 'Amanda Facundo'!$N$2:$N$1999, ">=01/10/2025", 'Amanda Facundo'!$N$2:$N$1999, "<=31/10/2025"), COUNTIFS('Rodrigo Oliveira'!$E$2:$E$4000, "Instagram", 'Rodrigo Oliveira'!$G$2:$G$4000, "Não Respondeu", 'Rodrigo Oliveira'!$N$2:$N$4000, ">=01/10/2025", 'Rodrigo Oliveira'!$N$2:$N$4000, "<=31/10/2025"), COUNTIFS('Marcio Jorge'!$E$2:$E$4000, "Instagram", 'Marcio Jorge'!$G$2:$G$4000, "Não Respondeu", 'Marcio Jorge'!$N$2:$N$4000, ">=01/10/2025", 'Marcio Jorge'!$N$2:$N$4000, "<=31/10/2025") ) -> 34 | AX10: =SUM( SUMIFS('Bruna Mamedes'!$H$2:$H$4000, 'Bruna Mamedes'!$E$2:$E$4000, "Instagram", 'Bruna Mamedes'!$G$2:$G$4000, "Plano Fechado", 'Bruna Mamedes'!$N$2:$N$4000, ">=01/10/2025", 'Bruna Mamedes'!$N$2:$N$4000, "<=31/10/2025"), SUMIFS('Camila Adão'!$H$2:$H$1997, 'Camila Adão'!$E$2:$E$1997, "Instagram", 'Camila Adão'!$G$2:$G$1997, "Plano Fechado", 'Camila Adão'!$N$2:$N$1997, ">=01/10/2025", 'Camila Adão'!$N$2:$N$1997, "<=31/10/2025"), SUMIFS('Vendas Organicas'!$H$2:$H$3000, 'Vendas Organicas'!$E$2:$E$3000, "Instagram", 'Vendas Organicas'!$G$2:$G$3000, "Plano Fechado", 'Vendas Organicas'!$N$2:$N$3000, ">=01/10/2025", 'Vendas Organicas'!$N$2:$N$3000, "<=31/10/2025"), SUMIFS('Diogo Lima'!$H$2:$H$1996, 'Diogo Lima'!$E$2:$E$1996, "Instagram", 'Diogo Lima'!$G$2:$G$1996, "Plano Fechado", 'Diogo Lima'!$N$2:$N$1996, ">=01/10/2025", 'Diogo Lima'!$N$2:$N$1996, "<=31/10/2025"), SUMIFS('Lucas Almeida'!$H$2:$H$4000, 'Lucas Almeida'!$E$2:$E$4000, "Instagram", 'Lucas Almeida'!$G$2:$G$4000, "Plano Fechado", 'Lucas Almeida'!$N$2:$N$4000, ">=01/10/2025", 'Lucas Almeida'!$N$2:$N$4000, "<=31/10/2025"), SUMIFS('Fernando Diamantino'!$H$2:$H$1999, 'Fernando Diamantino'!$E$2:$E$1999, "Instagram", 'Fernando Diamantino'!$G$2:$G$1999, "Plano Fechado", 'Fernando Diamantino'!$N$2:$N$1999, ">=01/10/2025", 'Fernando Diamantino'!$N$2:$N$1999, "<=31/10/2025"), SUMIFS('Maiara Andrade'!$H$2:$H$4000, 'Maiara Andrade'!$E$2:$E$4000, "Instagram", 'Maiara Andrade'!$G$2:$G$4000, "Plano Fechado", 'Maiara Andrade'!$N$2:$N$4000, ">=01/10/2025", 'Maiara Andrade'!$N$2:$N$4000, "<=31/10/2025"), SUMIFS('Roberto Ramos'!$H$2:$H$4000, 'Roberto Ramos'!$E$2:$E$4000, "Instagram", 'Roberto Ramos'!$G$2:$G$4000, "Plano Fechado", 'Roberto Ramos'!$N$2:$N$4000, ">=01/10/2025", 'Roberto Ramos'!$N$2:$N$4000, "<=31/10/2025"), SUMIFS('Amanda Facundo'!$H$2:$H$1999, 'Amanda Facundo'!$E$2:$E$1999, "Instagram", 'Amanda Facundo'!$G$2:$G$1999, "Plano Fechado", 'Amanda Facundo'!$N$2:$N$1999, ">=01/10/2025", 'Amanda Facundo'!$N$2:$N$1999, "<=31/10/2025"), SUMIFS('Rodrigo Oliveira'!$H$2:$H$4000, 'Rodrigo Oliveira'!$E$2:$E$4000, "Instagram", 'Rodrigo Oliveira'!$G$2:$G$4000, "Plano Fechado", 'Rodrigo Oliveira'!$N$2:$N$4000, ">=01/10/2025", 'Rodrigo Oliveira'!$N$2:$N$4000, "<=31/10/2025"), SUMIFS('Marcio Jorge'!$H$2:$H$4000, 'Marcio Jorge'!$E$2:$E$4000, "Instagram", 'Marcio Jorge'!$G$2:$G$4000, "Plano Fechado", 'Marcio Jorge'!$N$2:$N$4000, ">=01/10/2025", 'Marcio Jorge'!$N$2:$N$4000, "<=31/10/2025") ) -> 2276.52
C11: 0 | D11: 0.127 | E11: 0.143 | F11: 0.127 | G11: 0.603 | K11: 0.008 | L11: 0.008 | M11: 0.157 | N11: 0.024 | O11: 0.567 | S11: 0 | T11: 0.036 | U11: 0.182 | V11: 0.027 | W11: 0.755 | AA11: 0.025 | AB11: 0.107 | AC11: 0.14 | AD11: 0.05 | AE11: 0.719 | AI11: 0.01 | AJ11: 0.005 | AK11: 0.179 | AL11: 0.026 | AM11: 0.719 | AQ11: =(AQ10/AP10) -> 0.019607843 | AR11: =(AR10/AP10) -> 0 | AS11: =(AS10/AP10) -> 0 | AT11: =(AT10/AP10) -> 0 | AU11: =AU10/AP10 -> 0.17647059 | AV11: =AV10/AP10 -> 0.039215686 | AW11: =AW10/AP10 -> 0.66666667
B13: LEADS FACEBOOK | J13: LEADS FACEBOOK | R13: LEADS FACEBOOK | Z13: LEADS FACEBOOK | AH13: LEADS FACEBOOK | AP13: LEADS FACEBOOK
B14: QTD. Leads | C14: Vendas Fechadas | D14: Leads em Conversação | E14: Leads com Proposta Enviada | F14: Leads Desistentes | G14: Leads sem Resposta | H14: Faturamento | J14: QTD. Leads | K14: Vendas Fechadas | L14: Leads em Conversação | M14: Leads com Proposta Enviada | N14: Leads Desistentes | O14: Leads sem Resposta | P14: Faturamento | R14: QTD. Leads | S14: Vendas Fechadas | T14: Leads em Conversação | U14: Leads com Proposta Enviada | V14: Leads Desistentes | W14: Leads sem Resposta | X14: Faturamento | Z14: QTD. Leads | AA14: Vendas Fechadas | AB14: Leads em Conversação | AC14: Leads com Proposta Enviada | AD14: Leads Desistentes | AE14: Leads sem Resposta | AF14: Faturamento | AH14: QTD. Leads | AI14: Vendas Fechadas | AJ14: Leads em Conversação | AK14: Leads com Proposta Enviada | AL14: Leads Desistentes | AM14: Leads sem Resposta | AN14: Faturamento | AP14: QTD. Leads | AQ14: Plano Fechado | AR14: Em Análise | AS14: Aguardando Pagamento | AT14: Conversação | AU14: Proposta Enviada | AV14: Desistentes | AW14: Sem Resposta | AX14: Faturamento
B15: 38 | C15: 0 | D15: 3 | E15: 5 | F15: 0 | G15: 30 | H15: 0 | J15: 46 | K15: 2 | L15: 1 | M15: 5 | N15: 2 | O15: 29 | P15: 2245.61 | R15: 44 | S15: 0 | T15: 0 | U15: 7 | V15: 0 | W15: 37 | X15: 0 | Z15: 50 | AA15: 2 | AB15: 1 | AC15: 5 | AD15: 4 | AE15: 31 | AF15: 457.88 | AH15: 76 | AI15: 1 | AJ15: 2 | AK15: 8 | AL15: 3 | AM15: 53 | AN15: 649.71 | AP15: {=LET( abas, {"Amanda Facundo";"Bruna Mamedes";"Camila Adão";"Darlin Amorim";"Diogo Lima";"Externos";"Maiara Andrade";"Marcio Jorge";"Lucas Almeida";"Roberto Ramos";"Rodrigo Oliviera";"Leandro Nascimento";"Leandro Drumond";"Marcelle Marcela";"Anteriores";"Corretor 1";"Corretor 2";"Corretor 3";"Corretor 4";"Corretor 5"}, SUM( BYROW( abas, LAMBDA(a, COUNTIFS( INDIRECT("'"&a&"'!E:E"), "Facebook", INDIRECT("'"&a&"'!N:N"), ">="&DATE(2025,10,1), INDIRECT("'"&a&"'!N:N"), "<="&DATE(2025,10,31) ) ) ) ) )} -> 14 | AQ15: =SUM( COUNTIFS('Bruna Mamedes'!$E$2:$E$4000, "Facebook", 'Bruna Mamedes'!$G$2:$G$4000, "Plano Fechado", 'Bruna Mamedes'!$N$2:$N$4000, ">=01/10/2025", 'Bruna Mamedes'!$N$2:$N$4000, "<=31/10/2025"), COUNTIFS('Camila Adão'!$E$2:$E$1997, "Facebook", 'Camila Adão'!$G$2:$G$1997, "Plano Fechado", 'Camila Adão'!$N$2:$N$1997, ">=01/10/2025", 'Camila Adão'!$N$2:$N$1997, "<=31/10/2025"), COUNTIFS('Vendas Organicas'!$E$2:$E$3000, "Facebook", 'Vendas Organicas'!$G$2:$G$3000, "Plano Fechado", 'Vendas Organicas'!$N$2:$N$3000, ">=01/10/2025", 'Vendas Organicas'!$N$2:$N$3000, "<=31/10/2025"), COUNTIFS('Diogo Lima'!$E$2:$E$1996, "Facebook", 'Diogo Lima'!$G$2:$G$1996, "Plano Fechado", 'Diogo Lima'!$N$2:$N$1996, ">=01/10/2025", 'Diogo Lima'!$N$2:$N$1996, "<=31/10/2025"), COUNTIFS('Lucas Almeida'!$E$2:$E$4000, "Facebook", 'Lucas Almeida'!$G$2:$G$4000, "Plano Fechado", 'Lucas Almeida'!$N$2:$N$4000, ">=01/10/2025", 'Lucas Almeida'!$N$2:$N$4000, "<=31/10/2025"), COUNTIFS('Fernando Diamantino'!$E$2:$E$1999, "Facebook", 'Fernando Diamantino'!$G$2:$G$1999, "Plano Fechado", 'Fernando Diamantino'!$N$2:$N$1999, ">=01/10/2025", 'Fernando Diamantino'!$N$2:$N$1999, "<=31/10/2025"), COUNTIFS('Maiara Andrade'!$E$2:$E$4000, "Facebook", 'Maiara Andrade'!$G$2:$G$4000, "Plano Fechado", 'Maiara Andrade'!$N$2:$N$4000, ">=01/10/2025", 'Maiara Andrade'!$N$2:$N$4000, "<=31/10/2025"), COUNTIFS('Roberto Ramos'!$E$2:$E$4000, "Facebook", 'Roberto Ramos'!$G$2:$G$4000, "Plano Fechado", 'Roberto Ramos'!$N$2:$N$4000, ">=01/10/2025", 'Roberto Ramos'!$N$2:$N$4000, "<=31/10/2025"), COUNTIFS('Amanda Facundo'!$E$2:$E$1999, "Facebook", 'Amanda Facundo'!$G$2:$G$1999, "Plano Fechado", 'Amanda Facundo'!$N$2:$N$1999, ">=01/10/2025", 'Amanda Facundo'!$N$2:$N$1999, "<=31/10/2025"), COUNTIFS('Rodrigo Oliveira'!$E$2:$E$4000, "Facebook", 'Rodrigo Oliveira'!$G$2:$G$4000, "Plano Fechado", 'Rodrigo Oliveira'!$N$2:$N$4000, ">=01/10/2025", 'Rodrigo Oliveira'!$N$2:$N$4000, "<=31/10/2025"), COUNTIFS('Marcio Jorge'!$E$2:$E$4000, "Facebook", 'Marcio Jorge'!$G$2:$G$4000, "Plano Fechado", 'Marcio Jorge'!$N$2:$N$4000, ">=01/10/2025", 'Marcio Jorge'!$N$2:$N$4000, "<=31/10/2025") ) -> 1 | AR15: =SUM( COUNTIFS('Bruna Mamedes'!$E$2:$E$4000, "Facebook", 'Bruna Mamedes'!$G$2:$G$4000, "Em Análise", 'Bruna Mamedes'!$N$2:$N$4000, ">=01/10/2025", 'Bruna Mamedes'!$N$2:$N$4000, "<=31/10/2025"), COUNTIFS('Camila Adão'!$E$2:$E$1997, "Facebook", 'Camila Adão'!$G$2:$G$1997, "Em Análise", 'Camila Adão'!$N$2:$N$1997, ">=01/10/2025", 'Camila Adão'!$N$2:$N$1997, "<=31/10/2025"), COUNTIFS('Vendas Organicas'!$E$2:$E$3000, "Facebook", 'Vendas Organicas'!$G$2:$G$3000, "Em Análise", 'Vendas Organicas'!$N$2:$N$3000, ">=01/10/2025", 'Vendas Organicas'!$N$2:$N$3000, "<=31/10/2025"), COUNTIFS('Diogo Lima'!$E$2:$E$1996, "Facebook", 'Diogo Lima'!$G$2:$G$1996, "Em Análise", 'Diogo Lima'!$N$2:$N$1996, ">=01/10/2025", 'Diogo Lima'!$N$2:$N$1996, "<=31/10/2025"), COUNTIFS('Lucas Almeida'!$E$2:$E$4000, "Facebook", 'Lucas Almeida'!$G$2:$G$4000, "Em Análise", 'Lucas Almeida'!$N$2:$N$4000, ">=01/10/2025", 'Lucas Almeida'!$N$2:$N$4000, "<=31/10/2025"), COUNTIFS('Fernando Diamantino'!$E$2:$E$1999, "Facebook", 'Fernando Diamantino'!$G$2:$G$1999, "Em Análise", 'Fernando Diamantino'!$N$2:$N$1999, ">=01/10/2025", 'Fernando Diamantino'!$N$2:$N$1999, "<=31/10/2025"), COUNTIFS('Maiara Andrade'!$E$2:$E$4000, "Facebook", 'Maiara Andrade'!$G$2:$G$4000, "Em Análise", 'Maiara Andrade'!$N$2:$N$4000, ">=01/10/2025", 'Maiara Andrade'!$N$2:$N$4000, "<=31/10/2025"), COUNTIFS('Roberto Ramos'!$E$2:$E$4000, "Facebook", 'Roberto Ramos'!$G$2:$G$4000, "Em Análise", 'Roberto Ramos'!$N$2:$N$4000, ">=01/10/2025", 'Roberto Ramos'!$N$2:$N$4000, "<=31/10/2025"), COUNTIFS('Amanda Facundo'!$E$2:$E$1999, "Facebook", 'Amanda Facundo'!$G$2:$G$1999, "Em Análise", 'Amanda Facundo'!$N$2:$N$1999, ">=01/10/2025", 'Amanda Facundo'!$N$2:$N$1999, "<=31/10/2025"), COUNTIFS('Rodrigo Oliveira'!$E$2:$E$4000, "Facebook", 'Rodrigo Oliveira'!$G$2:$G$4000, "Em Análise", 'Rodrigo Oliveira'!$N$2:$N$4000, ">=01/10/2025", 'Rodrigo Oliveira'!$N$2:$N$4000, "<=31/10/2025"), COUNTIFS('Marcio Jorge'!$E$2:$E$4000, "Facebook", 'Marcio Jorge'!$G$2:$G$4000, "Em Análise", 'Marcio Jorge'!$N$2:$N$4000, ">=01/10/2025", 'Marcio Jorge'!$N$2:$N$4000, "<=31/10/2025") ) -> 0 | AS15: =SUM( COUNTIFS('Bruna Mamedes'!$E$2:$E$4000, "Facebook", 'Bruna Mamedes'!$G$2:$G$4000, "Aguardando Pagamento", 'Bruna Mamedes'!$N$2:$N$4000, ">=01/10/2025", 'Bruna Mamedes'!$N$2:$N$4000, "<=31/10/2025"), COUNTIFS('Camila Adão'!$E$2:$E$1997, "Facebook", 'Camila Adão'!$G$2:$G$1997, "Aguardando Pagamento", 'Camila Adão'!$N$2:$N$1997, ">=01/10/2025", 'Camila Adão'!$N$2:$N$1997, "<=31/10/2025"), COUNTIFS('Vendas Organicas'!$E$2:$E$3000, "Facebook", 'Vendas Organicas'!$G$2:$G$3000, "Aguardando Pagamento", 'Vendas Organicas'!$N$2:$N$3000, ">=01/10/2025", 'Vendas Organicas'!$N$2:$N$3000, "<=31/10/2025"), COUNTIFS('Diogo Lima'!$E$2:$E$1996, "Facebook", 'Diogo Lima'!$G$2:$G$1996, "Aguardando Pagamento", 'Diogo Lima'!$N$2:$N$1996, ">=01/10/2025", 'Diogo Lima'!$N$2:$N$1996, "<=31/10/2025"), COUNTIFS('Lucas Almeida'!$E$2:$E$4000, "Facebook", 'Lucas Almeida'!$G$2:$G$4000, "Aguardando Pagamento", 'Lucas Almeida'!$N$2:$N$4000, ">=01/10/2025", 'Lucas Almeida'!$N$2:$N$4000, "<=31/10/2025"), COUNTIFS('Fernando Diamantino'!$E$2:$E$1999, "Facebook", 'Fernando Diamantino'!$G$2:$G$1999, "Aguardando Pagamento", 'Fernando Diamantino'!$N$2:$N$1999, ">=01/10/2025", 'Fernando Diamantino'!$N$2:$N$1999, "<=31/10/2025"), COUNTIFS('Maiara Andrade'!$E$2:$E$4000, "Facebook", 'Maiara Andrade'!$G$2:$G$4000, "Aguardando Pagamento", 'Maiara Andrade'!$N$2:$N$4000, ">=01/10/2025", 'Maiara Andrade'!$N$2:$N$4000, "<=31/10/2025"), COUNTIFS('Roberto Ramos'!$E$2:$E$4000, "Facebook", 'Roberto Ramos'!$G$2:$G$4000, "Aguardando Pagamento", 'Roberto Ramos'!$N$2:$N$4000, ">=01/10/2025", 'Roberto Ramos'!$N$2:$N$4000, "<=31/10/2025"), COUNTIFS('Amanda Facundo'!$E$2:$E$1999, "Facebook", 'Amanda Facundo'!$G$2:$G$1999, "Aguardando Pagamento", 'Amanda Facundo'!$N$2:$N$1999, ">=01/10/2025", 'Amanda Facundo'!$N$2:$N$1999, "<=31/10/2025"), COUNTIFS('Rodrigo Oliveira'!$E$2:$E$4000, "Facebook", 'Rodrigo Oliveira'!$G$2:$G$4000, "Aguardando Pagamento", 'Rodrigo Oliveira'!$N$2:$N$4000, ">=01/10/2025", 'Rodrigo Oliveira'!$N$2:$N$4000, "<=31/10/2025"), COUNTIFS('Marcio Jorge'!$E$2:$E$4000, "Facebook", 'Marcio Jorge'!$G$2:$G$4000, "Aguardando Pagamento", 'Marcio Jorge'!$N$2:$N$4000, ">=01/10/2025", 'Marcio Jorge'!$N$2:$N$4000, "<=31/10/2025") ) -> 0 | AT15: =SUM( COUNTIFS('Bruna Mamedes'!$E$2:$E$4000, "Facebook", 'Bruna Mamedes'!$G$2:$G$4000, "Em conversação", 'Bruna Mamedes'!$N$2:$N$4000, ">=01/10/2025", 'Bruna Mamedes'!$N$2:$N$4000, "<=31/10/2025"), COUNTIFS('Camila Adão'!$E$2:$E$1997, "Facebook", 'Camila Adão'!$G$2:$G$1997, "Em conversação", 'Camila Adão'!$N$2:$N$1997, ">=01/10/2025", 'Camila Adão'!$N$2:$N$1997, "<=31/10/2025"), COUNTIFS('Vendas Organicas'!$E$2:$E$3000, "Facebook", 'Vendas Organicas'!$G$2:$G$3000, "Em conversação", 'Vendas Organicas'!$N$2:$N$3000, ">=01/10/2025", 'Vendas Organicas'!$N$2:$N$3000, "<=31/10/2025"), COUNTIFS('Diogo Lima'!$E$2:$E$1996, "Facebook", 'Diogo Lima'!$G$2:$G$1996, "Em conversação", 'Diogo Lima'!$N$2:$N$1996, ">=01/10/2025", 'Diogo Lima'!$N$2:$N$1996, "<=31/10/2025"), COUNTIFS('Lucas Almeida'!$E$2:$E$4000, "Facebook", 'Lucas Almeida'!$G$2:$G$4000, "Em conversação", 'Lucas Almeida'!$N$2:$N$4000, ">=01/10/2025", 'Lucas Almeida'!$N$2:$N$4000, "<=31/10/2025"), COUNTIFS('Fernando Diamantino'!$E$2:$E$1999, "Facebook", 'Fernando Diamantino'!$G$2:$G$1999, "Em conversação", 'Fernando Diamantino'!$N$2:$N$1999, ">=01/10/2025", 'Fernando Diamantino'!$N$2:$N$1999, "<=31/10/2025"), COUNTIFS('Maiara Andrade'!$E$2:$E$4000, "Facebook", 'Maiara Andrade'!$G$2:$G$4000, "Em conversação", 'Maiara Andrade'!$N$2:$N$4000, ">=01/10/2025", 'Maiara Andrade'!$N$2:$N$4000, "<=31/10/2025"), COUNTIFS('Roberto Ramos'!$E$2:$E$4000, "Facebook", 'Roberto Ramos'!$G$2:$G$4000, "Em conversação", 'Roberto Ramos'!$N$2:$N$4000, ">=01/10/2025", 'Roberto Ramos'!$N$2:$N$4000, "<=31/10/2025"), COUNTIFS('Amanda Facundo'!$E$2:$E$1999, "Facebook", 'Amanda Facundo'!$G$2:$G$1999, "Em conversação", 'Amanda Facundo'!$N$2:$N$1999, ">=01/10/2025", 'Amanda Facundo'!$N$2:$N$1999, "<=31/10/2025"), COUNTIFS('Rodrigo Oliveira'!$E$2:$E$4000, "Facebook", 'Rodrigo Oliveira'!$G$2:$G$4000, "Em conversação", 'Rodrigo Oliveira'!$N$2:$N$4000, ">=01/10/2025", 'Rodrigo Oliveira'!$N$2:$N$4000, "<=31/10/2025"), COUNTIFS('Marcio Jorge'!$E$2:$E$4000, "Facebook", 'Marcio Jorge'!$G$2:$G$4000, "Em conversação", 'Marcio Jorge'!$N$2:$N$4000, ">=01/10/2025", 'Marcio Jorge'!$N$2:$N$4000, "<=31/10/2025") ) -> 1 | AU15: =SUM( COUNTIFS('Bruna Mamedes'!$E$2:$E$4000, "Facebook", 'Bruna Mamedes'!$G$2:$G$4000, "Cotação Enviada", 'Bruna Mamedes'!$N$2:$N$4000, ">=01/10/2025", 'Bruna Mamedes'!$N$2:$N$4000, "<=31/10/2025"), COUNTIFS('Camila Adão'!$E$2:$E$1997, "Facebook", 'Camila Adão'!$G$2:$G$1997, "Cotação Enviada", 'Camila Adão'!$N$2:$N$1997, ">=01/10/2025", 'Camila Adão'!$N$2:$N$1997, "<=31/10/2025"), COUNTIFS('Vendas Organicas'!$E$2:$E$3000, "Facebook", 'Vendas Organicas'!$G$2:$G$3000, "Cotação Enviada", 'Vendas Organicas'!$N$2:$N$3000, ">=01/10/2025", 'Vendas Organicas'!$N$2:$N$3000, "<=31/10/2025"), COUNTIFS('Diogo Lima'!$E$2:$E$1996, "Facebook", 'Diogo Lima'!$G$2:$G$1996, "Cotação Enviada", 'Diogo Lima'!$N$2:$N$1996, ">=01/10/2025", 'Diogo Lima'!$N$2:$N$1996, "<=31/10/2025"), COUNTIFS('Lucas Almeida'!$E$2:$E$4000, "Facebook", 'Lucas Almeida'!$G$2:$G$4000, "Cotação Enviada", 'Lucas Almeida'!$N$2:$N$4000, ">=01/10/2025", 'Lucas Almeida'!$N$2:$N$4000, "<=31/10/2025"), COUNTIFS('Fernando Diamantino'!$E$2:$E$1999, "Facebook", 'Fernando Diamantino'!$G$2:$G$1999, "Cotação Enviada", 'Fernando Diamantino'!$N$2:$N$1999, ">=01/10/2025", 'Fernando Diamantino'!$N$2:$N$1999, "<=31/10/2025"), COUNTIFS('Maiara Andrade'!$E$2:$E$4000, "Facebook", 'Maiara Andrade'!$G$2:$G$4000, "Cotação Enviada", 'Maiara Andrade'!$N$2:$N$4000, ">=01/10/2025", 'Maiara Andrade'!$N$2:$N$4000, "<=31/10/2025"), COUNTIFS('Roberto Ramos'!$E$2:$E$4000, "Facebook", 'Roberto Ramos'!$G$2:$G$4000, "Cotação Enviada", 'Roberto Ramos'!$N$2:$N$4000, ">=01/10/2025", 'Roberto Ramos'!$N$2:$N$4000, "<=31/10/2025"), COUNTIFS('Amanda Facundo'!$E$2:$E$1999, "Facebook", 'Amanda Facundo'!$G$2:$G$1999, "Cotação Enviada", 'Amanda Facundo'!$N$2:$N$1999, ">=01/10/2025", 'Amanda Facundo'!$N$2:$N$1999, "<=31/10/2025"), COUNTIFS('Rodrigo Oliveira'!$E$2:$E$4000, "Facebook", 'Rodrigo Oliveira'!$G$2:$G$4000, "Cotação Enviada", 'Rodrigo Oliveira'!$N$2:$N$4000, ">=01/10/2025", 'Rodrigo Oliveira'!$N$2:$N$4000, "<=31/10/2025"), COUNTIFS('Marcio Jorge'!$E$2:$E$4000, "Facebook", 'Marcio Jorge'!$G$2:$G$4000, "Cotação Enviada", 'Marcio Jorge'!$N$2:$N$4000, ">=01/10/2025", 'Marcio Jorge'!$N$2:$N$4000, "<=31/10/2025") ) -> 2 | AV15: =SUM( COUNTIFS('Bruna Mamedes'!$E$2:$E$4000, "Facebook", 'Bruna Mamedes'!$G$2:$G$4000, "Desistência", 'Bruna Mamedes'!$N$2:$N$4000, ">=01/10/2025", 'Bruna Mamedes'!$N$2:$N$4000, "<=31/10/2025"), COUNTIFS('Camila Adão'!$E$2:$E$1997, "Facebook", 'Camila Adão'!$G$2:$G$1997, "Desistência", 'Camila Adão'!$N$2:$N$1997, ">=01/10/2025", 'Camila Adão'!$N$2:$N$1997, "<=31/10/2025"), COUNTIFS('Vendas Organicas'!$E$2:$E$3000, "Facebook", 'Vendas Organicas'!$G$2:$G$3000, "Desistência", 'Vendas Organicas'!$N$2:$N$3000, ">=01/10/2025", 'Vendas Organicas'!$N$2:$N$3000, "<=31/10/2025"), COUNTIFS('Diogo Lima'!$E$2:$E$1996, "Facebook", 'Diogo Lima'!$G$2:$G$1996, "Desistência", 'Diogo Lima'!$N$2:$N$1996, ">=01/10/2025", 'Diogo Lima'!$N$2:$N$1996, "<=31/10/2025"), COUNTIFS('Lucas Almeida'!$E$2:$E$4000, "Facebook", 'Lucas Almeida'!$G$2:$G$4000, "Desistência", 'Lucas Almeida'!$N$2:$N$4000, ">=01/10/2025", 'Lucas Almeida'!$N$2:$N$4000, "<=31/10/2025"), COUNTIFS('Fernando Diamantino'!$E$2:$E$1999, "Facebook", 'Fernando Diamantino'!$G$2:$G$1999, "Desistência", 'Fernando Diamantino'!$N$2:$N$1999, ">=01/10/2025", 'Fernando Diamantino'!$N$2:$N$1999, "<=31/10/2025"), COUNTIFS('Maiara Andrade'!$E$2:$E$4000, "Facebook", 'Maiara Andrade'!$G$2:$G$4000, "Desistência", 'Maiara Andrade'!$N$2:$N$4000, ">=01/10/2025", 'Maiara Andrade'!$N$2:$N$4000, "<=31/10/2025"), COUNTIFS('Roberto Ramos'!$E$2:$E$4000, "Facebook", 'Roberto Ramos'!$G$2:$G$4000, "Desistência", 'Roberto Ramos'!$N$2:$N$4000, ">=01/10/2025", 'Roberto Ramos'!$N$2:$N$4000, "<=31/10/2025"), COUNTIFS('Amanda Facundo'!$E$2:$E$1999, "Facebook", 'Amanda Facundo'!$G$2:$G$1999, "Desistência", 'Amanda Facundo'!$N$2:$N$1999, ">=01/10/2025", 'Amanda Facundo'!$N$2:$N$1999, "<=31/10/2025"), COUNTIFS('Rodrigo Oliveira'!$E$2:$E$4000, "Facebook", 'Rodrigo Oliveira'!$G$2:$G$4000, "Desistência", 'Rodrigo Oliveira'!$N$2:$N$4000, ">=01/10/2025", 'Rodrigo Oliveira'!$N$2:$N$4000, "<=31/10/2025"), COUNTIFS('Marcio Jorge'!$E$2:$E$4000, "Facebook", 'Marcio Jorge'!$G$2:$G$4000, "Desistência", 'Marcio Jorge'!$N$2:$N$4000, ">=01/10/2025", 'Marcio Jorge'!$N$2:$N$4000, "<=31/10/2025") ) -> 5 | AW15: =SUM( COUNTIFS('Bruna Mamedes'!$E$2:$E$4000, "Facebook", 'Bruna Mamedes'!$G$2:$G$4000, "Não Respondeu", 'Bruna Mamedes'!$N$2:$N$4000, ">=01/10/2025", 'Bruna Mamedes'!$N$2:$N$4000, "<=31/10/2025"), COUNTIFS('Camila Adão'!$E$2:$E$1997, "Facebook", 'Camila Adão'!$G$2:$G$1997, "Não Respondeu", 'Camila Adão'!$N$2:$N$1997, ">=01/10/2025", 'Camila Adão'!$N$2:$N$1997, "<=31/10/2025"), COUNTIFS('Vendas Organicas'!$E$2:$E$3000, "Facebook", 'Vendas Organicas'!$G$2:$G$3000, "Não Respondeu", 'Vendas Organicas'!$N$2:$N$3000, ">=01/10/2025", 'Vendas Organicas'!$N$2:$N$3000, "<=31/10/2025"), COUNTIFS('Diogo Lima'!$E$2:$E$1996, "Facebook", 'Diogo Lima'!$G$2:$G$1996, "Não Respondeu", 'Diogo Lima'!$N$2:$N$1996, ">=01/10/2025", 'Diogo Lima'!$N$2:$N$1996, "<=31/10/2025"), COUNTIFS('Lucas Almeida'!$E$2:$E$4000, "Facebook", 'Lucas Almeida'!$G$2:$G$4000, "Não Respondeu", 'Lucas Almeida'!$N$2:$N$4000, ">=01/10/2025", 'Lucas Almeida'!$N$2:$N$4000, "<=31/10/2025"), COUNTIFS('Fernando Diamantino'!$E$2:$E$1999, "Facebook", 'Fernando Diamantino'!$G$2:$G$1999, "Não Respondeu", 'Fernando Diamantino'!$N$2:$N$1999, ">=01/10/2025", 'Fernando Diamantino'!$N$2:$N$1999, "<=31/10/2025"), COUNTIFS('Maiara Andrade'!$E$2:$E$4000, "Facebook", 'Maiara Andrade'!$G$2:$G$4000, "Não Respondeu", 'Maiara Andrade'!$N$2:$N$4000, ">=01/10/2025", 'Maiara Andrade'!$N$2:$N$4000, "<=31/10/2025"), COUNTIFS('Roberto Ramos'!$E$2:$E$4000, "Facebook", 'Roberto Ramos'!$G$2:$G$4000, "Não Respondeu", 'Roberto Ramos'!$N$2:$N$4000, ">=01/10/2025", 'Roberto Ramos'!$N$2:$N$4000, "<=31/10/2025"), COUNTIFS('Amanda Facundo'!$E$2:$E$1999, "Facebook", 'Amanda Facundo'!$G$2:$G$1999, "Não Respondeu", 'Amanda Facundo'!$N$2:$N$1999, ">=01/10/2025", 'Amanda Facundo'!$N$2:$N$1999, "<=31/10/2025"), COUNTIFS('Rodrigo Oliveira'!$E$2:$E$4000, "Facebook", 'Rodrigo Oliveira'!$G$2:$G$4000, "Não Respondeu", 'Rodrigo Oliveira'!$N$2:$N$4000, ">=01/10/2025", 'Rodrigo Oliveira'!$N$2:$N$4000, "<=31/10/2025"), COUNTIFS('Marcio Jorge'!$E$2:$E$4000, "Facebook", 'Marcio Jorge'!$G$2:$G$4000, "Não Respondeu", 'Marcio Jorge'!$N$2:$N$4000, ">=01/10/2025", 'Marcio Jorge'!$N$2:$N$4000, "<=31/10/2025") ) -> 9 | AX15: =SUM( SUMIFS('Bruna Mamedes'!$H$2:$H$4000, 'Bruna Mamedes'!$E$2:$E$4000, "Facebook", 'Bruna Mamedes'!$G$2:$G$4000, "Plano Fechado", 'Bruna Mamedes'!$N$2:$N$4000, ">=01/10/2025", 'Bruna Mamedes'!$N$2:$N$4000, "<=31/10/2025"), SUMIFS('Camila Adão'!$H$2:$H$4000, 'Camila Adão'!$E$2:$E$4000, "Facebook", 'Camila Adão'!$G$2:$G$4000, "Plano Fechado", 'Camila Adão'!$N$2:$N$4000, ">=01/10/2025", 'Camila Adão'!$N$2:$N$4000, "<=31/10/2025"), SUMIFS('Vendas Organicas'!$H$2:$H$4000, 'Vendas Organicas'!$E$2:$E$4000, "Facebook", 'Vendas Organicas'!$G$2:$G$4000, "Plano Fechado", 'Vendas Organicas'!$N$2:$N$4000, ">=01/10/2025", 'Vendas Organicas'!$N$2:$N$4000, "<=31/10/2025"), SUMIFS('Diogo Lima'!$H$2:$H$4000, 'Diogo Lima'!$E$2:$E$4000, "Facebook", 'Diogo Lima'!$G$2:$G$4000, "Plano Fechado", 'Diogo Lima'!$N$2:$N$4000, ">=01/10/2025", 'Diogo Lima'!$N$2:$N$4000, "<=31/10/2025"), SUMIFS('Lucas Almeida'!$H$2:$H$4000, 'Lucas Almeida'!$E$2:$E$4000, "Facebook", 'Lucas Almeida'!$G$2:$G$4000, "Plano Fechado", 'Lucas Almeida'!$N$2:$N$4000, ">=01/10/2025", 'Lucas Almeida'!$N$2:$N$4000, "<=31/10/2025"), SUMIFS('Fernando Diamantino'!$H$2:$H$4000, 'Fernando Diamantino'!$E$2:$E$4000, "Facebook", 'Fernando Diamantino'!$G$2:$G$4000, "Plano Fechado", 'Fernando Diamantino'!$N$2:$N$4000, ">=01/10/2025", 'Fernando Diamantino'!$N$2:$N$4000, "<=31/10/2025"), SUMIFS('Maiara Andrade'!$H$2:$H$4000, 'Maiara Andrade'!$E$2:$E$4000, "Facebook", 'Maiara Andrade'!$G$2:$G$4000, "Plano Fechado", 'Maiara Andrade'!$N$2:$N$4000, ">=01/10/2025", 'Maiara Andrade'!$N$2:$N$4000, "<=31/10/2025"), SUMIFS('Roberto Ramos'!$H$2:$H$4000, 'Roberto Ramos'!$E$2:$E$4000, "Facebook", 'Roberto Ramos'!$G$2:$G$4000, "Plano Fechado", 'Roberto Ramos'!$N$2:$N$4000, ">=01/10/2025", 'Roberto Ramos'!$N$2:$N$4000, "<=31/10/2025"), SUMIFS('Amanda Facundo'!$H$2:$H$4000, 'Amanda Facundo'!$E$2:$E$4000, "Facebook", 'Amanda Facundo'!$G$2:$G$4000, "Plano Fechado", 'Amanda Facundo'!$N$2:$N$4000, ">=01/10/2025", 'Amanda Facundo'!$N$2:$N$4000, "<=31/10/2025"), SUMIFS('Rodrigo Oliveira'!$H$2:$H$4000, 'Rodrigo Oliveira'!$E$2:$E$4000, "Facebook", 'Rodrigo Oliveira'!$G$2:$G$4000, "Plano Fechado", 'Rodrigo Oliveira'!$N$2:$N$4000, ">=01/10/2025", 'Rodrigo Oliveira'!$N$2:$N$4000, "<=31/10/2025"), SUMIFS('Marcio Jorge'!$H$2:$H$4000, 'Marcio Jorge'!$E$2:$E$4000, "Facebook", 'Marcio Jorge'!$G$2:$G$4000, "Plano Fechado", 'Marcio Jorge'!$N$2:$N$4000, ">=01/10/2025", 'Marcio Jorge'!$N$2:$N$4000, "<=31/10/2025"), SUMIFS('Corretor 1'!$H$2:$H$4000, 'Corretor 1'!$E$2:$E$4000, "Facebook", 'Corretor 1'!$G$2:$G$4000, "Plano Fechado", 'Corretor 1'!$N$2:$N$4000, ">=01/10/2025", 'Corretor 1'!$N$2:$N$4000, "<=31/10/2025"), SUMIFS('Corretor 2'!$H$2:$H$4000, 'Corretor 2'!$E$2:$E$4000, "Facebook", 'Corretor 2'!$G$2:$G$4000, "Plano Fechado", 'Corretor 2'!$N$2:$N$4000, ">=01/10/2025", 'Corretor 2'!$N$2:$N$4000, "<=31/10/2025"), SUMIFS('Corretor 3'!$H$2:$H$4000, 'Corretor 3'!$E$2:$E$4000, "Facebook", 'Corretor 3'!$G$2:$G$4000, "Plano Fechado", 'Corretor 3'!$N$2:$N$4000, ">=01/10/2025", 'Corretor 3'!$N$2:$N$4000, "<=31/10/2025"), SUMIFS('Corretor 4'!$H$2:$H$4000, 'Corretor 4'!$E$2:$E$4000, "Facebook", 'Corretor 4'!$G$2:$G$4000, "Plano Fechado", 'Corretor 4'!$N$2:$N$4000, ">=01/10/2025", 'Corretor 4'!$N$2:$N$4000, "<=31/10/2025"), SUMIFS('Corretor 5'!$H$2:$H$4000, 'Corretor 5'!$E$2:$E$4000, "Facebook", 'Corretor 5'!$G$2:$G$4000, "Plano Fechado", 'Corretor 5'!$N$2:$N$4000, ">=01/10/2025", 'Corretor 5'!$N$2:$N$4000, "<=31/10/2025") ) -> 3446
C16: 0 | D16: 0.079 | E16: 0.132 | F16: 0 | G16: 0.789 | K16: 0.043 | L16: 0.022 | M16: 0.109 | N16: 0.043 | O16: 0.63 | S16: 0 | T16: 0 | U16: 0.159 | V16: 0 | W16: 0.841 | AA16: 0.04 | AB16: 0.02 | AC16: 0.1 | AD16: 0.08 | AE16: 0.62 | AI16: 0.013 | AJ16: 0.026 | AK16: 0.105 | AL16: 0.039 | AM16: 0.697 | AQ16: =(AQ15/AP15) -> 0.071428571 | AR16: =(AR15/AP15) -> 0 | AS16: =(AS15/AP15) -> 0 | AT16: =(AT15/AP15) -> 0.071428571 | AU16: =AU15/AP15 -> 0.14285714 | AV16: =AV15/AP15 -> 0.35714286 | AW16: =AW15/AP15 -> 0.64285714
B18: LEADS PLANTÃO - GOL | J18: LEADS PLANTÃO - GOL | R18: LEADS PLANTÃO - GOL | Z18: LEADS PLANTÃO - GOL | AH18: LEADS PLANTÃO - GOL | AP18: LEADS PLANTÃO - GOL
B19: QTD. Leads | C19: Vendas Fechadas | D19: Leads em Conversação | E19: Leads com Proposta Enviada | F19: Leads Desistentes | G19: Leads sem Resposta | H19: Faturamento | J19: QTD. Leads | K19: Vendas Fechadas | L19: Leads em Conversação | M19: Leads com Proposta Enviada | N19: Leads Desistentes | O19: Leads sem Resposta | P19: Faturamento | R19: QTD. Leads | S19: Vendas Fechadas | T19: Leads em Conversação | U19: Leads com Proposta Enviada | V19: Leads Desistentes | W19: Leads sem Resposta | X19: Faturamento | Z19: QTD. Leads | AA19: Vendas Fechadas | AB19: Leads em Conversação | AC19: Leads com Proposta Enviada | AD19: Leads Desistentes | AE19: Leads sem Resposta | AF19: Faturamento | AH19: QTD. Leads | AI19: Vendas Fechadas | AJ19: Leads em Conversação | AK19: Leads com Proposta Enviada | AL19: Leads Desistentes | AM19: Leads sem Resposta | AN19: Faturamento | AP19: QTD. Leads | AQ19: Plano Fechado | AR19: Em Análise | AS19: Aguardando Pagamento | AT19: Conversação | AU19: Proposta Enviada | AV19: Desistentes | AW19: Sem Resposta | AX19: Faturamento
B20: 280 | C20: 0 | D20: 26 | E20: 90 | F20: 9 | G20: 155 | H20: 0 | J20: 1071 | K20: 20 | L20: 36 | M20: 320 | N20: 43 | O20: 535 | P20: 18539.52 | R20: 1153 | S20: 24 | T20: 55 | U20: 311 | V20: 74 | W20: 686 | X20: 29065.31 | Z20: 859 | AA20: 27 | AB20: 76 | AC20: 261 | AD20: 57 | AE20: 514 | AF20: 21196.82 | AH20: 897 | AI20: 17 | AJ20: 57 | AK20: 348 | AL20: 50 | AM20: 419 | AN20: 14213.71 | AP20: {=LET( abas, {"Amanda Facundo";"Bruna Mamedes";"Camila Adão";"Darlin Amorim";"Diogo Lima";"Externos";"Maiara Andrade";"Marcio Jorge";"Lucas Almeida";"Roberto Ramos";"Rodrigo Oliviera";"Leandro Nascimento";"Leandro Drumond";"Marcelle Marcela";"Anteriores";"Corretor 1";"Corretor 2";"Corretor 3";"Corretor 4";"Corretor 5"}, SUM( BYROW( abas, LAMBDA(a, COUNTIFS( INDIRECT("'"&a&"'!E:E"), "Plantão", INDIRECT("'"&a&"'!N:N"), ">="&DATE(2025,10,1), INDIRECT("'"&a&"'!N:N"), "<="&DATE(2025,10,31) ) ) ) ) )} -> 732 | AQ20: =SUM( COUNTIFS('Bruna Mamedes'!$E$2:$E$4000, "Plantão", 'Bruna Mamedes'!$G$2:$G$4000, "Plano Fechado", 'Bruna Mamedes'!$N$2:$N$4000, ">=01/10/2025", 'Bruna Mamedes'!$N$2:$N$4000, "<=31/10/2025"), COUNTIFS('Camila Adão'!$E$2:$E$1997, "Plantão", 'Camila Adão'!$G$2:$G$1997, "Plano Fechado", 'Camila Adão'!$N$2:$N$1997, ">=01/10/2025", 'Camila Adão'!$N$2:$N$1997, "<=31/10/2025"), COUNTIFS('Vendas Organicas'!$E$2:$E$3000, "Plantão", 'Vendas Organicas'!$G$2:$G$3000, "Plano Fechado", 'Vendas Organicas'!$N$2:$N$3000, ">=01/10/2025", 'Vendas Organicas'!$N$2:$N$3000, "<=31/10/2025"), COUNTIFS('Diogo Lima'!$E$2:$E$1996, "Plantão", 'Diogo Lima'!$G$2:$G$1996, "Plano Fechado", 'Diogo Lima'!$N$2:$N$1996, ">=01/10/2025", 'Diogo Lima'!$N$2:$N$1996, "<=31/10/2025"), COUNTIFS('Lucas Almeida'!$E$2:$E$4000, "Plantão", 'Lucas Almeida'!$G$2:$G$4000, "Plano Fechado", 'Lucas Almeida'!$N$2:$N$4000, ">=01/10/2025", 'Lucas Almeida'!$N$2:$N$4000, "<=31/10/2025"), COUNTIFS('Fernando Diamantino'!$E$2:$E$1999, "Plantão", 'Fernando Diamantino'!$G$2:$G$1999, "Plano Fechado", 'Fernando Diamantino'!$N$2:$N$1999, ">=01/10/2025", 'Fernando Diamantino'!$N$2:$N$1999, "<=31/10/2025"), COUNTIFS('Maiara Andrade'!$E$2:$E$4000, "Plantão", 'Maiara Andrade'!$G$2:$G$4000, "Plano Fechado", 'Maiara Andrade'!$N$2:$N$4000, ">=01/10/2025", 'Maiara Andrade'!$N$2:$N$4000, "<=31/10/2025"), COUNTIFS('Roberto Ramos'!$E$2:$E$4000, "Plantão", 'Roberto Ramos'!$G$2:$G$4000, "Plano Fechado", 'Roberto Ramos'!$N$2:$N$4000, ">=01/10/2025", 'Roberto Ramos'!$N$2:$N$4000, "<=31/10/2025"), COUNTIFS('Amanda Facundo'!$E$2:$E$1999, "Plantão", 'Amanda Facundo'!$G$2:$G$1999, "Plano Fechado", 'Amanda Facundo'!$N$2:$N$1999, ">=01/10/2025", 'Amanda Facundo'!$N$2:$N$1999, "<=31/10/2025"), COUNTIFS('Rodrigo Oliveira'!$E$2:$E$4000, "Plantão", 'Rodrigo Oliveira'!$G$2:$G$4000, "Plano Fechado", 'Rodrigo Oliveira'!$N$2:$N$4000, ">=01/10/2025", 'Rodrigo Oliveira'!$N$2:$N$4000, "<=31/10/2025"), COUNTIFS('Marcio Jorge'!$E$2:$E$4000, "Plantão", 'Marcio Jorge'!$G$2:$G$4000, "Plano Fechado", 'Marcio Jorge'!$N$2:$N$4000, ">=01/10/2025", 'Marcio Jorge'!$N$2:$N$4000, "<=31/10/2025") ) -> 21 | AR20: =SUM( COUNTIFS('Bruna Mamedes'!$E$2:$E$4000, "Plantão", 'Bruna Mamedes'!$G$2:$G$4000, "Em Análise", 'Bruna Mamedes'!$N$2:$N$4000, ">=01/10/2025", 'Bruna Mamedes'!$N$2:$N$4000, "<=31/10/2025"), COUNTIFS('Camila Adão'!$E$2:$E$1997, "Plantão", 'Camila Adão'!$G$2:$G$1997, "Em Análise", 'Camila Adão'!$N$2:$N$1997, ">=01/10/2025", 'Camila Adão'!$N$2:$N$1997, "<=31/10/2025"), COUNTIFS('Vendas Organicas'!$E$2:$E$3000, "Plantão", 'Vendas Organicas'!$G$2:$G$3000, "Em Análise", 'Vendas Organicas'!$N$2:$N$3000, ">=01/10/2025", 'Vendas Organicas'!$N$2:$N$3000, "<=31/10/2025"), COUNTIFS('Diogo Lima'!$E$2:$E$1996, "Plantão", 'Diogo Lima'!$G$2:$G$1996, "Em Análise", 'Diogo Lima'!$N$2:$N$1996, ">=01/10/2025", 'Diogo Lima'!$N$2:$N$1996, "<=31/10/2025"), COUNTIFS('Lucas Almeida'!$E$2:$E$4000, "Plantão", 'Lucas Almeida'!$G$2:$G$4000, "Em Análise", 'Lucas Almeida'!$N$2:$N$4000, ">=01/10/2025", 'Lucas Almeida'!$N$2:$N$4000, "<=31/10/2025"), COUNTIFS('Fernando Diamantino'!$E$2:$E$1999, "Plantão", 'Fernando Diamantino'!$G$2:$G$1999, "Em Análise", 'Fernando Diamantino'!$N$2:$N$1999, ">=01/10/2025", 'Fernando Diamantino'!$N$2:$N$1999, "<=31/10/2025"), COUNTIFS('Maiara Andrade'!$E$2:$E$4000, "Plantão", 'Maiara Andrade'!$G$2:$G$4000, "Em Análise", 'Maiara Andrade'!$N$2:$N$4000, ">=01/10/2025", 'Maiara Andrade'!$N$2:$N$4000, "<=31/10/2025"), COUNTIFS('Roberto Ramos'!$E$2:$E$4000, "Plantão", 'Roberto Ramos'!$G$2:$G$4000, "Em Análise", 'Roberto Ramos'!$N$2:$N$4000, ">=01/10/2025", 'Roberto Ramos'!$N$2:$N$4000, "<=31/10/2025"), COUNTIFS('Amanda Facundo'!$E$2:$E$1999, "Plantão", 'Amanda Facundo'!$G$2:$G$1999, "Em Análise", 'Amanda Facundo'!$N$2:$N$1999, ">=01/10/2025", 'Amanda Facundo'!$N$2:$N$1999, "<=31/10/2025"), COUNTIFS('Rodrigo Oliveira'!$E$2:$E$4000, "Plantão", 'Rodrigo Oliveira'!$G$2:$G$4000, "Em Análise", 'Rodrigo Oliveira'!$N$2:$N$4000, ">=01/10/2025", 'Rodrigo Oliveira'!$N$2:$N$4000, "<=31/10/2025"), COUNTIFS('Marcio Jorge'!$E$2:$E$4000, "Plantão", 'Marcio Jorge'!$G$2:$G$4000, "Em Análise", 'Marcio Jorge'!$N$2:$N$4000, ">=01/10/2025", 'Marcio Jorge'!$N$2:$N$4000, "<=31/10/2025") ) -> 5 | AS20: =SUM( COUNTIFS('Bruna Mamedes'!$E$2:$E$4000, "Plantão", 'Bruna Mamedes'!$G$2:$G$4000, "Aguardando Pagamento", 'Bruna Mamedes'!$N$2:$N$4000, ">=01/10/2025", 'Bruna Mamedes'!$N$2:$N$4000, "<=31/10/2025"), COUNTIFS('Camila Adão'!$E$2:$E$1997, "Plantão", 'Camila Adão'!$G$2:$G$1997, "Aguardando Pagamento", 'Camila Adão'!$N$2:$N$1997, ">=01/10/2025", 'Camila Adão'!$N$2:$N$1997, "<=31/10/2025"), COUNTIFS('Vendas Organicas'!$E$2:$E$3000, "Plantão", 'Vendas Organicas'!$G$2:$G$3000, "Aguardando Pagamento", 'Vendas Organicas'!$N$2:$N$3000, ">=01/10/2025", 'Vendas Organicas'!$N$2:$N$3000, "<=31/10/2025"), COUNTIFS('Diogo Lima'!$E$2:$E$1996, "Plantão", 'Diogo Lima'!$G$2:$G$1996, "Aguardando Pagamento", 'Diogo Lima'!$N$2:$N$1996, ">=01/10/2025", 'Diogo Lima'!$N$2:$N$1996, "<=31/10/2025"), COUNTIFS('Lucas Almeida'!$E$2:$E$4000, "Plantão", 'Lucas Almeida'!$G$2:$G$4000, "Aguardando Pagamento", 'Lucas Almeida'!$N$2:$N$4000, ">=01/10/2025", 'Lucas Almeida'!$N$2:$N$4000, "<=31/10/2025"), COUNTIFS('Fernando Diamantino'!$E$2:$E$1999, "Plantão", 'Fernando Diamantino'!$G$2:$G$1999, "Aguardando Pagamento", 'Fernando Diamantino'!$N$2:$N$1999, ">=01/10/2025", 'Fernando Diamantino'!$N$2:$N$1999, "<=31/10/2025"), COUNTIFS('Maiara Andrade'!$E$2:$E$4000, "Plantão", 'Maiara Andrade'!$G$2:$G$4000, "Aguardando Pagamento", 'Maiara Andrade'!$N$2:$N$4000, ">=01/10/2025", 'Maiara Andrade'!$N$2:$N$4000, "<=31/10/2025"), COUNTIFS('Roberto Ramos'!$E$2:$E$4000, "Plantão", 'Roberto Ramos'!$G$2:$G$4000, "Aguardando Pagamento", 'Roberto Ramos'!$N$2:$N$4000, ">=01/10/2025", 'Roberto Ramos'!$N$2:$N$4000, "<=31/10/2025"), COUNTIFS('Amanda Facundo'!$E$2:$E$1999, "Plantão", 'Amanda Facundo'!$G$2:$G$1999, "Aguardando Pagamento", 'Amanda Facundo'!$N$2:$N$1999, ">=01/10/2025", 'Amanda Facundo'!$N$2:$N$1999, "<=31/10/2025"), COUNTIFS('Rodrigo Oliveira'!$E$2:$E$4000, "Plantão", 'Rodrigo Oliveira'!$G$2:$G$4000, "Aguardando Pagamento", 'Rodrigo Oliveira'!$N$2:$N$4000, ">=01/10/2025", 'Rodrigo Oliveira'!$N$2:$N$4000, "<=31/10/2025"), COUNTIFS('Marcio Jorge'!$E$2:$E$4000, "Plantão", 'Marcio Jorge'!$G$2:$G$4000, "Aguardando Pagamento", 'Marcio Jorge'!$N$2:$N$4000, ">=01/10/2025", 'Marcio Jorge'!$N$2:$N$4000, "<=31/10/2025") ) -> 2 | AT20: =SUM( COUNTIFS('Bruna Mamedes'!$E$2:$E$4000, "Plantão", 'Bruna Mamedes'!$G$2:$G$4000, "Em conversação", 'Bruna Mamedes'!$N$2:$N$4000, ">=01/10/2025", 'Bruna Mamedes'!$N$2:$N$4000, "<=31/10/2025"), COUNTIFS('Camila Adão'!$E$2:$E$1997, "Plantão", 'Camila Adão'!$G$2:$G$1997, "Em conversação", 'Camila Adão'!$N$2:$N$1997, ">=01/10/2025", 'Camila Adão'!$N$2:$N$1997, "<=31/10/2025"), COUNTIFS('Vendas Organicas'!$E$2:$E$3000, "Plantão", 'Vendas Organicas'!$G$2:$G$3000, "Em conversação", 'Vendas Organicas'!$N$2:$N$3000, ">=01/10/2025", 'Vendas Organicas'!$N$2:$N$3000, "<=31/10/2025"), COUNTIFS('Diogo Lima'!$E$2:$E$1996, "Plantão", 'Diogo Lima'!$G$2:$G$1996, "Em conversação", 'Diogo Lima'!$N$2:$N$1996, ">=01/10/2025", 'Diogo Lima'!$N$2:$N$1996, "<=31/10/2025"), COUNTIFS('Lucas Almeida'!$E$2:$E$4000, "Plantão", 'Lucas Almeida'!$G$2:$G$4000, "Em conversação", 'Lucas Almeida'!$N$2:$N$4000, ">=01/10/2025", 'Lucas Almeida'!$N$2:$N$4000, "<=31/10/2025"), COUNTIFS('Fernando Diamantino'!$E$2:$E$1999, "Plantão", 'Fernando Diamantino'!$G$2:$G$1999, "Em conversação", 'Fernando Diamantino'!$N$2:$N$1999, ">=01/10/2025", 'Fernando Diamantino'!$N$2:$N$1999, "<=31/10/2025"), COUNTIFS('Maiara Andrade'!$E$2:$E$4000, "Plantão", 'Maiara Andrade'!$G$2:$G$4000, "Em conversação", 'Maiara Andrade'!$N$2:$N$4000, ">=01/10/2025", 'Maiara Andrade'!$N$2:$N$4000, "<=31/10/2025"), COUNTIFS('Roberto Ramos'!$E$2:$E$4000, "Plantão", 'Roberto Ramos'!$G$2:$G$4000, "Em conversação", 'Roberto Ramos'!$N$2:$N$4000, ">=01/10/2025", 'Roberto Ramos'!$N$2:$N$4000, "<=31/10/2025"), COUNTIFS('Amanda Facundo'!$E$2:$E$1999, "Plantão", 'Amanda Facundo'!$G$2:$G$1999, "Em conversação", 'Amanda Facundo'!$N$2:$N$1999, ">=01/10/2025", 'Amanda Facundo'!$N$2:$N$1999, "<=31/10/2025"), COUNTIFS('Rodrigo Oliveira'!$E$2:$E$4000, "Plantão", 'Rodrigo Oliveira'!$G$2:$G$4000, "Em conversação", 'Rodrigo Oliveira'!$N$2:$N$4000, ">=01/10/2025", 'Rodrigo Oliveira'!$N$2:$N$4000, "<=31/10/2025"), COUNTIFS('Marcio Jorge'!$E$2:$E$4000, "Plantão", 'Marcio Jorge'!$G$2:$G$4000, "Em conversação", 'Marcio Jorge'!$N$2:$N$4000, ">=01/10/2025", 'Marcio Jorge'!$N$2:$N$4000, "<=31/10/2025") ) -> 16 | AU20: =SUM( COUNTIFS('Bruna Mamedes'!$E$2:$E$4000, "Plantão", 'Bruna Mamedes'!$G$2:$G$4000, "Cotação Enviada", 'Bruna Mamedes'!$N$2:$N$4000, ">=01/10/2025", 'Bruna Mamedes'!$N$2:$N$4000, "<=31/10/2025"), COUNTIFS('Camila Adão'!$E$2:$E$1997, "Plantão", 'Camila Adão'!$G$2:$G$1997, "Cotação Enviada", 'Camila Adão'!$N$2:$N$1997, ">=01/10/2025", 'Camila Adão'!$N$2:$N$1997, "<=31/10/2025"), COUNTIFS('Vendas Organicas'!$E$2:$E$3000, "Plantão", 'Vendas Organicas'!$G$2:$G$3000, "Cotação Enviada", 'Vendas Organicas'!$N$2:$N$3000, ">=01/10/2025", 'Vendas Organicas'!$N$2:$N$3000, "<=31/10/2025"), COUNTIFS('Diogo Lima'!$E$2:$E$1996, "Plantão", 'Diogo Lima'!$G$2:$G$1996, "Cotação Enviada", 'Diogo Lima'!$N$2:$N$1996, ">=01/10/2025", 'Diogo Lima'!$N$2:$N$1996, "<=31/10/2025"), COUNTIFS('Lucas Almeida'!$E$2:$E$4000, "Plantão", 'Lucas Almeida'!$G$2:$G$4000, "Cotação Enviada", 'Lucas Almeida'!$N$2:$N$4000, ">=01/10/2025", 'Lucas Almeida'!$N$2:$N$4000, "<=31/10/2025"), COUNTIFS('Fernando Diamantino'!$E$2:$E$1999, "Plantão", 'Fernando Diamantino'!$G$2:$G$1999, "Cotação Enviada", 'Fernando Diamantino'!$N$2:$N$1999, ">=01/10/2025", 'Fernando Diamantino'!$N$2:$N$1999, "<=31/10/2025"), COUNTIFS('Maiara Andrade'!$E$2:$E$4000, "Plantão", 'Maiara Andrade'!$G$2:$G$4000, "Cotação Enviada", 'Maiara Andrade'!$N$2:$N$4000, ">=01/10/2025", 'Maiara Andrade'!$N$2:$N$4000, "<=31/10/2025"), COUNTIFS('Roberto Ramos'!$E$2:$E$4000, "Plantão", 'Roberto Ramos'!$G$2:$G$4000, "Cotação Enviada", 'Roberto Ramos'!$N$2:$N$4000, ">=01/10/2025", 'Roberto Ramos'!$N$2:$N$4000, "<=31/10/2025"), COUNTIFS('Amanda Facundo'!$E$2:$E$1999, "Plantão", 'Amanda Facundo'!$G$2:$G$1999, "Cotação Enviada", 'Amanda Facundo'!$N$2:$N$1999, ">=01/10/2025", 'Amanda Facundo'!$N$2:$N$1999, "<=31/10/2025"), COUNTIFS('Rodrigo Oliveira'!$E$2:$E$4000, "Plantão", 'Rodrigo Oliveira'!$G$2:$G$4000, "Cotação Enviada", 'Rodrigo Oliveira'!$N$2:$N$4000, ">=01/10/2025", 'Rodrigo Oliveira'!$N$2:$N$4000, "<=31/10/2025"), COUNTIFS('Marcio Jorge'!$E$2:$E$4000, "Plantão", 'Marcio Jorge'!$G$2:$G$4000, "Cotação Enviada", 'Marcio Jorge'!$N$2:$N$4000, ">=01/10/2025", 'Marcio Jorge'!$N$2:$N$4000, "<=31/10/2025") ) -> 226 | AV20: =SUM( COUNTIFS('Bruna Mamedes'!$E$2:$E$4000, "Plantão", 'Bruna Mamedes'!$G$2:$G$4000, "Desistência", 'Bruna Mamedes'!$N$2:$N$4000, ">=01/10/2025", 'Bruna Mamedes'!$N$2:$N$4000, "<=31/10/2025"), COUNTIFS('Camila Adão'!$E$2:$E$1997, "Plantão", 'Camila Adão'!$G$2:$G$1997, "Desistência", 'Camila Adão'!$N$2:$N$1997, ">=01/10/2025", 'Camila Adão'!$N$2:$N$1997, "<=31/10/2025"), COUNTIFS('Vendas Organicas'!$E$2:$E$3000, "Plantão", 'Vendas Organicas'!$G$2:$G$3000, "Desistência", 'Vendas Organicas'!$N$2:$N$3000, ">=01/10/2025", 'Vendas Organicas'!$N$2:$N$3000, "<=31/10/2025"), COUNTIFS('Diogo Lima'!$E$2:$E$1996, "Plantão", 'Diogo Lima'!$G$2:$G$1996, "Desistência", 'Diogo Lima'!$N$2:$N$1996, ">=01/10/2025", 'Diogo Lima'!$N$2:$N$1996, "<=31/10/2025"), COUNTIFS('Lucas Almeida'!$E$2:$E$4000, "Plantão", 'Lucas Almeida'!$G$2:$G$4000, "Desistência", 'Lucas Almeida'!$N$2:$N$4000, ">=01/10/2025", 'Lucas Almeida'!$N$2:$N$4000, "<=31/10/2025"), COUNTIFS('Fernando Diamantino'!$E$2:$E$1999, "Plantão", 'Fernando Diamantino'!$G$2:$G$1999, "Desistência", 'Fernando Diamantino'!$N$2:$N$1999, ">=01/10/2025", 'Fernando Diamantino'!$N$2:$N$1999, "<=31/10/2025"), COUNTIFS('Maiara Andrade'!$E$2:$E$4000, "Plantão", 'Maiara Andrade'!$G$2:$G$4000, "Desistência", 'Maiara Andrade'!$N$2:$N$4000, ">=01/10/2025", 'Maiara Andrade'!$N$2:$N$4000, "<=31/10/2025"), COUNTIFS('Roberto Ramos'!$E$2:$E$4000, "Plantão", 'Roberto Ramos'!$G$2:$G$4000, "Desistência", 'Roberto Ramos'!$N$2:$N$4000, ">=01/10/2025", 'Roberto Ramos'!$N$2:$N$4000, "<=31/10/2025"), COUNTIFS('Amanda Facundo'!$E$2:$E$1999, "Plantão", 'Amanda Facundo'!$G$2:$G$1999, "Desistência", 'Amanda Facundo'!$N$2:$N$1999, ">=01/10/2025", 'Amanda Facundo'!$N$2:$N$1999, "<=31/10/2025"), COUNTIFS('Rodrigo Oliveira'!$E$2:$E$4000, "Plantão", 'Rodrigo Oliveira'!$G$2:$G$4000, "Desistência", 'Rodrigo Oliveira'!$N$2:$N$4000, ">=01/10/2025", 'Rodrigo Oliveira'!$N$2:$N$4000, "<=31/10/2025"), COUNTIFS('Marcio Jorge'!$E$2:$E$4000, "Plantão", 'Marcio Jorge'!$G$2:$G$4000, "Desistência", 'Marcio Jorge'!$N$2:$N$4000, ">=01/10/2025", 'Marcio Jorge'!$N$2:$N$4000, "<=31/10/2025") ) -> 43 | AW20: =SUM( COUNTIFS('Bruna Mamedes'!$E$2:$E$4000, "Plantão", 'Bruna Mamedes'!$G$2:$G$4000, "Não Respondeu", 'Bruna Mamedes'!$N$2:$N$4000, ">=01/10/2025", 'Bruna Mamedes'!$N$2:$N$4000, "<=31/10/2025"), COUNTIFS('Camila Adão'!$E$2:$E$1997, "Plantão", 'Camila Adão'!$G$2:$G$1997, "Não Respondeu", 'Camila Adão'!$N$2:$N$1997, ">=01/10/2025", 'Camila Adão'!$N$2:$N$1997, "<=31/10/2025"), COUNTIFS('Vendas Organicas'!$E$2:$E$3000, "Plantão", 'Vendas Organicas'!$G$2:$G$3000, "Não Respondeu", 'Vendas Organicas'!$N$2:$N$3000, ">=01/10/2025", 'Vendas Organicas'!$N$2:$N$3000, "<=31/10/2025"), COUNTIFS('Diogo Lima'!$E$2:$E$1996, "Plantão", 'Diogo Lima'!$G$2:$G$1996, "Não Respondeu", 'Diogo Lima'!$N$2:$N$1996, ">=01/10/2025", 'Diogo Lima'!$N$2:$N$1996, "<=31/10/2025"), COUNTIFS('Lucas Almeida'!$E$2:$E$4000, "Plantão", 'Lucas Almeida'!$G$2:$G$4000, "Não Respondeu", 'Lucas Almeida'!$N$2:$N$4000, ">=01/10/2025", 'Lucas Almeida'!$N$2:$N$4000, "<=31/10/2025"), COUNTIFS('Fernando Diamantino'!$E$2:$E$1999, "Plantão", 'Fernando Diamantino'!$G$2:$G$1999, "Não Respondeu", 'Fernando Diamantino'!$N$2:$N$1999, ">=01/10/2025", 'Fernando Diamantino'!$N$2:$N$1999, "<=31/10/2025"), COUNTIFS('Maiara Andrade'!$E$2:$E$4000, "Plantão", 'Maiara Andrade'!$G$2:$G$4000, "Não Respondeu", 'Maiara Andrade'!$N$2:$N$4000, ">=01/10/2025", 'Maiara Andrade'!$N$2:$N$4000, "<=31/10/2025"), COUNTIFS('Roberto Ramos'!$E$2:$E$4000, "Plantão", 'Roberto Ramos'!$G$2:$G$4000, "Não Respondeu", 'Roberto Ramos'!$N$2:$N$4000, ">=01/10/2025", 'Roberto Ramos'!$N$2:$N$4000, "<=31/10/2025"), COUNTIFS('Amanda Facundo'!$E$2:$E$1999, "Plantão", 'Amanda Facundo'!$G$2:$G$1999, "Não Respondeu", 'Amanda Facundo'!$N$2:$N$1999, ">=01/10/2025", 'Amanda Facundo'!$N$2:$N$1999, "<=31/10/2025"), COUNTIFS('Rodrigo Oliveira'!$E$2:$E$4000, "Plantão", 'Rodrigo Oliveira'!$G$2:$G$4000, "Não Respondeu", 'Rodrigo Oliveira'!$N$2:$N$4000, ">=01/10/2025", 'Rodrigo Oliveira'!$N$2:$N$4000, "<=31/10/2025"), COUNTIFS('Marcio Jorge'!$E$2:$E$4000, "Plantão", 'Marcio Jorge'!$G$2:$G$4000, "Não Respondeu", 'Marcio Jorge'!$N$2:$N$4000, ">=01/10/2025", 'Marcio Jorge'!$N$2:$N$4000, "<=31/10/2025") ) -> 197 | AX20: =SUM( SUMIFS('Bruna Mamedes'!$H$2:$H$4000, 'Bruna Mamedes'!$E$2:$E$4000, "Plantão", 'Bruna Mamedes'!$G$2:$G$4000, "Plano Fechado", 'Bruna Mamedes'!$N$2:$N$4000, ">=01/10/2025", 'Bruna Mamedes'!$N$2:$N$4000, "<=31/10/2025"), SUMIFS('Camila Adão'!$H$2:$H$1997, 'Camila Adão'!$E$2:$E$1997, "Plantão", 'Camila Adão'!$G$2:$G$1997, "Plano Fechado", 'Camila Adão'!$N$2:$N$1997, ">=01/10/2025", 'Camila Adão'!$N$2:$N$1997, "<=31/10/2025"), SUMIFS('Vendas Organicas'!$H$2:$H$3000, 'Vendas Organicas'!$E$2:$E$3000, "Plantão", 'Vendas Organicas'!$G$2:$G$3000, "Plano Fechado", 'Vendas Organicas'!$N$2:$N$3000, ">=01/10/2025", 'Vendas Organicas'!$N$2:$N$3000, "<=31/10/2025"), SUMIFS('Diogo Lima'!$H$2:$H$1996, 'Diogo Lima'!$E$2:$E$1996, "Plantão", 'Diogo Lima'!$G$2:$G$1996, "Plano Fechado", 'Diogo Lima'!$N$2:$N$1996, ">=01/10/2025", 'Diogo Lima'!$N$2:$N$1996, "<=31/10/2025"), SUMIFS('Lucas Almeida'!$H$2:$H$4000, 'Lucas Almeida'!$E$2:$E$4000, "Plantão", 'Lucas Almeida'!$G$2:$G$4000, "Plano Fechado", 'Lucas Almeida'!$N$2:$N$4000, ">=01/10/2025", 'Lucas Almeida'!$N$2:$N$4000, "<=31/10/2025"), SUMIFS('Fernando Diamantino'!$H$2:$H$1999, 'Fernando Diamantino'!$E$2:$E$1999, "Plantão", 'Fernando Diamantino'!$G$2:$G$1999, "Plano Fechado", 'Fernando Diamantino'!$N$2:$N$1999, ">=01/10/2025", 'Fernando Diamantino'!$N$2:$N$1999, "<=31/10/2025"), SUMIFS('Maiara Andrade'!$H$2:$H$4000, 'Maiara Andrade'!$E$2:$E$4000, "Plantão", 'Maiara Andrade'!$G$2:$G$4000, "Plano Fechado", 'Maiara Andrade'!$N$2:$N$4000, ">=01/10/2025", 'Maiara Andrade'!$N$2:$N$4000, "<=31/10/2025"), SUMIFS('Roberto Ramos'!$H$2:$H$4000, 'Roberto Ramos'!$E$2:$E$4000, "Plantão", 'Roberto Ramos'!$G$2:$G$4000, "Plano Fechado", 'Roberto Ramos'!$N$2:$N$4000, ">=01/10/2025", 'Roberto Ramos'!$N$2:$N$4000, "<=31/10/2025"), SUMIFS('Amanda Facundo'!$H$2:$H$1999, 'Amanda Facundo'!$E$2:$E$1999, "Plantão", 'Amanda Facundo'!$G$2:$G$1999, "Plano Fechado", 'Amanda Facundo'!$N$2:$N$1999, ">=01/10/2025", 'Amanda Facundo'!$N$2:$N$1999, "<=31/10/2025"), SUMIFS('Rodrigo Oliveira'!$H$2:$H$4000, 'Rodrigo Oliveira'!$E$2:$E$4000, "Plantão", 'Rodrigo Oliveira'!$G$2:$G$4000, "Plano Fechado", 'Rodrigo Oliveira'!$N$2:$N$4000, ">=01/10/2025", 'Rodrigo Oliveira'!$N$2:$N$4000, "<=31/10/2025"), SUMIFS('Marcio Jorge'!$H$2:$H$4000, 'Marcio Jorge'!$E$2:$E$4000, "Plantão", 'Marcio Jorge'!$G$2:$G$4000, "Plano Fechado", 'Marcio Jorge'!$N$2:$N$4000, ">=01/10/2025", 'Marcio Jorge'!$N$2:$N$4000, "<=31/10/2025") ) -> 43526.14
C21: 0 | D21: 0.093 | E21: 0.321 | F21: 0.032 | G21: 0.554 | K21: 0.019 | L21: 0.034 | M21: 0.299 | N21: 0.04 | O21: 0.5 | S21: 0.021 | T21: 0.048 | U21: 0.27 | V21: 0.064 | W21: 0.595 | AA21: 0.031 | AB21: 0.088 | AC21: 0.304 | AD21: 0.066 | AE21: 0.598 | AI21: 0.019 | AJ21: 0.064 | AK21: 0.388 | AL21: 0.056 | AM21: 0.467 | AQ21: =(AQ20/AP20) -> 0.028688525 | AR21: =(AR20/AP20) -> 0.0068306011 | AS21: =(AS20/AP20) -> 0.0027322404 | AT21: =(AT20/AP20) -> 0.021857924 | AU21: =AU20/AP20 -> 0.30874317 | AV21: =AV20/AP20 -> 0.058743169 | AW21: =AW20/AP20 -> 0.26912568
B23: LEADS LANDING PAGE | J23: LEADS LANDING PAGE | R23: LEADS LANDING PAGE | Z23: LEADS LANDING PAGE | AH23: LEADS LANDING PAGE | AP23: LEADS LANDING PAGE
B24: QTD. Leads | C24: Vendas Fechadas | D24: Leads em Conversação | E24: Leads com Proposta Enviada | F24: Leads Desistentes | G24: Leads sem Resposta | H24: Faturamento | J24: QTD. Leads | K24: Vendas Fechadas | L24: Leads em Conversação | M24: Leads com Proposta Enviada | N24: Leads Desistentes | O24: Leads sem Resposta | P24: Faturamento | R24: QTD. Leads | S24: Vendas Fechadas | T24: Leads em Conversação | U24: Leads com Proposta Enviada | V24: Leads Desistentes | W24: Leads sem Resposta | X24: Faturamento | Z24: QTD. Leads | AA24: Vendas Fechadas | AB24: Leads em Conversação | AC24: Leads com Proposta Enviada | AD24: Leads Desistentes | AE24: Leads sem Resposta | AF24: Faturamento | AH24: QTD. Leads | AI24: Vendas Fechadas | AJ24: Leads em Conversação | AK24: Leads com Proposta Enviada | AL24: Leads Desistentes | AM24: Leads sem Resposta | AN24: Faturamento | AP24: QTD. Leads | AQ24: Plano Fechado | AR24: Em Análise | AS24: Aguardando Pagamento | AT24: Conversação | AU24: Proposta Enviada | AV24: Desistentes | AW24: Sem Resposta | AX24: Faturamento
B25: 0 | C25: 0 | D25: 0 | E25: 0 | F25: 0 | G25: 0 | H25: 0 | J25: 0 | K25: 0 | L25: 0 | M25: 0 | N25: 0 | O25: 0 | P25: 0 | R25: 1 | S25: 0 | T25: 0 | U25: 0 | V25: 1 | W25: 0 | X25: #N/A | Z25: 0 | AA25: 0 | AB25: 0 | AC25: 0 | AD25: 0 | AE25: 0 | AF25: #N/A | AH25: 0 | AI25: 0 | AJ25: 0 | AK25: 0 | AL25: 0 | AM25: 0 | AN25: #N/A | AP25: {=LET( abas, {"Amanda Facundo";"Bruna Mamedes";"Camila Adão";"Darlin Amorim";"Diogo Lima";"Externos";"Maiara Andrade";"Marcio Jorge";"Lucas Almeida";"Roberto Ramos";"Rodrigo Oliviera";"Leandro Nascimento";"Leandro Drumond";"Marcelle Marcela";"Anteriores";"Corretor 1";"Corretor 2";"Corretor 3";"Corretor 4";"Corretor 5"}, SUM( BYROW( abas, LAMBDA(a, COUNTIFS( INDIRECT("'"&a&"'!E:E"), "Landing Page", INDIRECT("'"&a&"'!N:N"), ">="&DATE(2025,10,1), INDIRECT("'"&a&"'!N:N"), "<="&DATE(2025,10,31) ) ) ) ) )} -> 7 | AQ25: =SUM( COUNTIFS('Bruna Mamedes'!$E$2:$E$4000, "Landing Page", 'Bruna Mamedes'!$G$2:$G$4000, "Plano Fechado", 'Bruna Mamedes'!$N$2:$N$4000, ">=01/10/2025", 'Bruna Mamedes'!$N$2:$N$4000, "<=31/10/2025"), COUNTIFS('Camila Adão'!$E$2:$E$1997, "Landing Page", 'Camila Adão'!$G$2:$G$1997, "Plano Fechado", 'Camila Adão'!$N$2:$N$1997, ">=01/10/2025", 'Camila Adão'!$N$2:$N$1997, "<=31/10/2025"), COUNTIFS('Vendas Organicas'!$E$2:$E$3000, "Landing Page", 'Vendas Organicas'!$G$2:$G$3000, "Plano Fechado", 'Vendas Organicas'!$N$2:$N$3000, ">=01/10/2025", 'Vendas Organicas'!$N$2:$N$3000, "<=31/10/2025"), COUNTIFS('Diogo Lima'!$E$2:$E$1996, "Landing Page", 'Diogo Lima'!$G$2:$G$1996, "Plano Fechado", 'Diogo Lima'!$N$2:$N$1996, ">=01/10/2025", 'Diogo Lima'!$N$2:$N$1996, "<=31/10/2025"), COUNTIFS('Lucas Almeida'!$E$2:$E$4000, "Landing Page", 'Lucas Almeida'!$G$2:$G$4000, "Plano Fechado", 'Lucas Almeida'!$N$2:$N$4000, ">=01/10/2025", 'Lucas Almeida'!$N$2:$N$4000, "<=31/10/2025"), COUNTIFS('Fernando Diamantino'!$E$2:$E$1999, "Landing Page", 'Fernando Diamantino'!$G$2:$G$1999, "Plano Fechado", 'Fernando Diamantino'!$N$2:$N$1999, ">=01/10/2025", 'Fernando Diamantino'!$N$2:$N$1999, "<=31/10/2025"), COUNTIFS('Maiara Andrade'!$E$2:$E$4000, "Landing Page", 'Maiara Andrade'!$G$2:$G$4000, "Plano Fechado", 'Maiara Andrade'!$N$2:$N$4000, ">=01/10/2025", 'Maiara Andrade'!$N$2:$N$4000, "<=31/10/2025"), COUNTIFS('Roberto Ramos'!$E$2:$E$4000, "Landing Page", 'Roberto Ramos'!$G$2:$G$4000, "Plano Fechado", 'Roberto Ramos'!$N$2:$N$4000, ">=01/10/2025", 'Roberto Ramos'!$N$2:$N$4000, "<=31/10/2025"), COUNTIFS('Amanda Facundo'!$E$2:$E$1999, "Landing Page", 'Amanda Facundo'!$G$2:$G$1999, "Plano Fechado", 'Amanda Facundo'!$N$2:$N$1999, ">=01/10/2025", 'Amanda Facundo'!$N$2:$N$1999, "<=31/10/2025"), COUNTIFS('Rodrigo Oliveira'!$E$2:$E$4000, "Landing Page", 'Rodrigo Oliveira'!$G$2:$G$4000, "Plano Fechado", 'Rodrigo Oliveira'!$N$2:$N$4000, ">=01/10/2025", 'Rodrigo Oliveira'!$N$2:$N$4000, "<=31/10/2025"), COUNTIFS('Marcio Jorge'!$E$2:$E$4000, "Landing Page", 'Marcio Jorge'!$G$2:$G$4000, "Plano Fechado", 'Marcio Jorge'!$N$2:$N$4000, ">=01/10/2025", 'Marcio Jorge'!$N$2:$N$4000, "<=31/10/2025") ) -> 0 | AR25: =SUM( COUNTIFS('Bruna Mamedes'!$E$2:$E$4000, "Landing Page", 'Bruna Mamedes'!$G$2:$G$4000, "Em Análise", 'Bruna Mamedes'!$N$2:$N$4000, ">=01/10/2025", 'Bruna Mamedes'!$N$2:$N$4000, "<=31/10/2025"), COUNTIFS('Camila Adão'!$E$2:$E$1997, "Landing Page", 'Camila Adão'!$G$2:$G$1997, "Em Análise", 'Camila Adão'!$N$2:$N$1997, ">=01/10/2025", 'Camila Adão'!$N$2:$N$1997, "<=31/10/2025"), COUNTIFS('Vendas Organicas'!$E$2:$E$3000, "Landing Page", 'Vendas Organicas'!$G$2:$G$3000, "Em Análise", 'Vendas Organicas'!$N$2:$N$3000, ">=01/10/2025", 'Vendas Organicas'!$N$2:$N$3000, "<=31/10/2025"), COUNTIFS('Diogo Lima'!$E$2:$E$1996, "Landing Page", 'Diogo Lima'!$G$2:$G$1996, "Em Análise", 'Diogo Lima'!$N$2:$N$1996, ">=01/10/2025", 'Diogo Lima'!$N$2:$N$1996, "<=31/10/2025"), COUNTIFS('Lucas Almeida'!$E$2:$E$4000, "Landing Page", 'Lucas Almeida'!$G$2:$G$4000, "Em Análise", 'Lucas Almeida'!$N$2:$N$4000, ">=01/10/2025", 'Lucas Almeida'!$N$2:$N$4000, "<=31/10/2025"), COUNTIFS('Fernando Diamantino'!$E$2:$E$1999, "Landing Page", 'Fernando Diamantino'!$G$2:$G$1999, "Em Análise", 'Fernando Diamantino'!$N$2:$N$1999, ">=01/10/2025", 'Fernando Diamantino'!$N$2:$N$1999, "<=31/10/2025"), COUNTIFS('Maiara Andrade'!$E$2:$E$4000, "Landing Page", 'Maiara Andrade'!$G$2:$G$4000, "Em Análise", 'Maiara Andrade'!$N$2:$N$4000, ">=01/10/2025", 'Maiara Andrade'!$N$2:$N$4000, "<=31/10/2025"), COUNTIFS('Roberto Ramos'!$E$2:$E$4000, "Landing Page", 'Roberto Ramos'!$G$2:$G$4000, "Em Análise", 'Roberto Ramos'!$N$2:$N$4000, ">=01/10/2025", 'Roberto Ramos'!$N$2:$N$4000, "<=31/10/2025"), COUNTIFS('Amanda Facundo'!$E$2:$E$1999, "Landing Page", 'Amanda Facundo'!$G$2:$G$1999, "Em Análise", 'Amanda Facundo'!$N$2:$N$1999, ">=01/10/2025", 'Amanda Facundo'!$N$2:$N$1999, "<=31/10/2025"), COUNTIFS('Rodrigo Oliveira'!$E$2:$E$4000, "Landing Page", 'Rodrigo Oliveira'!$G$2:$G$4000, "Em Análise", 'Rodrigo Oliveira'!$N$2:$N$4000, ">=01/10/2025", 'Rodrigo Oliveira'!$N$2:$N$4000, "<=31/10/2025"), COUNTIFS('Marcio Jorge'!$E$2:$E$4000, "Landing Page", 'Marcio Jorge'!$G$2:$G$4000, "Em Análise", 'Marcio Jorge'!$N$2:$N$4000, ">=01/10/2025", 'Marcio Jorge'!$N$2:$N$4000, "<=31/10/2025") ) -> 0 | AS25: =SUM( COUNTIFS('Bruna Mamedes'!$E$2:$E$4000, "Landing Page", 'Bruna Mamedes'!$G$2:$G$4000, "Aguardando Pagamento", 'Bruna Mamedes'!$N$2:$N$4000, ">=01/10/2025", 'Bruna Mamedes'!$N$2:$N$4000, "<=31/10/2025"), COUNTIFS('Camila Adão'!$E$2:$E$1997, "Landing Page", 'Camila Adão'!$G$2:$G$1997, "Aguardando Pagamento", 'Camila Adão'!$N$2:$N$1997, ">=01/10/2025", 'Camila Adão'!$N$2:$N$1997, "<=31/10/2025"), COUNTIFS('Vendas Organicas'!$E$2:$E$3000, "Landing Page", 'Vendas Organicas'!$G$2:$G$3000, "Aguardando Pagamento", 'Vendas Organicas'!$N$2:$N$3000, ">=01/10/2025", 'Vendas Organicas'!$N$2:$N$3000, "<=31/10/2025"), COUNTIFS('Diogo Lima'!$E$2:$E$1996, "Landing Page", 'Diogo Lima'!$G$2:$G$1996, "Aguardando Pagamento", 'Diogo Lima'!$N$2:$N$1996, ">=01/10/2025", 'Diogo Lima'!$N$2:$N$1996, "<=31/10/2025"), COUNTIFS('Lucas Almeida'!$E$2:$E$4000, "Landing Page", 'Lucas Almeida'!$G$2:$G$4000, "Aguardando Pagamento", 'Lucas Almeida'!$N$2:$N$4000, ">=01/10/2025", 'Lucas Almeida'!$N$2:$N$4000, "<=31/10/2025"), COUNTIFS('Fernando Diamantino'!$E$2:$E$1999, "Landing Page", 'Fernando Diamantino'!$G$2:$G$1999, "Aguardando Pagamento", 'Fernando Diamantino'!$N$2:$N$1999, ">=01/10/2025", 'Fernando Diamantino'!$N$2:$N$1999, "<=31/10/2025"), COUNTIFS('Maiara Andrade'!$E$2:$E$4000, "Landing Page", 'Maiara Andrade'!$G$2:$G$4000, "Aguardando Pagamento", 'Maiara Andrade'!$N$2:$N$4000, ">=01/10/2025", 'Maiara Andrade'!$N$2:$N$4000, "<=31/10/2025"), COUNTIFS('Roberto Ramos'!$E$2:$E$4000, "Landing Page", 'Roberto Ramos'!$G$2:$G$4000, "Aguardando Pagamento", 'Roberto Ramos'!$N$2:$N$4000, ">=01/10/2025", 'Roberto Ramos'!$N$2:$N$4000, "<=31/10/2025"), COUNTIFS('Amanda Facundo'!$E$2:$E$1999, "Landing Page", 'Amanda Facundo'!$G$2:$G$1999, "Aguardando Pagamento", 'Amanda Facundo'!$N$2:$N$1999, ">=01/10/2025", 'Amanda Facundo'!$N$2:$N$1999, "<=31/10/2025"), COUNTIFS('Rodrigo Oliveira'!$E$2:$E$4000, "Landing Page", 'Rodrigo Oliveira'!$G$2:$G$4000, "Aguardando Pagamento", 'Rodrigo Oliveira'!$N$2:$N$4000, ">=01/10/2025", 'Rodrigo Oliveira'!$N$2:$N$4000, "<=31/10/2025"), COUNTIFS('Marcio Jorge'!$E$2:$E$4000, "Landing Page", 'Marcio Jorge'!$G$2:$G$4000, "Aguardando Pagamento", 'Marcio Jorge'!$N$2:$N$4000, ">=01/10/2025", 'Marcio Jorge'!$N$2:$N$4000, "<=31/10/2025") ) -> 0 | AT25: =SUM( COUNTIFS('Bruna Mamedes'!$E$2:$E$4000, "Landing Page", 'Bruna Mamedes'!$G$2:$G$4000, "Em conversação", 'Bruna Mamedes'!$N$2:$N$4000, ">=01/10/2025", 'Bruna Mamedes'!$N$2:$N$4000, "<=31/10/2025"), COUNTIFS('Camila Adão'!$E$2:$E$1997, "Landing Page", 'Camila Adão'!$G$2:$G$1997, "Em conversação", 'Camila Adão'!$N$2:$N$1997, ">=01/10/2025", 'Camila Adão'!$N$2:$N$1997, "<=31/10/2025"), COUNTIFS('Vendas Organicas'!$E$2:$E$3000, "Landing Page", 'Vendas Organicas'!$G$2:$G$3000, "Em conversação", 'Vendas Organicas'!$N$2:$N$3000, ">=01/10/2025", 'Vendas Organicas'!$N$2:$N$3000, "<=31/10/2025"), COUNTIFS('Diogo Lima'!$E$2:$E$1996, "Landing Page", 'Diogo Lima'!$G$2:$G$1996, "Em conversação", 'Diogo Lima'!$N$2:$N$1996, ">=01/10/2025", 'Diogo Lima'!$N$2:$N$1996, "<=31/10/2025"), COUNTIFS('Lucas Almeida'!$E$2:$E$4000, "Landing Page", 'Lucas Almeida'!$G$2:$G$4000, "Em conversação", 'Lucas Almeida'!$N$2:$N$4000, ">=01/10/2025", 'Lucas Almeida'!$N$2:$N$4000, "<=31/10/2025"), COUNTIFS('Fernando Diamantino'!$E$2:$E$1999, "Landing Page", 'Fernando Diamantino'!$G$2:$G$1999, "Em conversação", 'Fernando Diamantino'!$N$2:$N$1999, ">=01/10/2025", 'Fernando Diamantino'!$N$2:$N$1999, "<=31/10/2025"), COUNTIFS('Maiara Andrade'!$E$2:$E$4000, "Landing Page", 'Maiara Andrade'!$G$2:$G$4000, "Em conversação", 'Maiara Andrade'!$N$2:$N$4000, ">=01/10/2025", 'Maiara Andrade'!$N$2:$N$4000, "<=31/10/2025"), COUNTIFS('Roberto Ramos'!$E$2:$E$4000, "Landing Page", 'Roberto Ramos'!$G$2:$G$4000, "Em conversação", 'Roberto Ramos'!$N$2:$N$4000, ">=01/10/2025", 'Roberto Ramos'!$N$2:$N$4000, "<=31/10/2025"), COUNTIFS('Amanda Facundo'!$E$2:$E$1999, "Landing Page", 'Amanda Facundo'!$G$2:$G$1999, "Em conversação", 'Amanda Facundo'!$N$2:$N$1999, ">=01/10/2025", 'Amanda Facundo'!$N$2:$N$1999, "<=31/10/2025"), COUNTIFS('Rodrigo Oliveira'!$E$2:$E$4000, "Landing Page", 'Rodrigo Oliveira'!$G$2:$G$4000, "Em conversação", 'Rodrigo Oliveira'!$N$2:$N$4000, ">=01/10/2025", 'Rodrigo Oliveira'!$N$2:$N$4000, "<=31/10/2025"), COUNTIFS('Marcio Jorge'!$E$2:$E$4000, "Landing Page", 'Marcio Jorge'!$G$2:$G$4000, "Em conversação", 'Marcio Jorge'!$N$2:$N$4000, ">=01/10/2025", 'Marcio Jorge'!$N$2:$N$4000, "<=31/10/2025") ) -> 0 | AU25: =SUM( COUNTIFS('Bruna Mamedes'!$E$2:$E$4000, "Landing Page", 'Bruna Mamedes'!$G$2:$G$4000, "Cotação Enviada", 'Bruna Mamedes'!$N$2:$N$4000, ">=01/10/2025", 'Bruna Mamedes'!$N$2:$N$4000, "<=31/10/2025"), COUNTIFS('Camila Adão'!$E$2:$E$1997, "Landing Page", 'Camila Adão'!$G$2:$G$1997, "Cotação Enviada", 'Camila Adão'!$N$2:$N$1997, ">=01/10/2025", 'Camila Adão'!$N$2:$N$1997, "<=31/10/2025"), COUNTIFS('Vendas Organicas'!$E$2:$E$3000, "Landing Page", 'Vendas Organicas'!$G$2:$G$3000, "Cotação Enviada", 'Vendas Organicas'!$N$2:$N$3000, ">=01/10/2025", 'Vendas Organicas'!$N$2:$N$3000, "<=31/10/2025"), COUNTIFS('Diogo Lima'!$E$2:$E$1996, "Landing Page", 'Diogo Lima'!$G$2:$G$1996, "Cotação Enviada", 'Diogo Lima'!$N$2:$N$1996, ">=01/10/2025", 'Diogo Lima'!$N$2:$N$1996, "<=31/10/2025"), COUNTIFS('Lucas Almeida'!$E$2:$E$4000, "Landing Page", 'Lucas Almeida'!$G$2:$G$4000, "Cotação Enviada", 'Lucas Almeida'!$N$2:$N$4000, ">=01/10/2025", 'Lucas Almeida'!$N$2:$N$4000, "<=31/10/2025"), COUNTIFS('Fernando Diamantino'!$E$2:$E$1999, "Landing Page", 'Fernando Diamantino'!$G$2:$G$1999, "Cotação Enviada", 'Fernando Diamantino'!$N$2:$N$1999, ">=01/10/2025", 'Fernando Diamantino'!$N$2:$N$1999, "<=31/10/2025"), COUNTIFS('Maiara Andrade'!$E$2:$E$4000, "Landing Page", 'Maiara Andrade'!$G$2:$G$4000, "Cotação Enviada", 'Maiara Andrade'!$N$2:$N$4000, ">=01/10/2025", 'Maiara Andrade'!$N$2:$N$4000, "<=31/10/2025"), COUNTIFS('Roberto Ramos'!$E$2:$E$4000, "Landing Page", 'Roberto Ramos'!$G$2:$G$4000, "Cotação Enviada", 'Roberto Ramos'!$N$2:$N$4000, ">=01/10/2025", 'Roberto Ramos'!$N$2:$N$4000, "<=31/10/2025"), COUNTIFS('Amanda Facundo'!$E$2:$E$1999, "Landing Page", 'Amanda Facundo'!$G$2:$G$1999, "Cotação Enviada", 'Amanda Facundo'!$N$2:$N$1999, ">=01/10/2025", 'Amanda Facundo'!$N$2:$N$1999, "<=31/10/2025"), COUNTIFS('Rodrigo Oliveira'!$E$2:$E$4000, "Landing Page", 'Rodrigo Oliveira'!$G$2:$G$4000, "Cotação Enviada", 'Rodrigo Oliveira'!$N$2:$N$4000, ">=01/10/2025", 'Rodrigo Oliveira'!$N$2:$N$4000, "<=31/10/2025"), COUNTIFS('Marcio Jorge'!$E$2:$E$4000, "Landing Page", 'Marcio Jorge'!$G$2:$G$4000, "Cotação Enviada", 'Marcio Jorge'!$N$2:$N$4000, ">=01/10/2025", 'Marcio Jorge'!$N$2:$N$4000, "<=31/10/2025") ) -> 0 | AV25: =SUM( COUNTIFS('Bruna Mamedes'!$E$2:$E$4000, "Landing Page", 'Bruna Mamedes'!$G$2:$G$4000, "Desistência", 'Bruna Mamedes'!$N$2:$N$4000, ">=01/10/2025", 'Bruna Mamedes'!$N$2:$N$4000, "<=31/10/2025"), COUNTIFS('Camila Adão'!$E$2:$E$1997, "Landing Page", 'Camila Adão'!$G$2:$G$1997, "Desistência", 'Camila Adão'!$N$2:$N$1997, ">=01/10/2025", 'Camila Adão'!$N$2:$N$1997, "<=31/10/2025"), COUNTIFS('Vendas Organicas'!$E$2:$E$3000, "Landing Page", 'Vendas Organicas'!$G$2:$G$3000, "Desistência", 'Vendas Organicas'!$N$2:$N$3000, ">=01/10/2025", 'Vendas Organicas'!$N$2:$N$3000, "<=31/10/2025"), COUNTIFS('Diogo Lima'!$E$2:$E$1996, "Landing Page", 'Diogo Lima'!$G$2:$G$1996, "Desistência", 'Diogo Lima'!$N$2:$N$1996, ">=01/10/2025", 'Diogo Lima'!$N$2:$N$1996, "<=31/10/2025"), COUNTIFS('Lucas Almeida'!$E$2:$E$4000, "Landing Page", 'Lucas Almeida'!$G$2:$G$4000, "Desistência", 'Lucas Almeida'!$N$2:$N$4000, ">=01/10/2025", 'Lucas Almeida'!$N$2:$N$4000, "<=31/10/2025"), COUNTIFS('Fernando Diamantino'!$E$2:$E$1999, "Landing Page", 'Fernando Diamantino'!$G$2:$G$1999, "Desistência", 'Fernando Diamantino'!$N$2:$N$1999, ">=01/10/2025", 'Fernando Diamantino'!$N$2:$N$1999, "<=31/10/2025"), COUNTIFS('Maiara Andrade'!$E$2:$E$4000, "Landing Page", 'Maiara Andrade'!$G$2:$G$4000, "Desistência", 'Maiara Andrade'!$N$2:$N$4000, ">=01/10/2025", 'Maiara Andrade'!$N$2:$N$4000, "<=31/10/2025"), COUNTIFS('Roberto Ramos'!$E$2:$E$4000, "Landing Page", 'Roberto Ramos'!$G$2:$G$4000, "Desistência", 'Roberto Ramos'!$N$2:$N$4000, ">=01/10/2025", 'Roberto Ramos'!$N$2:$N$4000, "<=31/10/2025"), COUNTIFS('Amanda Facundo'!$E$2:$E$1999, "Landing Page", 'Amanda Facundo'!$G$2:$G$1999, "Desistência", 'Amanda Facundo'!$N$2:$N$1999, ">=01/10/2025", 'Amanda Facundo'!$N$2:$N$1999, "<=31/10/2025"), COUNTIFS('Rodrigo Oliveira'!$E$2:$E$4000, "Landing Page", 'Rodrigo Oliveira'!$G$2:$G$4000, "Desistência", 'Rodrigo Oliveira'!$N$2:$N$4000, ">=01/10/2025", 'Rodrigo Oliveira'!$N$2:$N$4000, "<=31/10/2025"), COUNTIFS('Marcio Jorge'!$E$2:$E$4000, "Landing Page", 'Marcio Jorge'!$G$2:$G$4000, "Desistência", 'Marcio Jorge'!$N$2:$N$4000, ">=01/10/2025", 'Marcio Jorge'!$N$2:$N$4000, "<=31/10/2025") ) -> 0 | AW25: =SUM( COUNTIFS('Bruna Mamedes'!$E$2:$E$4000, "Landing Page", 'Bruna Mamedes'!$G$2:$G$4000, "Não Respondeu", 'Bruna Mamedes'!$N$2:$N$4000, ">=01/10/2025", 'Bruna Mamedes'!$N$2:$N$4000, "<=31/10/2025"), COUNTIFS('Camila Adão'!$E$2:$E$1997, "Landing Page", 'Camila Adão'!$G$2:$G$1997, "Não Respondeu", 'Camila Adão'!$N$2:$N$1997, ">=01/10/2025", 'Camila Adão'!$N$2:$N$1997, "<=31/10/2025"), COUNTIFS('Vendas Organicas'!$E$2:$E$3000, "Landing Page", 'Vendas Organicas'!$G$2:$G$3000, "Não Respondeu", 'Vendas Organicas'!$N$2:$N$3000, ">=01/10/2025", 'Vendas Organicas'!$N$2:$N$3000, "<=31/10/2025"), COUNTIFS('Diogo Lima'!$E$2:$E$1996, "Landing Page", 'Diogo Lima'!$G$2:$G$1996, "Não Respondeu", 'Diogo Lima'!$N$2:$N$1996, ">=01/10/2025", 'Diogo Lima'!$N$2:$N$1996, "<=31/10/2025"), COUNTIFS('Lucas Almeida'!$E$2:$E$4000, "Landing Page", 'Lucas Almeida'!$G$2:$G$4000, "Não Respondeu", 'Lucas Almeida'!$N$2:$N$4000, ">=01/10/2025", 'Lucas Almeida'!$N$2:$N$4000, "<=31/10/2025"), COUNTIFS('Fernando Diamantino'!$E$2:$E$1999, "Landing Page", 'Fernando Diamantino'!$G$2:$G$1999, "Não Respondeu", 'Fernando Diamantino'!$N$2:$N$1999, ">=01/10/2025", 'Fernando Diamantino'!$N$2:$N$1999, "<=31/10/2025"), COUNTIFS('Maiara Andrade'!$E$2:$E$4000, "Landing Page", 'Maiara Andrade'!$G$2:$G$4000, "Não Respondeu", 'Maiara Andrade'!$N$2:$N$4000, ">=01/10/2025", 'Maiara Andrade'!$N$2:$N$4000, "<=31/10/2025"), COUNTIFS('Roberto Ramos'!$E$2:$E$4000, "Landing Page", 'Roberto Ramos'!$G$2:$G$4000, "Não Respondeu", 'Roberto Ramos'!$N$2:$N$4000, ">=01/10/2025", 'Roberto Ramos'!$N$2:$N$4000, "<=31/10/2025"), COUNTIFS('Amanda Facundo'!$E$2:$E$1999, "Landing Page", 'Amanda Facundo'!$G$2:$G$1999, "Não Respondeu", 'Amanda Facundo'!$N$2:$N$1999, ">=01/10/2025", 'Amanda Facundo'!$N$2:$N$1999, "<=31/10/2025"), COUNTIFS('Rodrigo Oliveira'!$E$2:$E$4000, "Landing Page", 'Rodrigo Oliveira'!$G$2:$G$4000, "Não Respondeu", 'Rodrigo Oliveira'!$N$2:$N$4000, ">=01/10/2025", 'Rodrigo Oliveira'!$N$2:$N$4000, "<=31/10/2025"), COUNTIFS('Marcio Jorge'!$E$2:$E$4000, "Landing Page", 'Marcio Jorge'!$G$2:$G$4000, "Não Respondeu", 'Marcio Jorge'!$N$2:$N$4000, ">=01/10/2025", 'Marcio Jorge'!$N$2:$N$4000, "<=31/10/2025") ) -> 0 | AX25: =SUM( SUMIFS('Bruna Mamedes'!$H$2:$H$4000, 'Bruna Mamedes'!$E$2:$E$4000, "Landing Page", 'Bruna Mamedes'!$G$2:$G$4000, "Plano Fechado", 'Bruna Mamedes'!$N$2:$N$4000, ">=01/10/2025", 'Bruna Mamedes'!$N$2:$N$4000, "<=31/10/2025"), SUMIFS('Camila Adão'!$H$2:$H$1997, 'Camila Adão'!$E$2:$E$1997, "Landing Page", 'Camila Adão'!$G$2:$G$1997, "Plano Fechado", 'Camila Adão'!$N$2:$N$1997, ">=01/10/2025", 'Camila Adão'!$N$2:$N$1997, "<=31/10/2025"), SUMIFS('Vendas Organicas'!$H$2:$H$3000, 'Vendas Organicas'!$E$2:$E$3000, "Landing Page", 'Vendas Organicas'!$G$2:$G$3000, "Plano Fechado", 'Vendas Organicas'!$N$2:$N$3000, ">=01/10/2025", 'Vendas Organicas'!$N$2:$N$3000, "<=31/10/2025"), SUMIFS('Diogo Lima'!$H$2:$H$1996, 'Diogo Lima'!$E$2:$E$1996, "Landing Page", 'Diogo Lima'!$G$2:$G$1996, "Plano Fechado", 'Diogo Lima'!$N$2:$N$1996, ">=01/10/2025", 'Diogo Lima'!$N$2:$N$1996, "<=31/10/2025"), SUMIFS('Lucas Almeida'!$H$2:$H$4000, 'Lucas Almeida'!$E$2:$E$4000, "Landing Page", 'Lucas Almeida'!$G$2:$G$4000, "Plano Fechado", 'Lucas Almeida'!$N$2:$N$4000, ">=01/10/2025", 'Lucas Almeida'!$N$2:$N$4000, "<=31/10/2025"), SUMIFS('Fernando Diamantino'!$H$2:$H$1999, 'Fernando Diamantino'!$E$2:$E$1999, "Landing Page", 'Fernando Diamantino'!$G$2:$G$1999, "Plano Fechado", 'Fernando Diamantino'!$N$2:$N$1999, ">=01/10/2025", 'Fernando Diamantino'!$N$2:$N$1999, "<=31/10/2025"), SUMIFS('Maiara Andrade'!$H$2:$H$4000, 'Maiara Andrade'!$E$2:$E$4000, "Landing Page", 'Maiara Andrade'!$G$2:$G$4000, "Plano Fechado", 'Maiara Andrade'!$N$2:$N$4000, ">=01/10/2025", 'Maiara Andrade'!$N$2:$N$4000, "<=31/10/2025"), SUMIFS('Roberto Ramos'!$H$2:$H$4000, 'Roberto Ramos'!$E$2:$E$4000, "Landing Page", 'Roberto Ramos'!$G$2:$G$4000, "Plano Fechado", 'Roberto Ramos'!$N$2:$N$4000, ">=01/10/2025", 'Roberto Ramos'!$N$2:$N$4000, "<=31/10/2025"), SUMIFS('Amanda Facundo'!$H$2:$H$1999, 'Amanda Facundo'!$E$2:$E$1999, "Landing Page", 'Amanda Facundo'!$G$2:$G$1999, "Plano Fechado", 'Amanda Facundo'!$N$2:$N$1999, ">=01/10/2025", 'Amanda Facundo'!$N$2:$N$1999, "<=31/10/2025"), SUMIFS('Rodrigo Oliveira'!$H$2:$H$4000, 'Rodrigo Oliveira'!$E$2:$E$4000, "Landing Page", 'Rodrigo Oliveira'!$G$2:$G$4000, "Plano Fechado", 'Rodrigo Oliveira'!$N$2:$N$4000, ">=01/10/2025", 'Rodrigo Oliveira'!$N$2:$N$4000, "<=31/10/2025"), SUMIFS('Marcio Jorge'!$H$2:$H$4000, 'Marcio Jorge'!$E$2:$E$4000, "Landing Page", 'Marcio Jorge'!$G$2:$G$4000, "Plano Fechado", 'Marcio Jorge'!$N$2:$N$4000, ">=01/10/2025", 'Marcio Jorge'!$N$2:$N$4000, "<=31/10/2025") ) -> 0
C26: #DIV/0! | D26: #DIV/0! | E26: #DIV/0! | F26: #DIV/0! | G26: #DIV/0! | K26: #DIV/0! | L26: #DIV/0! | M26: #DIV/0! | N26: #DIV/0! | O26: #DIV/0! | S26: 0 | T26: 0 | U26: 0 | V26: 1 | W26: 0 | AA26: #DIV/0! | AB26: #DIV/0! | AC26: #DIV/0! | AD26: #DIV/0! | AE26: #DIV/0! | AI26: #DIV/0! | AJ26: #DIV/0! | AK26: #DIV/0! | AL26: #DIV/0! | AM26: #DIV/0! | AQ26: =(AQ25/AP25) -> 0 | AR26: =(AR25/AP25) -> 0 | AS26: =(AS25/AP25) -> 0 | AT26: =(AT25/AP25) -> 0 | AU26: =AU25/AP25 -> 0 | AV26: =AV25/AP25 -> 0 | AW26: =AW25/AP25 -> 0
B28: LEADS EXTRA | J28: LEADS EXTRA | R28: LEADS EXTRA | Z28: LEADS EXTRA | AH28: LEADS EXTRA | AP28: LEADS EXTRA
B29: QTD. Leads | C29: Vendas Fechadas | D29: Leads em Conversação | E29: Leads com Proposta Enviada | F29: Leads Desistentes | G29: Leads sem Resposta | H29: Faturamento | J29: QTD. Leads | K29: Vendas Fechadas | L29: Leads em Conversação | M29: Leads com Proposta Enviada | N29: Leads Desistentes | O29: Leads sem Resposta | P29: Faturamento | R29: QTD. Leads | S29: Vendas Fechadas | T29: Leads em Conversação | U29: Leads com Proposta Enviada | V29: Leads Desistentes | W29: Leads sem Resposta | X29: Faturamento | Z29: QTD. Leads | AA29: Vendas Fechadas | AB29: Leads em Conversação | AC29: Leads com Proposta Enviada | AD29: Leads Desistentes | AE29: Leads sem Resposta | AF29: Faturamento | AH29: QTD. Leads | AI29: Vendas Fechadas | AJ29: Leads em Conversação | AK29: Leads com Proposta Enviada | AL29: Leads Desistentes | AM29: Leads sem Resposta | AN29: Faturamento | AP29: QTD. Leads | AQ29: Plano Fechado | AR29: Em Análise | AS29: Aguardando Pagamento | AT29: Conversação | AU29: Proposta Enviada | AV29: Desistentes | AW29: Sem Resposta | AX29: Faturamento
B30: 14 | C30: 0 | D30: 2 | E30: 3 | F30: 0 | G30: 9 | H30: 0 | J30: 43 | K30: 0 | L30: 1 | M30: 10 | N30: 1 | O30: 25 | P30: 0 | R30: 125 | S30: 3 | T30: 10 | U30: 21 | V30: 34 | W30: 288 | X30: 3442.67 | Z30: 174 | AA30: 6 | AB30: 12 | AC30: 54 | AD30: 40 | AE30: 477 | AF30: 2476.32 | AH30: 236 | AI30: 6 | AJ30: 25 | AK30: 87 | AL30: 4 | AM30: 286 | AN30: 6684.64 | AP30: {=LET( abas, {"Amanda Facundo";"Bruna Mamedes";"Camila Adão";"Darlin Amorim";"Diogo Lima";"Externos";"Maiara Andrade";"Marcio Jorge";"Lucas Almeida";"Roberto Ramos";"Rodrigo Oliviera";"Leandro Nascimento";"Leandro Drumond";"Marcelle Marcela";"Anteriores";"Corretor 1";"Corretor 2";"Corretor 3";"Corretor 4";"Corretor 5"}, SUM( BYROW( abas, LAMBDA(a, COUNTIFS( INDIRECT("'"&a&"'!E:E"), "Extra", INDIRECT("'"&a&"'!N:N"), ">="&DATE(2025,10,1), INDIRECT("'"&a&"'!N:N"), "<="&DATE(2025,10,31) ) ) ) ) )} -> 93 | AQ30: =SUM( COUNTIFS('Bruna Mamedes'!$E$2:$E$4000, "Extra", 'Bruna Mamedes'!$G$2:$G$4000, "Plano Fechado", 'Bruna Mamedes'!$N$2:$N$4000, ">=01/10/2025", 'Bruna Mamedes'!$N$2:$N$4000, "<=31/10/2025"), COUNTIFS('Camila Adão'!$E$2:$E$1997, "Extra", 'Camila Adão'!$G$2:$G$1997, "Plano Fechado", 'Camila Adão'!$N$2:$N$1997, ">=01/10/2025", 'Camila Adão'!$N$2:$N$1997, "<=31/10/2025"), COUNTIFS('Vendas Organicas'!$E$2:$E$3000, "Extra", 'Vendas Organicas'!$G$2:$G$3000, "Plano Fechado", 'Vendas Organicas'!$N$2:$N$3000, ">=01/10/2025", 'Vendas Organicas'!$N$2:$N$3000, "<=31/10/2025"), COUNTIFS('Diogo Lima'!$E$2:$E$1996, "Extra", 'Diogo Lima'!$G$2:$G$1996, "Plano Fechado", 'Diogo Lima'!$N$2:$N$1996, ">=01/10/2025", 'Diogo Lima'!$N$2:$N$1996, "<=31/10/2025"), COUNTIFS('Lucas Almeida'!$E$2:$E$4000, "Extra", 'Lucas Almeida'!$G$2:$G$4000, "Plano Fechado", 'Lucas Almeida'!$N$2:$N$4000, ">=01/10/2025", 'Lucas Almeida'!$N$2:$N$4000, "<=31/10/2025"), COUNTIFS('Fernando Diamantino'!$E$2:$E$1999, "Extra", 'Fernando Diamantino'!$G$2:$G$1999, "Plano Fechado", 'Fernando Diamantino'!$N$2:$N$1999, ">=01/10/2025", 'Fernando Diamantino'!$N$2:$N$1999, "<=31/10/2025"), COUNTIFS('Maiara Andrade'!$E$2:$E$4000, "Extra", 'Maiara Andrade'!$G$2:$G$4000, "Plano Fechado", 'Maiara Andrade'!$N$2:$N$4000, ">=01/10/2025", 'Maiara Andrade'!$N$2:$N$4000, "<=31/10/2025"), COUNTIFS('Roberto Ramos'!$E$2:$E$4000, "Extra", 'Roberto Ramos'!$G$2:$G$4000, "Plano Fechado", 'Roberto Ramos'!$N$2:$N$4000, ">=01/10/2025", 'Roberto Ramos'!$N$2:$N$4000, "<=31/10/2025"), COUNTIFS('Amanda Facundo'!$E$2:$E$1999, "Extra", 'Amanda Facundo'!$G$2:$G$1999, "Plano Fechado", 'Amanda Facundo'!$N$2:$N$1999, ">=01/10/2025", 'Amanda Facundo'!$N$2:$N$1999, "<=31/10/2025"), COUNTIFS('Rodrigo Oliveira'!$E$2:$E$4000, "Extra", 'Rodrigo Oliveira'!$G$2:$G$4000, "Plano Fechado", 'Rodrigo Oliveira'!$N$2:$N$4000, ">=01/10/2025", 'Rodrigo Oliveira'!$N$2:$N$4000, "<=31/10/2025"), COUNTIFS('Marcio Jorge'!$E$2:$E$4000, "Extra", 'Marcio Jorge'!$G$2:$G$4000, "Plano Fechado", 'Marcio Jorge'!$N$2:$N$4000, ">=01/10/2025", 'Marcio Jorge'!$N$2:$N$4000, "<=31/10/2025") ) -> 2 | AR30: =SUM( COUNTIFS('Bruna Mamedes'!$E$2:$E$4000, "Extra", 'Bruna Mamedes'!$G$2:$G$4000, "Em Análise", 'Bruna Mamedes'!$N$2:$N$4000, ">=01/10/2025", 'Bruna Mamedes'!$N$2:$N$4000, "<=31/10/2025"), COUNTIFS('Camila Adão'!$E$2:$E$1997, "Extra", 'Camila Adão'!$G$2:$G$1997, "Em Análise", 'Camila Adão'!$N$2:$N$1997, ">=01/10/2025", 'Camila Adão'!$N$2:$N$1997, "<=31/10/2025"), COUNTIFS('Vendas Organicas'!$E$2:$E$3000, "Extra", 'Vendas Organicas'!$G$2:$G$3000, "Em Análise", 'Vendas Organicas'!$N$2:$N$3000, ">=01/10/2025", 'Vendas Organicas'!$N$2:$N$3000, "<=31/10/2025"), COUNTIFS('Diogo Lima'!$E$2:$E$1996, "Extra", 'Diogo Lima'!$G$2:$G$1996, "Em Análise", 'Diogo Lima'!$N$2:$N$1996, ">=01/10/2025", 'Diogo Lima'!$N$2:$N$1996, "<=31/10/2025"), COUNTIFS('Lucas Almeida'!$E$2:$E$4000, "Extra", 'Lucas Almeida'!$G$2:$G$4000, "Em Análise", 'Lucas Almeida'!$N$2:$N$4000, ">=01/10/2025", 'Lucas Almeida'!$N$2:$N$4000, "<=31/10/2025"), COUNTIFS('Fernando Diamantino'!$E$2:$E$1999, "Extra", 'Fernando Diamantino'!$G$2:$G$1999, "Em Análise", 'Fernando Diamantino'!$N$2:$N$1999, ">=01/10/2025", 'Fernando Diamantino'!$N$2:$N$1999, "<=31/10/2025"), COUNTIFS('Maiara Andrade'!$E$2:$E$4000, "Extra", 'Maiara Andrade'!$G$2:$G$4000, "Em Análise", 'Maiara Andrade'!$N$2:$N$4000, ">=01/10/2025", 'Maiara Andrade'!$N$2:$N$4000, "<=31/10/2025"), COUNTIFS('Roberto Ramos'!$E$2:$E$4000, "Extra", 'Roberto Ramos'!$G$2:$G$4000, "Em Análise", 'Roberto Ramos'!$N$2:$N$4000, ">=01/10/2025", 'Roberto Ramos'!$N$2:$N$4000, "<=31/10/2025"), COUNTIFS('Amanda Facundo'!$E$2:$E$1999, "Extra", 'Amanda Facundo'!$G$2:$G$1999, "Em Análise", 'Amanda Facundo'!$N$2:$N$1999, ">=01/10/2025", 'Amanda Facundo'!$N$2:$N$1999, "<=31/10/2025"), COUNTIFS('Rodrigo Oliveira'!$E$2:$E$4000, "Extra", 'Rodrigo Oliveira'!$G$2:$G$4000, "Em Análise", 'Rodrigo Oliveira'!$N$2:$N$4000, ">=01/10/2025", 'Rodrigo Oliveira'!$N$2:$N$4000, "<=31/10/2025"), COUNTIFS('Marcio Jorge'!$E$2:$E$4000, "Extra", 'Marcio Jorge'!$G$2:$G$4000, "Em Análise", 'Marcio Jorge'!$N$2:$N$4000, ">=01/10/2025", 'Marcio Jorge'!$N$2:$N$4000, "<=31/10/2025") ) -> 1 | AS30: =SUM( COUNTIFS('Bruna Mamedes'!$E$2:$E$4000, "Extra", 'Bruna Mamedes'!$G$2:$G$4000, "Aguardando Pagamento", 'Bruna Mamedes'!$N$2:$N$4000, ">=01/10/2025", 'Bruna Mamedes'!$N$2:$N$4000, "<=31/10/2025"), COUNTIFS('Camila Adão'!$E$2:$E$1997, "Extra", 'Camila Adão'!$G$2:$G$1997, "Aguardando Pagamento", 'Camila Adão'!$N$2:$N$1997, ">=01/10/2025", 'Camila Adão'!$N$2:$N$1997, "<=31/10/2025"), COUNTIFS('Vendas Organicas'!$E$2:$E$3000, "Extra", 'Vendas Organicas'!$G$2:$G$3000, "Aguardando Pagamento", 'Vendas Organicas'!$N$2:$N$3000, ">=01/10/2025", 'Vendas Organicas'!$N$2:$N$3000, "<=31/10/2025"), COUNTIFS('Diogo Lima'!$E$2:$E$1996, "Extra", 'Diogo Lima'!$G$2:$G$1996, "Aguardando Pagamento", 'Diogo Lima'!$N$2:$N$1996, ">=01/10/2025", 'Diogo Lima'!$N$2:$N$1996, "<=31/10/2025"), COUNTIFS('Lucas Almeida'!$E$2:$E$4000, "Extra", 'Lucas Almeida'!$G$2:$G$4000, "Aguardando Pagamento", 'Lucas Almeida'!$N$2:$N$4000, ">=01/10/2025", 'Lucas Almeida'!$N$2:$N$4000, "<=31/10/2025"), COUNTIFS('Fernando Diamantino'!$E$2:$E$1999, "Extra", 'Fernando Diamantino'!$G$2:$G$1999, "Aguardando Pagamento", 'Fernando Diamantino'!$N$2:$N$1999, ">=01/10/2025", 'Fernando Diamantino'!$N$2:$N$1999, "<=31/10/2025"), COUNTIFS('Maiara Andrade'!$E$2:$E$4000, "Extra", 'Maiara Andrade'!$G$2:$G$4000, "Aguardando Pagamento", 'Maiara Andrade'!$N$2:$N$4000, ">=01/10/2025", 'Maiara Andrade'!$N$2:$N$4000, "<=31/10/2025"), COUNTIFS('Roberto Ramos'!$E$2:$E$4000, "Extra", 'Roberto Ramos'!$G$2:$G$4000, "Aguardando Pagamento", 'Roberto Ramos'!$N$2:$N$4000, ">=01/10/2025", 'Roberto Ramos'!$N$2:$N$4000, "<=31/10/2025"), COUNTIFS('Amanda Facundo'!$E$2:$E$1999, "Extra", 'Amanda Facundo'!$G$2:$G$1999, "Aguardando Pagamento", 'Amanda Facundo'!$N$2:$N$1999, ">=01/10/2025", 'Amanda Facundo'!$N$2:$N$1999, "<=31/10/2025"), COUNTIFS('Rodrigo Oliveira'!$E$2:$E$4000, "Extra", 'Rodrigo Oliveira'!$G$2:$G$4000, "Aguardando Pagamento", 'Rodrigo Oliveira'!$N$2:$N$4000, ">=01/10/2025", 'Rodrigo Oliveira'!$N$2:$N$4000, "<=31/10/2025"), COUNTIFS('Marcio Jorge'!$E$2:$E$4000, "Extra", 'Marcio Jorge'!$G$2:$G$4000, "Aguardando Pagamento", 'Marcio Jorge'!$N$2:$N$4000, ">=01/10/2025", 'Marcio Jorge'!$N$2:$N$4000, "<=31/10/2025") ) -> 0 | AT30: =SUM( COUNTIFS('Bruna Mamedes'!$E$2:$E$4000, "Extra", 'Bruna Mamedes'!$G$2:$G$4000, "Em conversação", 'Bruna Mamedes'!$N$2:$N$4000, ">=01/10/2025", 'Bruna Mamedes'!$N$2:$N$4000, "<=31/10/2025"), COUNTIFS('Camila Adão'!$E$2:$E$1997, "Extra", 'Camila Adão'!$G$2:$G$1997, "Em conversação", 'Camila Adão'!$N$2:$N$1997, ">=01/10/2025", 'Camila Adão'!$N$2:$N$1997, "<=31/10/2025"), COUNTIFS('Vendas Organicas'!$E$2:$E$3000, "Extra", 'Vendas Organicas'!$G$2:$G$3000, "Em conversação", 'Vendas Organicas'!$N$2:$N$3000, ">=01/10/2025", 'Vendas Organicas'!$N$2:$N$3000, "<=31/10/2025"), COUNTIFS('Diogo Lima'!$E$2:$E$1996, "Extra", 'Diogo Lima'!$G$2:$G$1996, "Em conversação", 'Diogo Lima'!$N$2:$N$1996, ">=01/10/2025", 'Diogo Lima'!$N$2:$N$1996, "<=31/10/2025"), COUNTIFS('Lucas Almeida'!$E$2:$E$4000, "Extra", 'Lucas Almeida'!$G$2:$G$4000, "Em conversação", 'Lucas Almeida'!$N$2:$N$4000, ">=01/10/2025", 'Lucas Almeida'!$N$2:$N$4000, "<=31/10/2025"), COUNTIFS('Fernando Diamantino'!$E$2:$E$1999, "Extra", 'Fernando Diamantino'!$G$2:$G$1999, "Em conversação", 'Fernando Diamantino'!$N$2:$N$1999, ">=01/10/2025", 'Fernando Diamantino'!$N$2:$N$1999, "<=31/10/2025"), COUNTIFS('Maiara Andrade'!$E$2:$E$4000, "Extra", 'Maiara Andrade'!$G$2:$G$4000, "Em conversação", 'Maiara Andrade'!$N$2:$N$4000, ">=01/10/2025", 'Maiara Andrade'!$N$2:$N$4000, "<=31/10/2025"), COUNTIFS('Roberto Ramos'!$E$2:$E$4000, "Extra", 'Roberto Ramos'!$G$2:$G$4000, "Em conversação", 'Roberto Ramos'!$N$2:$N$4000, ">=01/10/2025", 'Roberto Ramos'!$N$2:$N$4000, "<=31/10/2025"), COUNTIFS('Amanda Facundo'!$E$2:$E$1999, "Extra", 'Amanda Facundo'!$G$2:$G$1999, "Em conversação", 'Amanda Facundo'!$N$2:$N$1999, ">=01/10/2025", 'Amanda Facundo'!$N$2:$N$1999, "<=31/10/2025"), COUNTIFS('Rodrigo Oliveira'!$E$2:$E$4000, "Extra", 'Rodrigo Oliveira'!$G$2:$G$4000, "Em conversação", 'Rodrigo Oliveira'!$N$2:$N$4000, ">=01/10/2025", 'Rodrigo Oliveira'!$N$2:$N$4000, "<=31/10/2025"), COUNTIFS('Marcio Jorge'!$E$2:$E$4000, "Extra", 'Marcio Jorge'!$G$2:$G$4000, "Em conversação", 'Marcio Jorge'!$N$2:$N$4000, ">=01/10/2025", 'Marcio Jorge'!$N$2:$N$4000, "<=31/10/2025") ) -> 0 | AU30: =SUM( COUNTIFS('Bruna Mamedes'!$E$2:$E$4000, "Extra", 'Bruna Mamedes'!$G$2:$G$4000, "Cotação Enviada", 'Bruna Mamedes'!$N$2:$N$4000, ">=01/10/2025", 'Bruna Mamedes'!$N$2:$N$4000, "<=31/10/2025"), COUNTIFS('Camila Adão'!$E$2:$E$1997, "Extra", 'Camila Adão'!$G$2:$G$1997, "Cotação Enviada", 'Camila Adão'!$N$2:$N$1997, ">=01/10/2025", 'Camila Adão'!$N$2:$N$1997, "<=31/10/2025"), COUNTIFS('Vendas Organicas'!$E$2:$E$3000, "Extra", 'Vendas Organicas'!$G$2:$G$3000, "Cotação Enviada", 'Vendas Organicas'!$N$2:$N$3000, ">=01/10/2025", 'Vendas Organicas'!$N$2:$N$3000, "<=31/10/2025"), COUNTIFS('Diogo Lima'!$E$2:$E$1996, "Extra", 'Diogo Lima'!$G$2:$G$1996, "Cotação Enviada", 'Diogo Lima'!$N$2:$N$1996, ">=01/10/2025", 'Diogo Lima'!$N$2:$N$1996, "<=31/10/2025"), COUNTIFS('Lucas Almeida'!$E$2:$E$4000, "Extra", 'Lucas Almeida'!$G$2:$G$4000, "Cotação Enviada", 'Lucas Almeida'!$N$2:$N$4000, ">=01/10/2025", 'Lucas Almeida'!$N$2:$N$4000, "<=31/10/2025"), COUNTIFS('Fernando Diamantino'!$E$2:$E$1999, "Extra", 'Fernando Diamantino'!$G$2:$G$1999, "Cotação Enviada", 'Fernando Diamantino'!$N$2:$N$1999, ">=01/10/2025", 'Fernando Diamantino'!$N$2:$N$1999, "<=31/10/2025"), COUNTIFS('Maiara Andrade'!$E$2:$E$4000, "Extra", 'Maiara Andrade'!$G$2:$G$4000, "Cotação Enviada", 'Maiara Andrade'!$N$2:$N$4000, ">=01/10/2025", 'Maiara Andrade'!$N$2:$N$4000, "<=31/10/2025"), COUNTIFS('Roberto Ramos'!$E$2:$E$4000, "Extra", 'Roberto Ramos'!$G$2:$G$4000, "Cotação Enviada", 'Roberto Ramos'!$N$2:$N$4000, ">=01/10/2025", 'Roberto Ramos'!$N$2:$N$4000, "<=31/10/2025"), COUNTIFS('Amanda Facundo'!$E$2:$E$1999, "Extra", 'Amanda Facundo'!$G$2:$G$1999, "Cotação Enviada", 'Amanda Facundo'!$N$2:$N$1999, ">=01/10/2025", 'Amanda Facundo'!$N$2:$N$1999, "<=31/10/2025"), COUNTIFS('Rodrigo Oliveira'!$E$2:$E$4000, "Extra", 'Rodrigo Oliveira'!$G$2:$G$4000, "Cotação Enviada", 'Rodrigo Oliveira'!$N$2:$N$4000, ">=01/10/2025", 'Rodrigo Oliveira'!$N$2:$N$4000, "<=31/10/2025"), COUNTIFS('Marcio Jorge'!$E$2:$E$4000, "Extra", 'Marcio Jorge'!$G$2:$G$4000, "Cotação Enviada", 'Marcio Jorge'!$N$2:$N$4000, ">=01/10/2025", 'Marcio Jorge'!$N$2:$N$4000, "<=31/10/2025") ) -> 12 | AV30: =SUM( COUNTIFS('Bruna Mamedes'!$E$2:$E$4000, "Extra", 'Bruna Mamedes'!$G$2:$G$4000, "Desistência", 'Bruna Mamedes'!$N$2:$N$4000, ">=01/10/2025", 'Bruna Mamedes'!$N$2:$N$4000, "<=31/10/2025"), COUNTIFS('Camila Adão'!$E$2:$E$1997, "Extra", 'Camila Adão'!$G$2:$G$1997, "Desistência", 'Camila Adão'!$N$2:$N$1997, ">=01/10/2025", 'Camila Adão'!$N$2:$N$1997, "<=31/10/2025"), COUNTIFS('Vendas Organicas'!$E$2:$E$3000, "Extra", 'Vendas Organicas'!$G$2:$G$3000, "Desistência", 'Vendas Organicas'!$N$2:$N$3000, ">=01/10/2025", 'Vendas Organicas'!$N$2:$N$3000, "<=31/10/2025"), COUNTIFS('Diogo Lima'!$E$2:$E$1996, "Extra", 'Diogo Lima'!$G$2:$G$1996, "Desistência", 'Diogo Lima'!$N$2:$N$1996, ">=01/10/2025", 'Diogo Lima'!$N$2:$N$1996, "<=31/10/2025"), COUNTIFS('Lucas Almeida'!$E$2:$E$4000, "Extra", 'Lucas Almeida'!$G$2:$G$4000, "Desistência", 'Lucas Almeida'!$N$2:$N$4000, ">=01/10/2025", 'Lucas Almeida'!$N$2:$N$4000, "<=31/10/2025"), COUNTIFS('Fernando Diamantino'!$E$2:$E$1999, "Extra", 'Fernando Diamantino'!$G$2:$G$1999, "Desistência", 'Fernando Diamantino'!$N$2:$N$1999, ">=01/10/2025", 'Fernando Diamantino'!$N$2:$N$1999, "<=31/10/2025"), COUNTIFS('Maiara Andrade'!$E$2:$E$4000, "Extra", 'Maiara Andrade'!$G$2:$G$4000, "Desistência", 'Maiara Andrade'!$N$2:$N$4000, ">=01/10/2025", 'Maiara Andrade'!$N$2:$N$4000, "<=31/10/2025"), COUNTIFS('Roberto Ramos'!$E$2:$E$4000, "Extra", 'Roberto Ramos'!$G$2:$G$4000, "Desistência", 'Roberto Ramos'!$N$2:$N$4000, ">=01/10/2025", 'Roberto Ramos'!$N$2:$N$4000, "<=31/10/2025"), COUNTIFS('Amanda Facundo'!$E$2:$E$1999, "Extra", 'Amanda Facundo'!$G$2:$G$1999, "Desistência", 'Amanda Facundo'!$N$2:$N$1999, ">=01/10/2025", 'Amanda Facundo'!$N$2:$N$1999, "<=31/10/2025"), COUNTIFS('Rodrigo Oliveira'!$E$2:$E$4000, "Extra", 'Rodrigo Oliveira'!$G$2:$G$4000, "Desistência", 'Rodrigo Oliveira'!$N$2:$N$4000, ">=01/10/2025", 'Rodrigo Oliveira'!$N$2:$N$4000, "<=31/10/2025"), COUNTIFS('Marcio Jorge'!$E$2:$E$4000, "Extra", 'Marcio Jorge'!$G$2:$G$4000, "Desistência", 'Marcio Jorge'!$N$2:$N$4000, ">=01/10/2025", 'Marcio Jorge'!$N$2:$N$4000, "<=31/10/2025") ) -> 2 | AW30: =SUM( COUNTIFS('Bruna Mamedes'!$E$2:$E$4000, "Extra", 'Bruna Mamedes'!$G$2:$G$4000, "Não Respondeu", 'Bruna Mamedes'!$N$2:$N$4000, ">=01/10/2025", 'Bruna Mamedes'!$N$2:$N$4000, "<=31/10/2025"), COUNTIFS('Camila Adão'!$E$2:$E$1997, "Extra", 'Camila Adão'!$G$2:$G$1997, "Não Respondeu", 'Camila Adão'!$N$2:$N$1997, ">=01/10/2025", 'Camila Adão'!$N$2:$N$1997, "<=31/10/2025"), COUNTIFS('Vendas Organicas'!$E$2:$E$3000, "Extra", 'Vendas Organicas'!$G$2:$G$3000, "Não Respondeu", 'Vendas Organicas'!$N$2:$N$3000, ">=01/10/2025", 'Vendas Organicas'!$N$2:$N$3000, "<=31/10/2025"), COUNTIFS('Diogo Lima'!$E$2:$E$1996, "Extra", 'Diogo Lima'!$G$2:$G$1996, "Não Respondeu", 'Diogo Lima'!$N$2:$N$1996, ">=01/10/2025", 'Diogo Lima'!$N$2:$N$1996, "<=31/10/2025"), COUNTIFS('Lucas Almeida'!$E$2:$E$4000, "Extra", 'Lucas Almeida'!$G$2:$G$4000, "Não Respondeu", 'Lucas Almeida'!$N$2:$N$4000, ">=01/10/2025", 'Lucas Almeida'!$N$2:$N$4000, "<=31/10/2025"), COUNTIFS('Fernando Diamantino'!$E$2:$E$1999, "Extra", 'Fernando Diamantino'!$G$2:$G$1999, "Não Respondeu", 'Fernando Diamantino'!$N$2:$N$1999, ">=01/10/2025", 'Fernando Diamantino'!$N$2:$N$1999, "<=31/10/2025"), COUNTIFS('Maiara Andrade'!$E$2:$E$4000, "Extra", 'Maiara Andrade'!$G$2:$G$4000, "Não Respondeu", 'Maiara Andrade'!$N$2:$N$4000, ">=01/10/2025", 'Maiara Andrade'!$N$2:$N$4000, "<=31/10/2025"), COUNTIFS('Roberto Ramos'!$E$2:$E$4000, "Extra", 'Roberto Ramos'!$G$2:$G$4000, "Não Respondeu", 'Roberto Ramos'!$N$2:$N$4000, ">=01/10/2025", 'Roberto Ramos'!$N$2:$N$4000, "<=31/10/2025"), COUNTIFS('Amanda Facundo'!$E$2:$E$1999, "Extra", 'Amanda Facundo'!$G$2:$G$1999, "Não Respondeu", 'Amanda Facundo'!$N$2:$N$1999, ">=01/10/2025", 'Amanda Facundo'!$N$2:$N$1999, "<=31/10/2025"), COUNTIFS('Rodrigo Oliveira'!$E$2:$E$4000, "Extra", 'Rodrigo Oliveira'!$G$2:$G$4000, "Não Respondeu", 'Rodrigo Oliveira'!$N$2:$N$4000, ">=01/10/2025", 'Rodrigo Oliveira'!$N$2:$N$4000, "<=31/10/2025"), COUNTIFS('Marcio Jorge'!$E$2:$E$4000, "Extra", 'Marcio Jorge'!$G$2:$G$4000, "Não Respondeu", 'Marcio Jorge'!$N$2:$N$4000, ">=01/10/2025", 'Marcio Jorge'!$N$2:$N$4000, "<=31/10/2025") ) -> 25 | AX30: =SUM( SUMIFS('Bruna Mamedes'!$H$2:$H$4000, 'Bruna Mamedes'!$E$2:$E$4000, "Extra", 'Bruna Mamedes'!$G$2:$G$4000, "Plano Fechado", 'Bruna Mamedes'!$N$2:$N$4000, ">=01/10/2025", 'Bruna Mamedes'!$N$2:$N$4000, "<=31/10/2025"), SUMIFS('Camila Adão'!$H$2:$H$1997, 'Camila Adão'!$E$2:$E$1997, "Extra", 'Camila Adão'!$G$2:$G$1997, "Plano Fechado", 'Camila Adão'!$N$2:$N$1997, ">=01/10/2025", 'Camila Adão'!$N$2:$N$1997, "<=31/10/2025"), SUMIFS('Vendas Organicas'!$H$2:$H$3000, 'Vendas Organicas'!$E$2:$E$3000, "Extra", 'Vendas Organicas'!$G$2:$G$3000, "Plano Fechado", 'Vendas Organicas'!$N$2:$N$3000, ">=01/10/2025", 'Vendas Organicas'!$N$2:$N$3000, "<=31/10/2025"), SUMIFS('Diogo Lima'!$H$2:$H$1996, 'Diogo Lima'!$E$2:$E$1996, "Extra", 'Diogo Lima'!$G$2:$G$1996, "Plano Fechado", 'Diogo Lima'!$N$2:$N$1996, ">=01/10/2025", 'Diogo Lima'!$N$2:$N$1996, "<=31/10/2025"), SUMIFS('Lucas Almeida'!$H$2:$H$4000, 'Lucas Almeida'!$E$2:$E$4000, "Extra", 'Lucas Almeida'!$G$2:$G$4000, "Plano Fechado", 'Lucas Almeida'!$N$2:$N$4000, ">=01/10/2025", 'Lucas Almeida'!$N$2:$N$4000, "<=31/10/2025"), SUMIFS('Fernando Diamantino'!$H$2:$H$1999, 'Fernando Diamantino'!$E$2:$E$1999, "Extra", 'Fernando Diamantino'!$G$2:$G$1999, "Plano Fechado", 'Fernando Diamantino'!$N$2:$N$1999, ">=01/10/2025", 'Fernando Diamantino'!$N$2:$N$1999, "<=31/10/2025"), SUMIFS('Maiara Andrade'!$H$2:$H$4000, 'Maiara Andrade'!$E$2:$E$4000, "Extra", 'Maiara Andrade'!$G$2:$G$4000, "Plano Fechado", 'Maiara Andrade'!$N$2:$N$4000, ">=01/10/2025", 'Maiara Andrade'!$N$2:$N$4000, "<=31/10/2025"), SUMIFS('Roberto Ramos'!$H$2:$H$4000, 'Roberto Ramos'!$E$2:$E$4000, "Extra", 'Roberto Ramos'!$G$2:$G$4000, "Plano Fechado", 'Roberto Ramos'!$N$2:$N$4000, ">=01/10/2025", 'Roberto Ramos'!$N$2:$N$4000, "<=31/10/2025"), SUMIFS('Amanda Facundo'!$H$2:$H$1999, 'Amanda Facundo'!$E$2:$E$1999, "Extra", 'Amanda Facundo'!$G$2:$G$1999, "Plano Fechado", 'Amanda Facundo'!$N$2:$N$1999, ">=01/10/2025", 'Amanda Facundo'!$N$2:$N$1999, "<=31/10/2025"), SUMIFS('Rodrigo Oliveira'!$H$2:$H$4000, 'Rodrigo Oliveira'!$E$2:$E$4000, "Extra", 'Rodrigo Oliveira'!$G$2:$G$4000, "Plano Fechado", 'Rodrigo Oliveira'!$N$2:$N$4000, ">=01/10/2025", 'Rodrigo Oliveira'!$N$2:$N$4000, "<=31/10/2025"), SUMIFS('Marcio Jorge'!$H$2:$H$4000, 'Marcio Jorge'!$E$2:$E$4000, "Extra", 'Marcio Jorge'!$G$2:$G$4000, "Plano Fechado", 'Marcio Jorge'!$N$2:$N$4000, ">=01/10/2025", 'Marcio Jorge'!$N$2:$N$4000, "<=31/10/2025") ) -> 2694.66
C31: 0 | D31: 0.143 | E31: 0.214 | F31: 0 | G31: 0.643 | K31: 0 | L31: 0.023 | M31: 0.233 | N31: 0.023 | O31: 0.581 | S31: 0.024 | T31: 0.08 | U31: 0.168 | V31: 0.272 | W31: 2.304 | AA31: 0.034 | AB31: 0.069 | AC31: 0.31 | AD31: 0.23 | AE31: 2.741 | AI31: 0.025 | AJ31: 0.106 | AK31: 0.369 | AL31: 0.017 | AM31: 1.212 | AQ31: =(AQ30/AP30) -> 0.021505376 | AR31: =(AR30/AP30) -> 0.010752688 | AS31: =(AS30/AP30) -> 0 | AT31: =(AT30/AP30) -> 0 | AU31: =AU30/AP30 -> 0.12903226 | AV31: =AV30/AP30 -> 0.021505376 | AW31: =AW30/AP30 -> 0.2688172
B33: LEADS INDICAÇÃO | J33: LEADS INDICAÇÃO | R33: LEADS INDICAÇÃO | Z33: LEADS INDICAÇÃO | AH33: LEADS INDICAÇÃO | AP33: LEADS INDICAÇÃO
B34: QTD. Leads | C34: Vendas Fechadas | D34: Leads em Conversação | E34: Leads com Proposta Enviada | F34: Leads Desistentes | G34: Leads sem Resposta | H34: Faturamento | J34: QTD. Leads | K34: Vendas Fechadas | L34: Leads em Conversação | M34: Leads com Proposta Enviada | N34: Leads Desistentes | O34: Leads sem Resposta | P34: Faturamento | R34: QTD. Leads | S34: Vendas Fechadas | T34: Leads em Conversação | U34: Leads com Proposta Enviada | V34: Leads Desistentes | W34: Leads sem Resposta | X34: Faturamento | Z34: QTD. Leads | AA34: Vendas Fechadas | AB34: Leads em Conversação | AC34: Leads com Proposta Enviada | AD34: Leads Desistentes | AE34: Leads sem Resposta | AF34: Faturamento | AH34: QTD. Leads | AI34: Vendas Fechadas | AJ34: Leads em Conversação | AK34: Leads com Proposta Enviada | AL34: Leads Desistentes | AM34: Leads sem Resposta | AN34: Faturamento | AP34: QTD. Leads | AQ34: Plano Fechado | AR34: Em Análise | AS34: Aguardando Pagamento | AT34: Conversação | AU34: Proposta Enviada | AV34: Desistentes | AW34: Sem Resposta | AX34: Faturamento
B35: 6 | C35: 4 | D35: 0 | E35: 1 | F35: 1 | G35: 0 | H35: 3267.91 | J35: 37 | K35: 34 | L35: 2 | M35: 0 | N35: 0 | O35: 1 | P35: 73198.56 | R35: 42 | S35: 27 | T35: 1 | U35: 6 | V35: 3 | W35: 6 | X35: 45464.3 | Z35: 29 | AA35: 25 | AB35: 1 | AC35: 3 | AD35: 2 | AE35: 1 | AF35: 27957.35 | AH35: 29 | AI35: 26 | AJ35: 1 | AK35: 1 | AL35: 2 | AM35: 0 | AN35: 30080.44 | AP35: {=LET( abas, {"Amanda Facundo";"Bruna Mamedes";"Camila Adão";"Darlin Amorim";"Diogo Lima";"Externos";"Maiara Andrade";"Marcio Jorge";"Lucas Almeida";"Roberto Ramos";"Rodrigo Oliviera";"Leandro Nascimento";"Leandro Drumond";"Marcelle Marcela";"Anteriores";"Corretor 1";"Corretor 2";"Corretor 3";"Corretor 4";"Corretor 5"}, SUM( BYROW( abas, LAMBDA(a, COUNTIFS( INDIRECT("'"&a&"'!E:E"), "Indicação", INDIRECT("'"&a&"'!N:N"), ">="&DATE(2025,10,1), INDIRECT("'"&a&"'!N:N"), "<="&DATE(2025,10,31) ) ) ) ) )} -> 21 | AQ35: =SUM( COUNTIFS('Bruna Mamedes'!$E$2:$E$4000, "Indicação", 'Bruna Mamedes'!$G$2:$G$4000, "Plano Fechado", 'Bruna Mamedes'!$N$2:$N$4000, ">=01/10/2025", 'Bruna Mamedes'!$N$2:$N$4000, "<=31/10/2025"), COUNTIFS('Camila Adão'!$E$2:$E$1997, "Indicação", 'Camila Adão'!$G$2:$G$1997, "Plano Fechado", 'Camila Adão'!$N$2:$N$1997, ">=01/10/2025", 'Camila Adão'!$N$2:$N$1997, "<=31/10/2025"), COUNTIFS('Vendas Organicas'!$E$2:$E$3000, "Indicação", 'Vendas Organicas'!$G$2:$G$3000, "Plano Fechado", 'Vendas Organicas'!$N$2:$N$3000, ">=01/10/2025", 'Vendas Organicas'!$N$2:$N$3000, "<=31/10/2025"), COUNTIFS('Diogo Lima'!$E$2:$E$1996, "Indicação", 'Diogo Lima'!$G$2:$G$1996, "Plano Fechado", 'Diogo Lima'!$N$2:$N$1996, ">=01/10/2025", 'Diogo Lima'!$N$2:$N$1996, "<=31/10/2025"), COUNTIFS('Lucas Almeida'!$E$2:$E$4000, "Indicação", 'Lucas Almeida'!$G$2:$G$4000, "Plano Fechado", 'Lucas Almeida'!$N$2:$N$4000, ">=01/10/2025", 'Lucas Almeida'!$N$2:$N$4000, "<=31/10/2025"), COUNTIFS('Fernando Diamantino'!$E$2:$E$1999, "Indicação", 'Fernando Diamantino'!$G$2:$G$1999, "Plano Fechado", 'Fernando Diamantino'!$N$2:$N$1999, ">=01/10/2025", 'Fernando Diamantino'!$N$2:$N$1999, "<=31/10/2025"), COUNTIFS('Maiara Andrade'!$E$2:$E$4000, "Indicação", 'Maiara Andrade'!$G$2:$G$4000, "Plano Fechado", 'Maiara Andrade'!$N$2:$N$4000, ">=01/10/2025", 'Maiara Andrade'!$N$2:$N$4000, "<=31/10/2025"), COUNTIFS('Roberto Ramos'!$E$2:$E$4000, "Indicação", 'Roberto Ramos'!$G$2:$G$4000, "Plano Fechado", 'Roberto Ramos'!$N$2:$N$4000, ">=01/10/2025", 'Roberto Ramos'!$N$2:$N$4000, "<=31/10/2025"), COUNTIFS('Amanda Facundo'!$E$2:$E$1999, "Indicação", 'Amanda Facundo'!$G$2:$G$1999, "Plano Fechado", 'Amanda Facundo'!$N$2:$N$1999, ">=01/10/2025", 'Amanda Facundo'!$N$2:$N$1999, "<=31/10/2025"), COUNTIFS('Rodrigo Oliveira'!$E$2:$E$4000, "Indicação", 'Rodrigo Oliveira'!$G$2:$G$4000, "Plano Fechado", 'Rodrigo Oliveira'!$N$2:$N$4000, ">=01/10/2025", 'Rodrigo Oliveira'!$N$2:$N$4000, "<=31/10/2025"), COUNTIFS('Marcio Jorge'!$E$2:$E$4000, "Indicação", 'Marcio Jorge'!$G$2:$G$4000, "Plano Fechado", 'Marcio Jorge'!$N$2:$N$4000, ">=01/10/2025", 'Marcio Jorge'!$N$2:$N$4000, "<=31/10/2025") ) -> 12 | AR35: =SUM( COUNTIFS('Bruna Mamedes'!$E$2:$E$4000, "Indicação", 'Bruna Mamedes'!$G$2:$G$4000, "Em Análise", 'Bruna Mamedes'!$N$2:$N$4000, ">=01/10/2025", 'Bruna Mamedes'!$N$2:$N$4000, "<=31/10/2025"), COUNTIFS('Camila Adão'!$E$2:$E$1997, "Indicação", 'Camila Adão'!$G$2:$G$1997, "Em Análise", 'Camila Adão'!$N$2:$N$1997, ">=01/10/2025", 'Camila Adão'!$N$2:$N$1997, "<=31/10/2025"), COUNTIFS('Vendas Organicas'!$E$2:$E$3000, "Indicação", 'Vendas Organicas'!$G$2:$G$3000, "Em Análise", 'Vendas Organicas'!$N$2:$N$3000, ">=01/10/2025", 'Vendas Organicas'!$N$2:$N$3000, "<=31/10/2025"), COUNTIFS('Diogo Lima'!$E$2:$E$1996, "Indicação", 'Diogo Lima'!$G$2:$G$1996, "Em Análise", 'Diogo Lima'!$N$2:$N$1996, ">=01/10/2025", 'Diogo Lima'!$N$2:$N$1996, "<=31/10/2025"), COUNTIFS('Lucas Almeida'!$E$2:$E$4000, "Indicação", 'Lucas Almeida'!$G$2:$G$4000, "Em Análise", 'Lucas Almeida'!$N$2:$N$4000, ">=01/10/2025", 'Lucas Almeida'!$N$2:$N$4000, "<=31/10/2025"), COUNTIFS('Fernando Diamantino'!$E$2:$E$1999, "Indicação", 'Fernando Diamantino'!$G$2:$G$1999, "Em Análise", 'Fernando Diamantino'!$N$2:$N$1999, ">=01/10/2025", 'Fernando Diamantino'!$N$2:$N$1999, "<=31/10/2025"), COUNTIFS('Maiara Andrade'!$E$2:$E$4000, "Indicação", 'Maiara Andrade'!$G$2:$G$4000, "Em Análise", 'Maiara Andrade'!$N$2:$N$4000, ">=01/10/2025", 'Maiara Andrade'!$N$2:$N$4000, "<=31/10/2025"), COUNTIFS('Roberto Ramos'!$E$2:$E$4000, "Indicação", 'Roberto Ramos'!$G$2:$G$4000, "Em Análise", 'Roberto Ramos'!$N$2:$N$4000, ">=01/10/2025", 'Roberto Ramos'!$N$2:$N$4000, "<=31/10/2025"), COUNTIFS('Amanda Facundo'!$E$2:$E$1999, "Indicação", 'Amanda Facundo'!$G$2:$G$1999, "Em Análise", 'Amanda Facundo'!$N$2:$N$1999, ">=01/10/2025", 'Amanda Facundo'!$N$2:$N$1999, "<=31/10/2025"), COUNTIFS('Rodrigo Oliveira'!$E$2:$E$4000, "Indicação", 'Rodrigo Oliveira'!$G$2:$G$4000, "Em Análise", 'Rodrigo Oliveira'!$N$2:$N$4000, ">=01/10/2025", 'Rodrigo Oliveira'!$N$2:$N$4000, "<=31/10/2025"), COUNTIFS('Marcio Jorge'!$E$2:$E$4000, "Indicação", 'Marcio Jorge'!$G$2:$G$4000, "Em Análise", 'Marcio Jorge'!$N$2:$N$4000, ">=01/10/2025", 'Marcio Jorge'!$N$2:$N$4000, "<=31/10/2025") ) -> 4 | AS35: =SUM( COUNTIFS('Bruna Mamedes'!$E$2:$E$4000, "Indicação", 'Bruna Mamedes'!$G$2:$G$4000, "Aguardando Pagamento", 'Bruna Mamedes'!$N$2:$N$4000, ">=01/10/2025", 'Bruna Mamedes'!$N$2:$N$4000, "<=31/10/2025"), COUNTIFS('Camila Adão'!$E$2:$E$1997, "Indicação", 'Camila Adão'!$G$2:$G$1997, "Aguardando Pagamento", 'Camila Adão'!$N$2:$N$1997, ">=01/10/2025", 'Camila Adão'!$N$2:$N$1997, "<=31/10/2025"), COUNTIFS('Vendas Organicas'!$E$2:$E$3000, "Indicação", 'Vendas Organicas'!$G$2:$G$3000, "Aguardando Pagamento", 'Vendas Organicas'!$N$2:$N$3000, ">=01/10/2025", 'Vendas Organicas'!$N$2:$N$3000, "<=31/10/2025"), COUNTIFS('Diogo Lima'!$E$2:$E$1996, "Indicação", 'Diogo Lima'!$G$2:$G$1996, "Aguardando Pagamento", 'Diogo Lima'!$N$2:$N$1996, ">=01/10/2025", 'Diogo Lima'!$N$2:$N$1996, "<=31/10/2025"), COUNTIFS('Lucas Almeida'!$E$2:$E$4000, "Indicação", 'Lucas Almeida'!$G$2:$G$4000, "Aguardando Pagamento", 'Lucas Almeida'!$N$2:$N$4000, ">=01/10/2025", 'Lucas Almeida'!$N$2:$N$4000, "<=31/10/2025"), COUNTIFS('Fernando Diamantino'!$E$2:$E$1999, "Indicação", 'Fernando Diamantino'!$G$2:$G$1999, "Aguardando Pagamento", 'Fernando Diamantino'!$N$2:$N$1999, ">=01/10/2025", 'Fernando Diamantino'!$N$2:$N$1999, "<=31/10/2025"), COUNTIFS('Maiara Andrade'!$E$2:$E$4000, "Indicação", 'Maiara Andrade'!$G$2:$G$4000, "Aguardando Pagamento", 'Maiara Andrade'!$N$2:$N$4000, ">=01/10/2025", 'Maiara Andrade'!$N$2:$N$4000, "<=31/10/2025"), COUNTIFS('Roberto Ramos'!$E$2:$E$4000, "Indicação", 'Roberto Ramos'!$G$2:$G$4000, "Aguardando Pagamento", 'Roberto Ramos'!$N$2:$N$4000, ">=01/10/2025", 'Roberto Ramos'!$N$2:$N$4000, "<=31/10/2025"), COUNTIFS('Amanda Facundo'!$E$2:$E$1999, "Indicação", 'Amanda Facundo'!$G$2:$G$1999, "Aguardando Pagamento", 'Amanda Facundo'!$N$2:$N$1999, ">=01/10/2025", 'Amanda Facundo'!$N$2:$N$1999, "<=31/10/2025"), COUNTIFS('Rodrigo Oliveira'!$E$2:$E$4000, "Indicação", 'Rodrigo Oliveira'!$G$2:$G$4000, "Aguardando Pagamento", 'Rodrigo Oliveira'!$N$2:$N$4000, ">=01/10/2025", 'Rodrigo Oliveira'!$N$2:$N$4000, "<=31/10/2025"), COUNTIFS('Marcio Jorge'!$E$2:$E$4000, "Indicação", 'Marcio Jorge'!$G$2:$G$4000, "Aguardando Pagamento", 'Marcio Jorge'!$N$2:$N$4000, ">=01/10/2025", 'Marcio Jorge'!$N$2:$N$4000, "<=31/10/2025") ) -> 0 | AT35: =SUM( COUNTIFS('Bruna Mamedes'!$E$2:$E$4000, "Indicação", 'Bruna Mamedes'!$G$2:$G$4000, "Em conversação", 'Bruna Mamedes'!$N$2:$N$4000, ">=01/10/2025", 'Bruna Mamedes'!$N$2:$N$4000, "<=31/10/2025"), COUNTIFS('Camila Adão'!$E$2:$E$1997, "Indicação", 'Camila Adão'!$G$2:$G$1997, "Em conversação", 'Camila Adão'!$N$2:$N$1997, ">=01/10/2025", 'Camila Adão'!$N$2:$N$1997, "<=31/10/2025"), COUNTIFS('Vendas Organicas'!$E$2:$E$3000, "Indicação", 'Vendas Organicas'!$G$2:$G$3000, "Em conversação", 'Vendas Organicas'!$N$2:$N$3000, ">=01/10/2025", 'Vendas Organicas'!$N$2:$N$3000, "<=31/10/2025"), COUNTIFS('Diogo Lima'!$E$2:$E$1996, "Indicação", 'Diogo Lima'!$G$2:$G$1996, "Em conversação", 'Diogo Lima'!$N$2:$N$1996, ">=01/10/2025", 'Diogo Lima'!$N$2:$N$1996, "<=31/10/2025"), COUNTIFS('Lucas Almeida'!$E$2:$E$4000, "Indicação", 'Lucas Almeida'!$G$2:$G$4000, "Em conversação", 'Lucas Almeida'!$N$2:$N$4000, ">=01/10/2025", 'Lucas Almeida'!$N$2:$N$4000, "<=31/10/2025"), COUNTIFS('Fernando Diamantino'!$E$2:$E$1999, "Indicação", 'Fernando Diamantino'!$G$2:$G$1999, "Em conversação", 'Fernando Diamantino'!$N$2:$N$1999, ">=01/10/2025", 'Fernando Diamantino'!$N$2:$N$1999, "<=31/10/2025"), COUNTIFS('Maiara Andrade'!$E$2:$E$4000, "Indicação", 'Maiara Andrade'!$G$2:$G$4000, "Em conversação", 'Maiara Andrade'!$N$2:$N$4000, ">=01/10/2025", 'Maiara Andrade'!$N$2:$N$4000, "<=31/10/2025"), COUNTIFS('Roberto Ramos'!$E$2:$E$4000, "Indicação", 'Roberto Ramos'!$G$2:$G$4000, "Em conversação", 'Roberto Ramos'!$N$2:$N$4000, ">=01/10/2025", 'Roberto Ramos'!$N$2:$N$4000, "<=31/10/2025"), COUNTIFS('Amanda Facundo'!$E$2:$E$1999, "Indicação", 'Amanda Facundo'!$G$2:$G$1999, "Em conversação", 'Amanda Facundo'!$N$2:$N$1999, ">=01/10/2025", 'Amanda Facundo'!$N$2:$N$1999, "<=31/10/2025"), COUNTIFS('Rodrigo Oliveira'!$E$2:$E$4000, "Indicação", 'Rodrigo Oliveira'!$G$2:$G$4000, "Em conversação", 'Rodrigo Oliveira'!$N$2:$N$4000, ">=01/10/2025", 'Rodrigo Oliveira'!$N$2:$N$4000, "<=31/10/2025"), COUNTIFS('Marcio Jorge'!$E$2:$E$4000, "Indicação", 'Marcio Jorge'!$G$2:$G$4000, "Em conversação", 'Marcio Jorge'!$N$2:$N$4000, ">=01/10/2025", 'Marcio Jorge'!$N$2:$N$4000, "<=31/10/2025") ) -> 0 | AU35: =SUM( COUNTIFS('Bruna Mamedes'!$E$2:$E$4000, "Indicação", 'Bruna Mamedes'!$G$2:$G$4000, "Cotação Enviada", 'Bruna Mamedes'!$N$2:$N$4000, ">=01/10/2025", 'Bruna Mamedes'!$N$2:$N$4000, "<=31/10/2025"), COUNTIFS('Camila Adão'!$E$2:$E$1997, "Indicação", 'Camila Adão'!$G$2:$G$1997, "Cotação Enviada", 'Camila Adão'!$N$2:$N$1997, ">=01/10/2025", 'Camila Adão'!$N$2:$N$1997, "<=31/10/2025"), COUNTIFS('Vendas Organicas'!$E$2:$E$3000, "Indicação", 'Vendas Organicas'!$G$2:$G$3000, "Cotação Enviada", 'Vendas Organicas'!$N$2:$N$3000, ">=01/10/2025", 'Vendas Organicas'!$N$2:$N$3000, "<=31/10/2025"), COUNTIFS('Diogo Lima'!$E$2:$E$1996, "Indicação", 'Diogo Lima'!$G$2:$G$1996, "Cotação Enviada", 'Diogo Lima'!$N$2:$N$1996, ">=01/10/2025", 'Diogo Lima'!$N$2:$N$1996, "<=31/10/2025"), COUNTIFS('Lucas Almeida'!$E$2:$E$4000, "Indicação", 'Lucas Almeida'!$G$2:$G$4000, "Cotação Enviada", 'Lucas Almeida'!$N$2:$N$4000, ">=01/10/2025", 'Lucas Almeida'!$N$2:$N$4000, "<=31/10/2025"), COUNTIFS('Fernando Diamantino'!$E$2:$E$1999, "Indicação", 'Fernando Diamantino'!$G$2:$G$1999, "Cotação Enviada", 'Fernando Diamantino'!$N$2:$N$1999, ">=01/10/2025", 'Fernando Diamantino'!$N$2:$N$1999, "<=31/10/2025"), COUNTIFS('Maiara Andrade'!$E$2:$E$4000, "Indicação", 'Maiara Andrade'!$G$2:$G$4000, "Cotação Enviada", 'Maiara Andrade'!$N$2:$N$4000, ">=01/10/2025", 'Maiara Andrade'!$N$2:$N$4000, "<=31/10/2025"), COUNTIFS('Roberto Ramos'!$E$2:$E$4000, "Indicação", 'Roberto Ramos'!$G$2:$G$4000, "Cotação Enviada", 'Roberto Ramos'!$N$2:$N$4000, ">=01/10/2025", 'Roberto Ramos'!$N$2:$N$4000, "<=31/10/2025"), COUNTIFS('Amanda Facundo'!$E$2:$E$1999, "Indicação", 'Amanda Facundo'!$G$2:$G$1999, "Cotação Enviada", 'Amanda Facundo'!$N$2:$N$1999, ">=01/10/2025", 'Amanda Facundo'!$N$2:$N$1999, "<=31/10/2025"), COUNTIFS('Rodrigo Oliveira'!$E$2:$E$4000, "Indicação", 'Rodrigo Oliveira'!$G$2:$G$4000, "Cotação Enviada", 'Rodrigo Oliveira'!$N$2:$N$4000, ">=01/10/2025", 'Rodrigo Oliveira'!$N$2:$N$4000, "<=31/10/2025"), COUNTIFS('Marcio Jorge'!$E$2:$E$4000, "Indicação", 'Marcio Jorge'!$G$2:$G$4000, "Cotação Enviada", 'Marcio Jorge'!$N$2:$N$4000, ">=01/10/2025", 'Marcio Jorge'!$N$2:$N$4000, "<=31/10/2025") ) -> 0 | AV35: =SUM( COUNTIFS('Bruna Mamedes'!$E$2:$E$4000, "Indicação", 'Bruna Mamedes'!$G$2:$G$4000, "Desistência", 'Bruna Mamedes'!$N$2:$N$4000, ">=01/10/2025", 'Bruna Mamedes'!$N$2:$N$4000, "<=31/10/2025"), COUNTIFS('Camila Adão'!$E$2:$E$1997, "Indicação", 'Camila Adão'!$G$2:$G$1997, "Desistência", 'Camila Adão'!$N$2:$N$1997, ">=01/10/2025", 'Camila Adão'!$N$2:$N$1997, "<=31/10/2025"), COUNTIFS('Vendas Organicas'!$E$2:$E$3000, "Indicação", 'Vendas Organicas'!$G$2:$G$3000, "Desistência", 'Vendas Organicas'!$N$2:$N$3000, ">=01/10/2025", 'Vendas Organicas'!$N$2:$N$3000, "<=31/10/2025"), COUNTIFS('Diogo Lima'!$E$2:$E$1996, "Indicação", 'Diogo Lima'!$G$2:$G$1996, "Desistência", 'Diogo Lima'!$N$2:$N$1996, ">=01/10/2025", 'Diogo Lima'!$N$2:$N$1996, "<=31/10/2025"), COUNTIFS('Lucas Almeida'!$E$2:$E$4000, "Indicação", 'Lucas Almeida'!$G$2:$G$4000, "Desistência", 'Lucas Almeida'!$N$2:$N$4000, ">=01/10/2025", 'Lucas Almeida'!$N$2:$N$4000, "<=31/10/2025"), COUNTIFS('Fernando Diamantino'!$E$2:$E$1999, "Indicação", 'Fernando Diamantino'!$G$2:$G$1999, "Desistência", 'Fernando Diamantino'!$N$2:$N$1999, ">=01/10/2025", 'Fernando Diamantino'!$N$2:$N$1999, "<=31/10/2025"), COUNTIFS('Maiara Andrade'!$E$2:$E$4000, "Indicação", 'Maiara Andrade'!$G$2:$G$4000, "Desistência", 'Maiara Andrade'!$N$2:$N$4000, ">=01/10/2025", 'Maiara Andrade'!$N$2:$N$4000, "<=31/10/2025"), COUNTIFS('Roberto Ramos'!$E$2:$E$4000, "Indicação", 'Roberto Ramos'!$G$2:$G$4000, "Desistência", 'Roberto Ramos'!$N$2:$N$4000, ">=01/10/2025", 'Roberto Ramos'!$N$2:$N$4000, "<=31/10/2025"), COUNTIFS('Amanda Facundo'!$E$2:$E$1999, "Indicação", 'Amanda Facundo'!$G$2:$G$1999, "Desistência", 'Amanda Facundo'!$N$2:$N$1999, ">=01/10/2025", 'Amanda Facundo'!$N$2:$N$1999, "<=31/10/2025"), COUNTIFS('Rodrigo Oliveira'!$E$2:$E$4000, "Indicação", 'Rodrigo Oliveira'!$G$2:$G$4000, "Desistência", 'Rodrigo Oliveira'!$N$2:$N$4000, ">=01/10/2025", 'Rodrigo Oliveira'!$N$2:$N$4000, "<=31/10/2025"), COUNTIFS('Marcio Jorge'!$E$2:$E$4000, "Indicação", 'Marcio Jorge'!$G$2:$G$4000, "Desistência", 'Marcio Jorge'!$N$2:$N$4000, ">=01/10/2025", 'Marcio Jorge'!$N$2:$N$4000, "<=31/10/2025") ) -> 0 | AW35: =SUM( COUNTIFS('Bruna Mamedes'!$E$2:$E$4000, "Indicação", 'Bruna Mamedes'!$G$2:$G$4000, "Não Respondeu", 'Bruna Mamedes'!$N$2:$N$4000, ">=01/10/2025", 'Bruna Mamedes'!$N$2:$N$4000, "<=31/10/2025"), COUNTIFS('Camila Adão'!$E$2:$E$1997, "Indicação", 'Camila Adão'!$G$2:$G$1997, "Não Respondeu", 'Camila Adão'!$N$2:$N$1997, ">=01/10/2025", 'Camila Adão'!$N$2:$N$1997, "<=31/10/2025"), COUNTIFS('Vendas Organicas'!$E$2:$E$3000, "Indicação", 'Vendas Organicas'!$G$2:$G$3000, "Não Respondeu", 'Vendas Organicas'!$N$2:$N$3000, ">=01/10/2025", 'Vendas Organicas'!$N$2:$N$3000, "<=31/10/2025"), COUNTIFS('Diogo Lima'!$E$2:$E$1996, "Indicação", 'Diogo Lima'!$G$2:$G$1996, "Não Respondeu", 'Diogo Lima'!$N$2:$N$1996, ">=01/10/2025", 'Diogo Lima'!$N$2:$N$1996, "<=31/10/2025"), COUNTIFS('Lucas Almeida'!$E$2:$E$4000, "Indicação", 'Lucas Almeida'!$G$2:$G$4000, "Não Respondeu", 'Lucas Almeida'!$N$2:$N$4000, ">=01/10/2025", 'Lucas Almeida'!$N$2:$N$4000, "<=31/10/2025"), COUNTIFS('Fernando Diamantino'!$E$2:$E$1999, "Indicação", 'Fernando Diamantino'!$G$2:$G$1999, "Não Respondeu", 'Fernando Diamantino'!$N$2:$N$1999, ">=01/10/2025", 'Fernando Diamantino'!$N$2:$N$1999, "<=31/10/2025"), COUNTIFS('Maiara Andrade'!$E$2:$E$4000, "Indicação", 'Maiara Andrade'!$G$2:$G$4000, "Não Respondeu", 'Maiara Andrade'!$N$2:$N$4000, ">=01/10/2025", 'Maiara Andrade'!$N$2:$N$4000, "<=31/10/2025"), COUNTIFS('Roberto Ramos'!$E$2:$E$4000, "Indicação", 'Roberto Ramos'!$G$2:$G$4000, "Não Respondeu", 'Roberto Ramos'!$N$2:$N$4000, ">=01/10/2025", 'Roberto Ramos'!$N$2:$N$4000, "<=31/10/2025"), COUNTIFS('Amanda Facundo'!$E$2:$E$1999, "Indicação", 'Amanda Facundo'!$G$2:$G$1999, "Não Respondeu", 'Amanda Facundo'!$N$2:$N$1999, ">=01/10/2025", 'Amanda Facundo'!$N$2:$N$1999, "<=31/10/2025"), COUNTIFS('Rodrigo Oliveira'!$E$2:$E$4000, "Indicação", 'Rodrigo Oliveira'!$G$2:$G$4000, "Não Respondeu", 'Rodrigo Oliveira'!$N$2:$N$4000, ">=01/10/2025", 'Rodrigo Oliveira'!$N$2:$N$4000, "<=31/10/2025"), COUNTIFS('Marcio Jorge'!$E$2:$E$4000, "Indicação", 'Marcio Jorge'!$G$2:$G$4000, "Não Respondeu", 'Marcio Jorge'!$N$2:$N$4000, ">=01/10/2025", 'Marcio Jorge'!$N$2:$N$4000, "<=31/10/2025") ) -> 0 | AX35: =SUM( SUMIFS('Bruna Mamedes'!$H$2:$H$4000, 'Bruna Mamedes'!$E$2:$E$4000, "Indicação", 'Bruna Mamedes'!$G$2:$G$4000, "Plano Fechado", 'Bruna Mamedes'!$N$2:$N$4000, ">=01/10/2025", 'Bruna Mamedes'!$N$2:$N$4000, "<=31/10/2025"), SUMIFS('Camila Adão'!$H$2:$H$1997, 'Camila Adão'!$E$2:$E$1997, "Indicação", 'Camila Adão'!$G$2:$G$1997, "Plano Fechado", 'Camila Adão'!$N$2:$N$1997, ">=01/10/2025", 'Camila Adão'!$N$2:$N$1997, "<=31/10/2025"), SUMIFS('Vendas Organicas'!$H$2:$H$3000, 'Vendas Organicas'!$E$2:$E$3000, "Indicação", 'Vendas Organicas'!$G$2:$G$3000, "Plano Fechado", 'Vendas Organicas'!$N$2:$N$3000, ">=01/10/2025", 'Vendas Organicas'!$N$2:$N$3000, "<=31/10/2025"), SUMIFS('Diogo Lima'!$H$2:$H$1996, 'Diogo Lima'!$E$2:$E$1996, "Indicação", 'Diogo Lima'!$G$2:$G$1996, "Plano Fechado", 'Diogo Lima'!$N$2:$N$1996, ">=01/10/2025", 'Diogo Lima'!$N$2:$N$1996, "<=31/10/2025"), SUMIFS('Lucas Almeida'!$H$2:$H$4000, 'Lucas Almeida'!$E$2:$E$4000, "Indicação", 'Lucas Almeida'!$G$2:$G$4000, "Plano Fechado", 'Lucas Almeida'!$N$2:$N$4000, ">=01/10/2025", 'Lucas Almeida'!$N$2:$N$4000, "<=31/10/2025"), SUMIFS('Fernando Diamantino'!$H$2:$H$1999, 'Fernando Diamantino'!$E$2:$E$1999, "Indicação", 'Fernando Diamantino'!$G$2:$G$1999, "Plano Fechado", 'Fernando Diamantino'!$N$2:$N$1999, ">=01/10/2025", 'Fernando Diamantino'!$N$2:$N$1999, "<=31/10/2025"), SUMIFS('Maiara Andrade'!$H$2:$H$4000, 'Maiara Andrade'!$E$2:$E$4000, "Indicação", 'Maiara Andrade'!$G$2:$G$4000, "Plano Fechado", 'Maiara Andrade'!$N$2:$N$4000, ">=01/10/2025", 'Maiara Andrade'!$N$2:$N$4000, "<=31/10/2025"), SUMIFS('Roberto Ramos'!$H$2:$H$4000, 'Roberto Ramos'!$E$2:$E$4000, "Indicação", 'Roberto Ramos'!$G$2:$G$4000, "Plano Fechado", 'Roberto Ramos'!$N$2:$N$4000, ">=01/10/2025", 'Roberto Ramos'!$N$2:$N$4000, "<=31/10/2025"), SUMIFS('Amanda Facundo'!$H$2:$H$1999, 'Amanda Facundo'!$E$2:$E$1999, "Indicação", 'Amanda Facundo'!$G$2:$G$1999, "Plano Fechado", 'Amanda Facundo'!$N$2:$N$1999, ">=01/10/2025", 'Amanda Facundo'!$N$2:$N$1999, "<=31/10/2025"), SUMIFS('Rodrigo Oliveira'!$H$2:$H$4000, 'Rodrigo Oliveira'!$E$2:$E$4000, "Indicação", 'Rodrigo Oliveira'!$G$2:$G$4000, "Plano Fechado", 'Rodrigo Oliveira'!$N$2:$N$4000, ">=01/10/2025", 'Rodrigo Oliveira'!$N$2:$N$4000, "<=31/10/2025"), SUMIFS('Marcio Jorge'!$H$2:$H$4000, 'Marcio Jorge'!$E$2:$E$4000, "Indicação", 'Marcio Jorge'!$G$2:$G$4000, "Plano Fechado", 'Marcio Jorge'!$N$2:$N$4000, ">=01/10/2025", 'Marcio Jorge'!$N$2:$N$4000, "<=31/10/2025") ) -> 20233.88
C36: 0.667 | D36: 0 | E36: 0.167 | F36: 0.167 | G36: 0 | K36: 0.919 | L36: 0.054 | M36: 0 | N36: 0 | O36: 0.027 | S36: 0.643 | T36: 0.024 | U36: 0.143 | V36: 0.071 | W36: 0.143 | AA36: 0.862 | AB36: 0.034 | AC36: 0.103 | AD36: 0.069 | AE36: 0.034 | AI36: 0.897 | AJ36: 0.034 | AK36: 0.034 | AL36: 0.069 | AM36: 0 | AQ36: =(AQ35/AP35) -> 0.57142857 | AR36: =(AR35/AP35) -> 0.19047619 | AS36: =(AS35/AP35) -> 0 | AT36: =(AT35/AP35) -> 0 | AU36: =AU35/AP35 -> 0 | AV36: =AV35/AP35 -> 0 | AW36: =AW35/AP35 -> 0
R37: LEADS PROSPECÇÃO INDIVIDUAL | Z37: LEADS PROSPECÇÃO INDIVIDUAL | AH37: LEADS PROSPECÇÃO INDIVIDUAL | AP37: LEADS PROSPECÇÃO INDIVIDUAL
R38: QTD. Leads | S38: Vendas Fechadas | T38: Leads em Conversação | U38: Leads com Proposta Enviada | V38: Leads Desistentes | W38: Leads sem Resposta | X38: Faturamento | Z38: QTD. Leads | AA38: Vendas Fechadas | AB38: Leads em Conversação | AC38: Leads com Proposta Enviada | AD38: Leads Desistentes | AE38: Leads sem Resposta | AF38: Faturamento | AH38: QTD. Leads | AI38: Vendas Fechadas | AJ38: Leads em Conversação | AK38: Leads com Proposta Enviada | AL38: Leads Desistentes | AM38: Leads sem Resposta | AN38: Faturamento | AP38: QTD. Leads | AQ38: Plano Fechado | AR38: Em Análise | AS38: Aguardando Pagamento | AT38: Conversação | AU38: Proposta Enviada | AV38: Desistentes | AW38: Sem Resposta | AX38: Faturamento
R39: 11 | S39: 8 | T39: 2 | U39: 1 | V39: 0 | W39: 0 | X39: 12049.78 | Z39: 8 | AA39: 5 | AB39: 0 | AC39: 1 | AD39: 2 | AE39: 0 | AF39: 2596.38 | AH39: 13 | AI39: 9 | AJ39: 1 | AK39: 1 | AL39: 1 | AM39: 0 | AN39: 5785.8 | AP39: {=LET( abas, {"Amanda Facundo";"Bruna Mamedes";"Camila Adão";"Darlin Amorim";"Diogo Lima";"Externos";"Maiara Andrade";"Marcio Jorge";"Lucas Almeida";"Roberto Ramos";"Rodrigo Oliviera";"Leandro Nascimento";"Leandro Drumond";"Marcelle Marcela";"Anteriores";"Corretor 1";"Corretor 2";"Corretor 3";"Corretor 4";"Corretor 5"}, SUM( BYROW( abas, LAMBDA(a, COUNTIFS( INDIRECT("'"&a&"'!E:E"), "Prospecção Individual", INDIRECT("'"&a&"'!N:N"), ">="&DATE(2025,10,1), INDIRECT("'"&a&"'!N:N"), "<="&DATE(2025,10,31) ) ) ) ) )} -> 18 | AQ39: =SUM( COUNTIFS('Bruna Mamedes'!$E$2:$E$4000, "Prospecção Individual", 'Bruna Mamedes'!$G$2:$G$4000, "Plano Fechado", 'Bruna Mamedes'!$N$2:$N$4000, ">=01/10/2025", 'Bruna Mamedes'!$N$2:$N$4000, "<=31/10/2025"), COUNTIFS('Camila Adão'!$E$2:$E$1997, "Prospecção Individual", 'Camila Adão'!$G$2:$G$1997, "Plano Fechado", 'Camila Adão'!$N$2:$N$1997, ">=01/10/2025", 'Camila Adão'!$N$2:$N$1997, "<=31/10/2025"), COUNTIFS('Vendas Organicas'!$E$2:$E$3000, "Prospecção Individual", 'Vendas Organicas'!$G$2:$G$3000, "Plano Fechado", 'Vendas Organicas'!$N$2:$N$3000, ">=01/10/2025", 'Vendas Organicas'!$N$2:$N$3000, "<=31/10/2025"), COUNTIFS('Diogo Lima'!$E$2:$E$1996, "Prospecção Individual", 'Diogo Lima'!$G$2:$G$1996, "Plano Fechado", 'Diogo Lima'!$N$2:$N$1996, ">=01/10/2025", 'Diogo Lima'!$N$2:$N$1996, "<=31/10/2025"), COUNTIFS('Lucas Almeida'!$E$2:$E$4000, "Prospecção Individual", 'Lucas Almeida'!$G$2:$G$4000, "Plano Fechado", 'Lucas Almeida'!$N$2:$N$4000, ">=01/10/2025", 'Lucas Almeida'!$N$2:$N$4000, "<=31/10/2025"), COUNTIFS('Fernando Diamantino'!$E$2:$E$1999, "Prospecção Individual", 'Fernando Diamantino'!$G$2:$G$1999, "Plano Fechado", 'Fernando Diamantino'!$N$2:$N$1999, ">=01/10/2025", 'Fernando Diamantino'!$N$2:$N$1999, "<=31/10/2025"), COUNTIFS('Maiara Andrade'!$E$2:$E$4000, "Prospecção Individual", 'Maiara Andrade'!$G$2:$G$4000, "Plano Fechado", 'Maiara Andrade'!$N$2:$N$4000, ">=01/10/2025", 'Maiara Andrade'!$N$2:$N$4000, "<=31/10/2025"), COUNTIFS('Roberto Ramos'!$E$2:$E$4000, "Prospecção Individual", 'Roberto Ramos'!$G$2:$G$4000, "Plano Fechado", 'Roberto Ramos'!$N$2:$N$4000, ">=01/10/2025", 'Roberto Ramos'!$N$2:$N$4000, "<=31/10/2025"), COUNTIFS('Amanda Facundo'!$E$2:$E$1999, "Prospecção Individual", 'Amanda Facundo'!$G$2:$G$1999, "Plano Fechado", 'Amanda Facundo'!$N$2:$N$1999, ">=01/10/2025", 'Amanda Facundo'!$N$2:$N$1999, "<=31/10/2025"), COUNTIFS('Rodrigo Oliveira'!$E$2:$E$4000, "Prospecção Individual", 'Rodrigo Oliveira'!$G$2:$G$4000, "Plano Fechado", 'Rodrigo Oliveira'!$N$2:$N$4000, ">=01/10/2025", 'Rodrigo Oliveira'!$N$2:$N$4000, "<=31/10/2025"), COUNTIFS('Marcio Jorge'!$E$2:$E$4000, "Prospecção Individual", 'Marcio Jorge'!$G$2:$G$4000, "Plano Fechado", 'Marcio Jorge'!$N$2:$N$4000, ">=01/10/2025", 'Marcio Jorge'!$N$2:$N$4000, "<=31/10/2025") ) -> 7 | AR39: =SUM( COUNTIFS('Bruna Mamedes'!$E$2:$E$4000, "Prospecção Individual", 'Bruna Mamedes'!$G$2:$G$4000, "Em Análise", 'Bruna Mamedes'!$N$2:$N$4000, ">=01/10/2025", 'Bruna Mamedes'!$N$2:$N$4000, "<=31/10/2025"), COUNTIFS('Camila Adão'!$E$2:$E$1997, "Prospecção Individual", 'Camila Adão'!$G$2:$G$1997, "Em Análise", 'Camila Adão'!$N$2:$N$1997, ">=01/10/2025", 'Camila Adão'!$N$2:$N$1997, "<=31/10/2025"), COUNTIFS('Vendas Organicas'!$E$2:$E$3000, "Prospecção Individual", 'Vendas Organicas'!$G$2:$G$3000, "Em Análise", 'Vendas Organicas'!$N$2:$N$3000, ">=01/10/2025", 'Vendas Organicas'!$N$2:$N$3000, "<=31/10/2025"), COUNTIFS('Diogo Lima'!$E$2:$E$1996, "Prospecção Individual", 'Diogo Lima'!$G$2:$G$1996, "Em Análise", 'Diogo Lima'!$N$2:$N$1996, ">=01/10/2025", 'Diogo Lima'!$N$2:$N$1996, "<=31/10/2025"), COUNTIFS('Lucas Almeida'!$E$2:$E$4000, "Prospecção Individual", 'Lucas Almeida'!$G$2:$G$4000, "Em Análise", 'Lucas Almeida'!$N$2:$N$4000, ">=01/10/2025", 'Lucas Almeida'!$N$2:$N$4000, "<=31/10/2025"), COUNTIFS('Fernando Diamantino'!$E$2:$E$1999, "Prospecção Individual", 'Fernando Diamantino'!$G$2:$G$1999, "Em Análise", 'Fernando Diamantino'!$N$2:$N$1999, ">=01/10/2025", 'Fernando Diamantino'!$N$2:$N$1999, "<=31/10/2025"), COUNTIFS('Maiara Andrade'!$E$2:$E$4000, "Prospecção Individual", 'Maiara Andrade'!$G$2:$G$4000, "Em Análise", 'Maiara Andrade'!$N$2:$N$4000, ">=01/10/2025", 'Maiara Andrade'!$N$2:$N$4000, "<=31/10/2025"), COUNTIFS('Roberto Ramos'!$E$2:$E$4000, "Prospecção Individual", 'Roberto Ramos'!$G$2:$G$4000, "Em Análise", 'Roberto Ramos'!$N$2:$N$4000, ">=01/10/2025", 'Roberto Ramos'!$N$2:$N$4000, "<=31/10/2025"), COUNTIFS('Amanda Facundo'!$E$2:$E$1999, "Prospecção Individual", 'Amanda Facundo'!$G$2:$G$1999, "Em Análise", 'Amanda Facundo'!$N$2:$N$1999, ">=01/10/2025", 'Amanda Facundo'!$N$2:$N$1999, "<=31/10/2025"), COUNTIFS('Rodrigo Oliveira'!$E$2:$E$4000, "Prospecção Individual", 'Rodrigo Oliveira'!$G$2:$G$4000, "Em Análise", 'Rodrigo Oliveira'!$N$2:$N$4000, ">=01/10/2025", 'Rodrigo Oliveira'!$N$2:$N$4000, "<=31/10/2025"), COUNTIFS('Marcio Jorge'!$E$2:$E$4000, "Prospecção Individual", 'Marcio Jorge'!$G$2:$G$4000, "Em Análise", 'Marcio Jorge'!$N$2:$N$4000, ">=01/10/2025", 'Marcio Jorge'!$N$2:$N$4000, "<=31/10/2025") ) -> 2 | AS39: =SUM( COUNTIFS('Bruna Mamedes'!$E$2:$E$4000, "Prospecção Individual", 'Bruna Mamedes'!$G$2:$G$4000, "Aguardando Pagamento", 'Bruna Mamedes'!$N$2:$N$4000, ">=01/10/2025", 'Bruna Mamedes'!$N$2:$N$4000, "<=31/10/2025"), COUNTIFS('Camila Adão'!$E$2:$E$1997, "Prospecção Individual", 'Camila Adão'!$G$2:$G$1997, "Aguardando Pagamento", 'Camila Adão'!$N$2:$N$1997, ">=01/10/2025", 'Camila Adão'!$N$2:$N$1997, "<=31/10/2025"), COUNTIFS('Vendas Organicas'!$E$2:$E$3000, "Prospecção Individual", 'Vendas Organicas'!$G$2:$G$3000, "Aguardando Pagamento", 'Vendas Organicas'!$N$2:$N$3000, ">=01/10/2025", 'Vendas Organicas'!$N$2:$N$3000, "<=31/10/2025"), COUNTIFS('Diogo Lima'!$E$2:$E$1996, "Prospecção Individual", 'Diogo Lima'!$G$2:$G$1996, "Aguardando Pagamento", 'Diogo Lima'!$N$2:$N$1996, ">=01/10/2025", 'Diogo Lima'!$N$2:$N$1996, "<=31/10/2025"), COUNTIFS('Lucas Almeida'!$E$2:$E$4000, "Prospecção Individual", 'Lucas Almeida'!$G$2:$G$4000, "Aguardando Pagamento", 'Lucas Almeida'!$N$2:$N$4000, ">=01/10/2025", 'Lucas Almeida'!$N$2:$N$4000, "<=31/10/2025"), COUNTIFS('Fernando Diamantino'!$E$2:$E$1999, "Prospecção Individual", 'Fernando Diamantino'!$G$2:$G$1999, "Aguardando Pagamento", 'Fernando Diamantino'!$N$2:$N$1999, ">=01/10/2025", 'Fernando Diamantino'!$N$2:$N$1999, "<=31/10/2025"), COUNTIFS('Maiara Andrade'!$E$2:$E$4000, "Prospecção Individual", 'Maiara Andrade'!$G$2:$G$4000, "Aguardando Pagamento", 'Maiara Andrade'!$N$2:$N$4000, ">=01/10/2025", 'Maiara Andrade'!$N$2:$N$4000, "<=31/10/2025"), COUNTIFS('Roberto Ramos'!$E$2:$E$4000, "Prospecção Individual", 'Roberto Ramos'!$G$2:$G$4000, "Aguardando Pagamento", 'Roberto Ramos'!$N$2:$N$4000, ">=01/10/2025", 'Roberto Ramos'!$N$2:$N$4000, "<=31/10/2025"), COUNTIFS('Amanda Facundo'!$E$2:$E$1999, "Prospecção Individual", 'Amanda Facundo'!$G$2:$G$1999, "Aguardando Pagamento", 'Amanda Facundo'!$N$2:$N$1999, ">=01/10/2025", 'Amanda Facundo'!$N$2:$N$1999, "<=31/10/2025"), COUNTIFS('Rodrigo Oliveira'!$E$2:$E$4000, "Prospecção Individual", 'Rodrigo Oliveira'!$G$2:$G$4000, "Aguardando Pagamento", 'Rodrigo Oliveira'!$N$2:$N$4000, ">=01/10/2025", 'Rodrigo Oliveira'!$N$2:$N$4000, "<=31/10/2025"), COUNTIFS('Marcio Jorge'!$E$2:$E$4000, "Prospecção Individual", 'Marcio Jorge'!$G$2:$G$4000, "Aguardando Pagamento", 'Marcio Jorge'!$N$2:$N$4000, ">=01/10/2025", 'Marcio Jorge'!$N$2:$N$4000, "<=31/10/2025") ) -> 1 | AT39: =SUM( COUNTIFS('Bruna Mamedes'!$E$2:$E$4000, "Prospecção Individual", 'Bruna Mamedes'!$G$2:$G$4000, "Em conversação", 'Bruna Mamedes'!$N$2:$N$4000, ">=01/10/2025", 'Bruna Mamedes'!$N$2:$N$4000, "<=31/10/2025"), COUNTIFS('Camila Adão'!$E$2:$E$1997, "Prospecção Individual", 'Camila Adão'!$G$2:$G$1997, "Em conversação", 'Camila Adão'!$N$2:$N$1997, ">=01/10/2025", 'Camila Adão'!$N$2:$N$1997, "<=31/10/2025"), COUNTIFS('Vendas Organicas'!$E$2:$E$3000, "Prospecção Individual", 'Vendas Organicas'!$G$2:$G$3000, "Em conversação", 'Vendas Organicas'!$N$2:$N$3000, ">=01/10/2025", 'Vendas Organicas'!$N$2:$N$3000, "<=31/10/2025"), COUNTIFS('Diogo Lima'!$E$2:$E$1996, "Prospecção Individual", 'Diogo Lima'!$G$2:$G$1996, "Em conversação", 'Diogo Lima'!$N$2:$N$1996, ">=01/10/2025", 'Diogo Lima'!$N$2:$N$1996, "<=31/10/2025"), COUNTIFS('Lucas Almeida'!$E$2:$E$4000, "Prospecção Individual", 'Lucas Almeida'!$G$2:$G$4000, "Em conversação", 'Lucas Almeida'!$N$2:$N$4000, ">=01/10/2025", 'Lucas Almeida'!$N$2:$N$4000, "<=31/10/2025"), COUNTIFS('Fernando Diamantino'!$E$2:$E$1999, "Prospecção Individual", 'Fernando Diamantino'!$G$2:$G$1999, "Em conversação", 'Fernando Diamantino'!$N$2:$N$1999, ">=01/10/2025", 'Fernando Diamantino'!$N$2:$N$1999, "<=31/10/2025"), COUNTIFS('Maiara Andrade'!$E$2:$E$4000, "Prospecção Individual", 'Maiara Andrade'!$G$2:$G$4000, "Em conversação", 'Maiara Andrade'!$N$2:$N$4000, ">=01/10/2025", 'Maiara Andrade'!$N$2:$N$4000, "<=31/10/2025"), COUNTIFS('Roberto Ramos'!$E$2:$E$4000, "Prospecção Individual", 'Roberto Ramos'!$G$2:$G$4000, "Em conversação", 'Roberto Ramos'!$N$2:$N$4000, ">=01/10/2025", 'Roberto Ramos'!$N$2:$N$4000, "<=31/10/2025"), COUNTIFS('Amanda Facundo'!$E$2:$E$1999, "Prospecção Individual", 'Amanda Facundo'!$G$2:$G$1999, "Em conversação", 'Amanda Facundo'!$N$2:$N$1999, ">=01/10/2025", 'Amanda Facundo'!$N$2:$N$1999, "<=31/10/2025"), COUNTIFS('Rodrigo Oliveira'!$E$2:$E$4000, "Prospecção Individual", 'Rodrigo Oliveira'!$G$2:$G$4000, "Em conversação", 'Rodrigo Oliveira'!$N$2:$N$4000, ">=01/10/2025", 'Rodrigo Oliveira'!$N$2:$N$4000, "<=31/10/2025"), COUNTIFS('Marcio Jorge'!$E$2:$E$4000, "Prospecção Individual", 'Marcio Jorge'!$G$2:$G$4000, "Em conversação", 'Marcio Jorge'!$N$2:$N$4000, ">=01/10/2025", 'Marcio Jorge'!$N$2:$N$4000, "<=31/10/2025") ) -> 0 | AU39: =SUM( COUNTIFS('Bruna Mamedes'!$E$2:$E$4000, "Prospecção Individual", 'Bruna Mamedes'!$G$2:$G$4000, "Cotação Enviada", 'Bruna Mamedes'!$N$2:$N$4000, ">=01/10/2025", 'Bruna Mamedes'!$N$2:$N$4000, "<=31/10/2025"), COUNTIFS('Camila Adão'!$E$2:$E$1997, "Prospecção Individual", 'Camila Adão'!$G$2:$G$1997, "Cotação Enviada", 'Camila Adão'!$N$2:$N$1997, ">=01/10/2025", 'Camila Adão'!$N$2:$N$1997, "<=31/10/2025"), COUNTIFS('Vendas Organicas'!$E$2:$E$3000, "Prospecção Individual", 'Vendas Organicas'!$G$2:$G$3000, "Cotação Enviada", 'Vendas Organicas'!$N$2:$N$3000, ">=01/10/2025", 'Vendas Organicas'!$N$2:$N$3000, "<=31/10/2025"), COUNTIFS('Diogo Lima'!$E$2:$E$1996, "Prospecção Individual", 'Diogo Lima'!$G$2:$G$1996, "Cotação Enviada", 'Diogo Lima'!$N$2:$N$1996, ">=01/10/2025", 'Diogo Lima'!$N$2:$N$1996, "<=31/10/2025"), COUNTIFS('Lucas Almeida'!$E$2:$E$4000, "Prospecção Individual", 'Lucas Almeida'!$G$2:$G$4000, "Cotação Enviada", 'Lucas Almeida'!$N$2:$N$4000, ">=01/10/2025", 'Lucas Almeida'!$N$2:$N$4000, "<=31/10/2025"), COUNTIFS('Fernando Diamantino'!$E$2:$E$1999, "Prospecção Individual", 'Fernando Diamantino'!$G$2:$G$1999, "Cotação Enviada", 'Fernando Diamantino'!$N$2:$N$1999, ">=01/10/2025", 'Fernando Diamantino'!$N$2:$N$1999, "<=31/10/2025"), COUNTIFS('Maiara Andrade'!$E$2:$E$4000, "Prospecção Individual", 'Maiara Andrade'!$G$2:$G$4000, "Cotação Enviada", 'Maiara Andrade'!$N$2:$N$4000, ">=01/10/2025", 'Maiara Andrade'!$N$2:$N$4000, "<=31/10/2025"), COUNTIFS('Roberto Ramos'!$E$2:$E$4000, "Prospecção Individual", 'Roberto Ramos'!$G$2:$G$4000, "Cotação Enviada", 'Roberto Ramos'!$N$2:$N$4000, ">=01/10/2025", 'Roberto Ramos'!$N$2:$N$4000, "<=31/10/2025"), COUNTIFS('Amanda Facundo'!$E$2:$E$1999, "Prospecção Individual", 'Amanda Facundo'!$G$2:$G$1999, "Cotação Enviada", 'Amanda Facundo'!$N$2:$N$1999, ">=01/10/2025", 'Amanda Facundo'!$N$2:$N$1999, "<=31/10/2025"), COUNTIFS('Rodrigo Oliveira'!$E$2:$E$4000, "Prospecção Individual", 'Rodrigo Oliveira'!$G$2:$G$4000, "Cotação Enviada", 'Rodrigo Oliveira'!$N$2:$N$4000, ">=01/10/2025", 'Rodrigo Oliveira'!$N$2:$N$4000, "<=31/10/2025"), COUNTIFS('Marcio Jorge'!$E$2:$E$4000, "Prospecção Individual", 'Marcio Jorge'!$G$2:$G$4000, "Cotação Enviada", 'Marcio Jorge'!$N$2:$N$4000, ">=01/10/2025", 'Marcio Jorge'!$N$2:$N$4000, "<=31/10/2025") ) -> 0 | AV39: =SUM( COUNTIFS('Bruna Mamedes'!$E$2:$E$4000, "Prospecção Individual", 'Bruna Mamedes'!$G$2:$G$4000, "Desistência", 'Bruna Mamedes'!$N$2:$N$4000, ">=01/10/2025", 'Bruna Mamedes'!$N$2:$N$4000, "<=31/10/2025"), COUNTIFS('Camila Adão'!$E$2:$E$1997, "Prospecção Individual", 'Camila Adão'!$G$2:$G$1997, "Desistência", 'Camila Adão'!$N$2:$N$1997, ">=01/10/2025", 'Camila Adão'!$N$2:$N$1997, "<=31/10/2025"), COUNTIFS('Vendas Organicas'!$E$2:$E$3000, "Prospecção Individual", 'Vendas Organicas'!$G$2:$G$3000, "Desistência", 'Vendas Organicas'!$N$2:$N$3000, ">=01/10/2025", 'Vendas Organicas'!$N$2:$N$3000, "<=31/10/2025"), COUNTIFS('Diogo Lima'!$E$2:$E$1996, "Prospecção Individual", 'Diogo Lima'!$G$2:$G$1996, "Desistência", 'Diogo Lima'!$N$2:$N$1996, ">=01/10/2025", 'Diogo Lima'!$N$2:$N$1996, "<=31/10/2025"), COUNTIFS('Lucas Almeida'!$E$2:$E$4000, "Prospecção Individual", 'Lucas Almeida'!$G$2:$G$4000, "Desistência", 'Lucas Almeida'!$N$2:$N$4000, ">=01/10/2025", 'Lucas Almeida'!$N$2:$N$4000, "<=31/10/2025"), COUNTIFS('Fernando Diamantino'!$E$2:$E$1999, "Prospecção Individual", 'Fernando Diamantino'!$G$2:$G$1999, "Desistência", 'Fernando Diamantino'!$N$2:$N$1999, ">=01/10/2025", 'Fernando Diamantino'!$N$2:$N$1999, "<=31/10/2025"), COUNTIFS('Maiara Andrade'!$E$2:$E$4000, "Prospecção Individual", 'Maiara Andrade'!$G$2:$G$4000, "Desistência", 'Maiara Andrade'!$N$2:$N$4000, ">=01/10/2025", 'Maiara Andrade'!$N$2:$N$4000, "<=31/10/2025"), COUNTIFS('Roberto Ramos'!$E$2:$E$4000, "Prospecção Individual", 'Roberto Ramos'!$G$2:$G$4000, "Desistência", 'Roberto Ramos'!$N$2:$N$4000, ">=01/10/2025", 'Roberto Ramos'!$N$2:$N$4000, "<=31/10/2025"), COUNTIFS('Amanda Facundo'!$E$2:$E$1999, "Prospecção Individual", 'Amanda Facundo'!$G$2:$G$1999, "Desistência", 'Amanda Facundo'!$N$2:$N$1999, ">=01/10/2025", 'Amanda Facundo'!$N$2:$N$1999, "<=31/10/2025"), COUNTIFS('Rodrigo Oliveira'!$E$2:$E$4000, "Prospecção Individual", 'Rodrigo Oliveira'!$G$2:$G$4000, "Desistência", 'Rodrigo Oliveira'!$N$2:$N$4000, ">=01/10/2025", 'Rodrigo Oliveira'!$N$2:$N$4000, "<=31/10/2025"), COUNTIFS('Marcio Jorge'!$E$2:$E$4000, "Prospecção Individual", 'Marcio Jorge'!$G$2:$G$4000, "Desistência", 'Marcio Jorge'!$N$2:$N$4000, ">=01/10/2025", 'Marcio Jorge'!$N$2:$N$4000, "<=31/10/2025") ) -> 2 | AW39: =SUM( COUNTIFS('Bruna Mamedes'!$E$2:$E$4000, "Prospecção Individual", 'Bruna Mamedes'!$G$2:$G$4000, "Não Respondeu", 'Bruna Mamedes'!$N$2:$N$4000, ">=01/10/2025", 'Bruna Mamedes'!$N$2:$N$4000, "<=31/10/2025"), COUNTIFS('Camila Adão'!$E$2:$E$1997, "Prospecção Individual", 'Camila Adão'!$G$2:$G$1997, "Não Respondeu", 'Camila Adão'!$N$2:$N$1997, ">=01/10/2025", 'Camila Adão'!$N$2:$N$1997, "<=31/10/2025"), COUNTIFS('Vendas Organicas'!$E$2:$E$3000, "Prospecção Individual", 'Vendas Organicas'!$G$2:$G$3000, "Não Respondeu", 'Vendas Organicas'!$N$2:$N$3000, ">=01/10/2025", 'Vendas Organicas'!$N$2:$N$3000, "<=31/10/2025"), COUNTIFS('Diogo Lima'!$E$2:$E$1996, "Prospecção Individual", 'Diogo Lima'!$G$2:$G$1996, "Não Respondeu", 'Diogo Lima'!$N$2:$N$1996, ">=01/10/2025", 'Diogo Lima'!$N$2:$N$1996, "<=31/10/2025"), COUNTIFS('Lucas Almeida'!$E$2:$E$4000, "Prospecção Individual", 'Lucas Almeida'!$G$2:$G$4000, "Não Respondeu", 'Lucas Almeida'!$N$2:$N$4000, ">=01/10/2025", 'Lucas Almeida'!$N$2:$N$4000, "<=31/10/2025"), COUNTIFS('Fernando Diamantino'!$E$2:$E$1999, "Prospecção Individual", 'Fernando Diamantino'!$G$2:$G$1999, "Não Respondeu", 'Fernando Diamantino'!$N$2:$N$1999, ">=01/10/2025", 'Fernando Diamantino'!$N$2:$N$1999, "<=31/10/2025"), COUNTIFS('Maiara Andrade'!$E$2:$E$4000, "Prospecção Individual", 'Maiara Andrade'!$G$2:$G$4000, "Não Respondeu", 'Maiara Andrade'!$N$2:$N$4000, ">=01/10/2025", 'Maiara Andrade'!$N$2:$N$4000, "<=31/10/2025"), COUNTIFS('Roberto Ramos'!$E$2:$E$4000, "Prospecção Individual", 'Roberto Ramos'!$G$2:$G$4000, "Não Respondeu", 'Roberto Ramos'!$N$2:$N$4000, ">=01/10/2025", 'Roberto Ramos'!$N$2:$N$4000, "<=31/10/2025"), COUNTIFS('Amanda Facundo'!$E$2:$E$1999, "Prospecção Individual", 'Amanda Facundo'!$G$2:$G$1999, "Não Respondeu", 'Amanda Facundo'!$N$2:$N$1999, ">=01/10/2025", 'Amanda Facundo'!$N$2:$N$1999, "<=31/10/2025"), COUNTIFS('Rodrigo Oliveira'!$E$2:$E$4000, "Prospecção Individual", 'Rodrigo Oliveira'!$G$2:$G$4000, "Não Respondeu", 'Rodrigo Oliveira'!$N$2:$N$4000, ">=01/10/2025", 'Rodrigo Oliveira'!$N$2:$N$4000, "<=31/10/2025"), COUNTIFS('Marcio Jorge'!$E$2:$E$4000, "Prospecção Individual", 'Marcio Jorge'!$G$2:$G$4000, "Não Respondeu", 'Marcio Jorge'!$N$2:$N$4000, ">=01/10/2025", 'Marcio Jorge'!$N$2:$N$4000, "<=31/10/2025") ) -> 0 | AX39: =SUM( SUMIFS('Bruna Mamedes'!$H$2:$H$4000, 'Bruna Mamedes'!$E$2:$E$4000, "Prospecção Individual", 'Bruna Mamedes'!$G$2:$G$4000, "Plano Fechado", 'Bruna Mamedes'!$N$2:$N$4000, ">=01/10/2025", 'Bruna Mamedes'!$N$2:$N$4000, "<=31/10/2025"), SUMIFS('Camila Adão'!$H$2:$H$1997, 'Camila Adão'!$E$2:$E$1997, "Prospecção Individual", 'Camila Adão'!$G$2:$G$1997, "Plano Fechado", 'Camila Adão'!$N$2:$N$1997, ">=01/10/2025", 'Camila Adão'!$N$2:$N$1997, "<=31/10/2025"), SUMIFS('Vendas Organicas'!$H$2:$H$3000, 'Vendas Organicas'!$E$2:$E$3000, "Prospecção Individual", 'Vendas Organicas'!$G$2:$G$3000, "Plano Fechado", 'Vendas Organicas'!$N$2:$N$3000, ">=01/10/2025", 'Vendas Organicas'!$N$2:$N$3000, "<=31/10/2025"), SUMIFS('Diogo Lima'!$H$2:$H$1996, 'Diogo Lima'!$E$2:$E$1996, "Prospecção Individual", 'Diogo Lima'!$G$2:$G$1996, "Plano Fechado", 'Diogo Lima'!$N$2:$N$1996, ">=01/10/2025", 'Diogo Lima'!$N$2:$N$1996, "<=31/10/2025"), SUMIFS('Lucas Almeida'!$H$2:$H$4000, 'Lucas Almeida'!$E$2:$E$4000, "Prospecção Individual", 'Lucas Almeida'!$G$2:$G$4000, "Plano Fechado", 'Lucas Almeida'!$N$2:$N$4000, ">=01/10/2025", 'Lucas Almeida'!$N$2:$N$4000, "<=31/10/2025"), SUMIFS('Fernando Diamantino'!$H$2:$H$1999, 'Fernando Diamantino'!$E$2:$E$1999, "Prospecção Individual", 'Fernando Diamantino'!$G$2:$G$1999, "Plano Fechado", 'Fernando Diamantino'!$N$2:$N$1999, ">=01/10/2025", 'Fernando Diamantino'!$N$2:$N$1999, "<=31/10/2025"), SUMIFS('Maiara Andrade'!$H$2:$H$4000, 'Maiara Andrade'!$E$2:$E$4000, "Prospecção Individual", 'Maiara Andrade'!$G$2:$G$4000, "Plano Fechado", 'Maiara Andrade'!$N$2:$N$4000, ">=01/10/2025", 'Maiara Andrade'!$N$2:$N$4000, "<=31/10/2025"), SUMIFS('Roberto Ramos'!$H$2:$H$4000, 'Roberto Ramos'!$E$2:$E$4000, "Prospecção Individual", 'Roberto Ramos'!$G$2:$G$4000, "Plano Fechado", 'Roberto Ramos'!$N$2:$N$4000, ">=01/10/2025", 'Roberto Ramos'!$N$2:$N$4000, "<=31/10/2025"), SUMIFS('Amanda Facundo'!$H$2:$H$1999, 'Amanda Facundo'!$E$2:$E$1999, "Prospecção Individual", 'Amanda Facundo'!$G$2:$G$1999, "Plano Fechado", 'Amanda Facundo'!$N$2:$N$1999, ">=01/10/2025", 'Amanda Facundo'!$N$2:$N$1999, "<=31/10/2025"), SUMIFS('Rodrigo Oliveira'!$H$2:$H$4000, 'Rodrigo Oliveira'!$E$2:$E$4000, "Prospecção Individual", 'Rodrigo Oliveira'!$G$2:$G$4000, "Plano Fechado", 'Rodrigo Oliveira'!$N$2:$N$4000, ">=01/10/2025", 'Rodrigo Oliveira'!$N$2:$N$4000, "<=31/10/2025"), SUMIFS('Marcio Jorge'!$H$2:$H$4000, 'Marcio Jorge'!$E$2:$E$4000, "Prospecção Individual", 'Marcio Jorge'!$G$2:$G$4000, "Plano Fechado", 'Marcio Jorge'!$N$2:$N$4000, ">=01/10/2025", 'Marcio Jorge'!$N$2:$N$4000, "<=31/10/2025") ) -> 9379.11
S40: 0.727 | T40: 0.182 | U40: 0.091 | V40: 0 | W40: 0 | AA40: 0.625 | AB40: 0 | AC40: 0.125 | AD40: 0.25 | AE40: 0 | AI40: 0.692 | AJ40: 0.077 | AK40: 0.077 | AL40: 0.077 | AM40: 0 | AQ40: =(AQ39/AP39) -> 0.38888889 | AR40: =(AR39/AP39) -> 0.11111111 | AS40: =(AS39/AP39) -> 0.055555556 | AT40: =(AT39/AP39) -> 0 | AU40: =AU39/AP39 -> 0 | AV40: =AV39/AP39 -> 0.11111111 | AW40: =AW39/AP39 -> 0
R42: LEADS DO REMARKETING | Z42: LEADS DO REMARKETING | AH42: LEADS DO REMARKETING | AP42: LEADS DO REMARKETING
R43: QTD. Leads | S43: Vendas Fechadas | T43: Leads em Conversação | U43: Leads com Proposta Enviada | V43: Leads Desistentes | W43: Leads sem Resposta | X43: Faturamento | Z43: QTD. Leads | AA43: Vendas Fechadas | AB43: Leads em Conversação | AC43: Leads com Proposta Enviada | AD43: Leads Desistentes | AE43: Leads sem Resposta | AF43: Faturamento | AH43: QTD. Leads | AI43: Vendas Fechadas | AJ43: Leads em Conversação | AK43: Leads com Proposta Enviada | AL43: Leads Desistentes | AM43: Leads sem Resposta | AN43: Faturamento | AP43: QTD. Leads | AQ43: Plano Fechado | AR43: Em Análise | AS43: Aguardando Pagamento | AT43: Conversação | AU43: Proposta Enviada | AV43: Desistentes | AW43: Sem Resposta | AX43: Faturamento
